Workbook
Name Dia_Firma: #REF!

Sheet Cálculo pagos
B2: Préstamo | C2: 100000
B3: Interés ordinario | C3: 0.12
B4: Intereses anuales | C4: =C2*C3 -> 12000
B5: Intereses mensuales (habitual) | C5: =C4/12 -> 1000
B7: Participación | C7: 20000
B8: % participación | C8: =C7/C2 -> 0.2
B9: Factor de este mes | C9: 1 | D9: Este factor responde a la cantidad de días que hay que pagar (puede ser distinto de 1 en los 2 primeros pagos)
B10: Devengado mensual habitual | C10: =C5*C8*C9 -> 200
B11: % gestión | C11: 0.02
B12: Gestión | C12: =C7*C11/12*C9 -> 33.333333
B13: Bruto | C13: =C10-C12 -> 166.66667
B14: % IRPF | C14: 0.19
B15: IRPF | C15: =C13*19% -> 31.666667
B16: Neto | C16: =C13-C15 -> 135
B18: Rentabilidad anualizada partícipe | C18: =C13*12/C7 -> 0.1

Sheet Dashboard
F1: Activo | G1: Judicializado
B2: En curso | C2: =F2+G2 -> 2781010 | F2: =SUMIFS(T_Prestamos[Importe],T_Prestamos[Situación],"Activos") -> 2690710 | G2: =SUMIFS(T_Prestamos[Importe],T_Prestamos[Situación],"Judicializados") -> 90300
B3: Activo | C3: =F3+G3 -> 2656056.3 | F3: =SUMIFS(T_Prestamos[Pendiente],T_Prestamos[Situación],"Activos") -> 2597747.2 | G3: =SUMIFS(T_Prestamos[Pendiente],T_Prestamos[Situación],"Judicializados") -> 58309.061 | K3: Desplegadas
B4: Participado | C4: =F4+G4 -> 1475000 | D4: =F4/C3 -> 0.55533462 | F4: 1475000 | K4: En Curso
B5: Promocima (Activo) | C5: =F5+G5 -> 1181056.3 | D5: =C5/C3 -> 0.44466538 | F5: =F3-F4 -> 1122747.2 | G5: =G3-G4 -> 58309.061 | K5: Activas
A6: 2026 | B6: Intereses | F6: =SUMIFS(T_Prestamos[Int. Anual],T_Prestamos[Situación],"Activos") -> 289988.83 | K6: Al día
B7: Rentabilidad media | F7: =F6/F3 -> 0.11163089 | K7: Con retraso
B8: Intereses partícipes | F8: =SUM(T_Participaciones[Intereses]) -> 165758.75 | K8: Judicializadas
B9: Rent. Partícipes | F9: =F8/F4 -> 0.11237881 | K9: Canceladas
B10: Ingresos gestión | F10: =SUMIFS(T_Participaciones[Gestión],T_Participaciones[Situación],"Activa") -> 28500
B11: Ingresos Promocima | F11: =F6-F8+F10 -> 152730.08
B12: Rent. Promocima | F12: =F11/F5 -> 0.13603247
B13: Apertura LTM | F13: =SUM(T_Prestamos[Aperturas LTM]) -> 25612.225
B14: Papertura LTM Participada | F14: =SUM(T_Participaciones[Apertura LTM]) -> 1000
B16: KPI 1 | E16: KPI 2 | H16: KPI 3 | K16: KPI 4 | N16: KPI 5
B17: En cruso | C17: =C2 -> 2781010 | E17: Ingresos Anuales op. Activas | F17: =F6 -> 289988.83 | H17: Operaciones Totales | I17: =COUNT(T_Prestamos[Centro coste]) -> 65 | K17: Total Garantías op en curso | L17: =SUMIFS(T_Prestamos[Garantía],T_Prestamos[Situación],"Activos")+SUMIFS(T_Prestamos[Garantía],T_Prestamos[Situación],"Judicializados") -> 10924830 | N17: Duración media op en curso | O17: =(SUMIFS(T_Prestamos[Duración],T_Prestamos[Situación],"Activos")+SUMIFS(T_Prestamos[Duración],T_Prestamos[Situación],"Judicializados"))/(COUNTIFS(T_Prestamos[Situación],"Activos")+COUNTIFS(T_Prestamos[Situación],"Judicializados")) -> 1342.7692
B18: Activo | C18: =F3 -> 2597747.2 | E18: Ingresos Anuales part. Activas | F18: =F8 -> 165758.75 | H18: Operaciones Canceladas | I18: =COUNTIFS(T_Prestamos[Situación],"Cancelados") -> 39 | K18: LTV op vivas | L18: =C2/L17 -> 0.25455866 | N18: Duración media op canceladas | O18: =SUMIFS(T_Prestamos[Duración],T_Prestamos[Situación],"Cancelados")/COUNTIFS(T_Prestamos[Situación],"Cancelados") -> 721.25641
B19: Judicializado | C19: =G3 -> 58309.061 | E19: Ingresos Promocima Gestión | F19: =F10 -> 28500 | H19: Operaciones En curso | I19: =I17-I18 -> 26 | K19: Total garantías partícipes | L19: =SUM(T_Participaciones[Garantía]) -> 6091055.9 | N19: Duración media op activas | O19: =SUMIFS(T_Prestamos[Duración],T_Prestamos[Situación],"Activos")/COUNTIFS(T_Prestamos[Situación],"Activos") -> 1120.0455
B20: % judicializado | C20: =C19/C17 -> 0.020966865 | E20: Ingresos Apert. Promocima (Últimos 12 meses) | F20: =F13-F14 -> 24612.225 | H20: Operaciones Judicializadas | I20: =COUNTIFS(T_Prestamos[Situación],"Judicializados") -> 4 | K20: LTV op participadas | L20: =F4/L19 -> 0.24215834 | N20: Duración media op judicializadas | O20: =SUMIFS(T_Prestamos[Duración],T_Prestamos[Situación],"Judicializados")/COUNTIFS(T_Prestamos[Situación],"Judicializados") -> 2567.75
B21: Participado Activo | C21: =F4 -> 1475000 | E21: Rentabilidad Activas | F21: =F17/C18 -> 0.11163089 | H21: Operaciones Activas | I21: =COUNTIFS(T_Prestamos[Situación],"Activos") -> 22
B22: Participado Judicializado | C22: =G4 -> 0 | E22: Rentabilidad Partícipes | F22: =F8/F4 -> 0.11237881 | H22: Operaciones Al día
B23: % Judic. Partícipes | C23: =C22/C21 -> 0 | E23: Rentabilidad Total Promocima | F23: =(F17-F18+F19+F20)/F5 -> 0.1579539 | H23: Operaciones Con retraso
E26: En curso | F26: 2672058
E27: Activas | F27: 2598162
E28: Rentabilidad | F28: 289444
E29: Gestión | F29: 28500
E30: Apertura | F30: 25612
E31: Rent op activas | F31: =F28/F27 -> 0.11140337
E32: OJO, el calcula esto | F32: =F28/F26 -> 0.1083225
E34: Participadas | F34: 1475000
E35: Rentabil. Partícipes | F35: 165759
E36: Rent. Part. | F36: =F35/F34 -> 0.11237898
E37: Rent tot. Promocima | F37: =(F28-F35+F29+F30)/(F27-F34) -> 0.15830041
E39: Garantías | F39: 10003131
E40: LTV op.activas | F40: =F26/F39 -> 0.26712216
E41: Garantías participadas | F41: 5371230
E42: LTV op.activas | F42: =F34/F41 -> 0.27461122

Sheet Tabla Préstamos
B2: =COLUMN()-1 -> 1 | C2: =COLUMN()-1 -> 2 | D2: =COLUMN()-1 -> 3 | E2: =COLUMN()-1 -> 4 | F2: =COLUMN()-1 -> 5 | G2: =COLUMN()-1 -> 6 | H2: =COLUMN()-1 -> 7 | I2: =COLUMN()-1 -> 8 | ... O2: =COLUMN()-1 -> 14 | Q2: =COLUMN()-1 -> 16 | R2: =COLUMN()-1 -> 17 | S2: =COLUMN()-1 -> 18 | T2: =COLUMN()-1 -> 19 | U2: =COLUMN()-1 -> 20 | V2: =COLUMN()-1 -> 21 | W2: =COLUMN()-1 -> 22 | X2: =COLUMN()-1 -> 23 | Z2: =COLUMN()-1 -> 25 | AA2: =COLUMN()-1 -> 26
B3: Créditos activos
B4: Centro coste | C4: Nombre | D4: firma préstamo | E4: Años | F4: Importe | G4: % interés ordinario | H4: % interés demora | I4: Garantía | J4: LTV vs Pendiente | K4: Destinatario | L4: Tipo préstamo | M4: Intermediario | N4: Situación | O4: Fecha cancelación | P4: Importe retraso | Q4: Duración | R4: Meses | S4: Pendiente | T4: Intereses anuales | U4: % apertura | V4: Apertura | W4: Observaciones | X4: Prestatario | Y4: Primera cuota año | Z4: Int. Anual | AA4: Aperturas LTM
B5: 2001 | C5: Préstamo Peinado Vives | D5: 42883 | E5: 10 | F5: 28500 | G5: 0.12 | H5: 0.12 | J5: =IF(T_Prestamos[[#This Row],[Garantía]]="","",T_Prestamos[[#This Row],[Pendiente]]/T_Prestamos[[#This Row],[Garantía]]) | K5: Física | L5: Francés | M5: Silex | N5: Cancelados | O5: 45770 | Q5: =IF(T_Prestamos[[#This Row],[Situación]]="Cancelados",T_Prestamos[[#This Row],[Fecha cancelación]],TODAY())-T_Prestamos[[#This Row],[firma préstamo]] -> 2887 | R5: =IF(T_Prestamos[[#This Row],[Situación]]="Cancelada","",DATEDIF(T_Prestamos[[#This Row],[firma préstamo]],TODAY(),"m")) -> 105 | S5: =IF(T_Prestamos[[#This Row],[Situación]]="Cancelados",0,IF(T_Prestamos[[#This Row],[Tipo préstamo]]="Americano",T_Prestamos[[#This Row],[Importe]],T_Prestamos[[#This Row],[Importe]]+CUMPRINC(G5/12,E5*12,F5,1,R5,0))) -> 0 | T5: =IF(T_Prestamos[[#This Row],[Situación]]="Cancelados",0,IF(T_Prestamos[[#This Row],[Tipo préstamo]]="Americano",T_Prestamos[[#This Row],[Pendiente]]*T_Prestamos[[#This Row],[% interés ordinario]],-CUMIPMT(G5/12,E5*12,F5,R5,R5+11,0))) -> 0 | U5: 0 | V5: =T_Prestamos[[#This Row],[% apertura]]*T_Prestamos[[#This Row],[Importe]] -> 0 | Y5: =IF(T_Prestamos[[#This Row],[Situación]]="Activos",IF(T_Prestamos[[#This Row],[Tipo préstamo]]="Francés",DATEDIF(T_Prestamos[[#This Row],[firma préstamo]],DATE(YEAR(TODAY()),1,1),"m"),0),0) -> 0 | Z5: =IF(T_Prestamos[[#This Row],[Situación]]="Activos",IF(T_Prestamos[[#This Row],[Tipo préstamo]]="Americano",T_Prestamos[[#This Row],[Importe]]*T_Prestamos[[#This Row],[% interés ordinario]],-CUMIPMT(T_Prestamos[[#This Row],[% interés ordinario]]/12,T_Prestamos[[#This Row],[Años]]*12,T_Prestamos[[#This Row],[Importe]],T_Prestamos[[#This Row],[Primera cuota año]],T_Prestamos[[#This Row],[Primera cuota año]]+11,0)),0) -> 0 | AA5: =IF(T_Prestamos[[#This Row],[firma préstamo]]>DATE(YEAR(TODAY())-1,MONTH(TODAY()),DAY(TODAY())),T_Prestamos[[#This Row],[Importe]]*T_Prestamos[[#This Row],[% apertura]],0) -> 0
B6: 2002 | C6: Présamo Panadero Hinarejos | D6: 43003 | E6: 11 | F6: 47500 | G6: 0.125 | H6: 0.145 | J6: =IF(T_Prestamos[[#This Row],[Garantía]]="","",T_Prestamos[[#This Row],[Pendiente]]/T_Prestamos[[#This Row],[Garantía]]) | K6: Física | L6: Francés | M6: Silex | N6: Cancelados | O6: 43532 | Q6: =IF(T_Prestamos[[#This Row],[Situación]]="Cancelados",T_Prestamos[[#This Row],[Fecha cancelación]],TODAY())-T_Prestamos[[#This Row],[firma préstamo]] -> 529 | R6: =IF(T_Prestamos[[#This Row],[Situación]]="Cancelada","",DATEDIF(T_Prestamos[[#This Row],[firma préstamo]],TODAY(),"m")) -> 101 | S6: =IF(T_Prestamos[[#This Row],[Situación]]="Cancelados",0,IF(T_Prestamos[[#This Row],[Tipo préstamo]]="Americano",T_Prestamos[[#This Row],[Importe]],T_Prestamos[[#This Row],[Importe]]+CUMPRINC(G6/12,E6*12,F6,1,R6,0))) -> 0 | T6: =IF(T_Prestamos[[#This Row],[Situación]]="Cancelados",0,IF(T_Prestamos[[#This Row],[Tipo préstamo]]="Americano",T_Prestamos[[#This Row],[Pendiente]]*T_Prestamos[[#This Row],[% interés ordinario]],-CUMIPMT(G6/12,E6*12,F6,R6,R6+11,0))) -> 0 | U6: 0 | V6: =T_Prestamos[[#This Row],[% apertura]]*T_Prestamos[[#This Row],[Importe]] -> 0 | Y6: =IF(T_Prestamos[[#This Row],[Situación]]="Activos",IF(T_Prestamos[[#This Row],[Tipo préstamo]]="Francés",DATEDIF(T_Prestamos[[#This Row],[firma préstamo]],DATE(YEAR(TODAY()),1,1),"m"),0),0) -> 0 | Z6: =IF(T_Prestamos[[#This Row],[Situación]]="Activos",IF(T_Prestamos[[#This Row],[Tipo préstamo]]="Americano",T_Prestamos[[#This Row],[Importe]]*T_Prestamos[[#This Row],[% interés ordinario]],-CUMIPMT(T_Prestamos[[#This Row],[% interés ordinario]]/12,T_Prestamos[[#This Row],[Años]]*12,T_Prestamos[[#This Row],[Importe]],T_Prestamos[[#This Row],[Primera cuota año]],T_Prestamos[[#This Row],[Primera cuota año]]+11,0)),0) -> 0 | AA6: =IF(T_Prestamos[[#This Row],[firma préstamo]]>DATE(YEAR(TODAY())-1,MONTH(TODAY()),DAY(TODAY())),T_Prestamos[[#This Row],[Importe]]*T_Prestamos[[#This Row],[% apertura]],0) -> 0
B7: 2003 | C7: Préstamo Carlos Santiago Reyes | D7: 43041 | E7: 10 | F7: 45000 | G7: 0.125 | H7: =T_Prestamos[[#This Row],[% interés ordinario]]+3% -> 0.155 | J7: =IF(T_Prestamos[[#This Row],[Garantía]]="","",T_Prestamos[[#This Row],[Pendiente]]/T_Prestamos[[#This Row],[Garantía]]) | K7: Física | L7: Francés | M7: Silex | N7: Cancelados | O7: 44542 | Q7: =IF(T_Prestamos[[#This Row],[Situación]]="Cancelados",T_Prestamos[[#This Row],[Fecha cancelación]],TODAY())-T_Prestamos[[#This Row],[firma préstamo]] -> 1501 | R7: =IF(T_Prestamos[[#This Row],[Situación]]="Cancelada","",DATEDIF(T_Prestamos[[#This Row],[firma préstamo]],TODAY(),"m")) -> 100 | S7: =IF(T_Prestamos[[#This Row],[Situación]]="Cancelados",0,IF(T_Prestamos[[#This Row],[Tipo préstamo]]="Americano",T_Prestamos[[#This Row],[Importe]],T_Prestamos[[#This Row],[Importe]]+CUMPRINC(G7/12,E7*12,F7,1,R7,0))) -> 0 | T7: =IF(T_Prestamos[[#This Row],[Situación]]="Cancelados",0,IF(T_Prestamos[[#This Row],[Tipo préstamo]]="Americano",T_Prestamos[[#This Row],[Pendiente]]*T_Prestamos[[#This Row],[% interés ordinario]],-CUMIPMT(G7/12,E7*12,F7,R7,R7+11,0))) -> 0 | U7: 0 | V7: =T_Prestamos[[#This Row],[% apertura]]*T_Prestamos[[#This Row],[Importe]] -> 0 | Y7: =IF(T_Prestamos[[#This Row],[Situación]]="Activos",IF(T_Prestamos[[#This Row],[Tipo préstamo]]="Francés",DATEDIF(T_Prestamos[[#This Row],[firma préstamo]],DATE(YEAR(TODAY()),1,1),"m"),0),0) -> 0 | Z7: =IF(T_Prestamos[[#This Row],[Situación]]="Activos",IF(T_Prestamos[[#This Row],[Tipo préstamo]]="Americano",T_Prestamos[[#This Row],[Importe]]*T_Prestamos[[#This Row],[% interés ordinario]],-CUMIPMT(T_Prestamos[[#This Row],[% interés ordinario]]/12,T_Prestamos[[#This Row],[Años]]*12,T_Prestamos[[#This Row],[Importe]],T_Prestamos[[#This Row],[Primera cuota año]],T_Prestamos[[#This Row],[Primera cuota año]]+11,0)),0) -> 0 | AA7: =IF(T_Prestamos[[#This Row],[firma préstamo]]>DATE(YEAR(TODAY())-1,MONTH(TODAY()),DAY(TODAY())),T_Prestamos[[#This Row],[Importe]]*T_Prestamos[[#This Row],[% apertura]],0) -> 0
B8: 2004 | C8: Las Palmas de GC - Persona física | D8: 43040 | E8: 10 | F8: 24000 | G8: 0.15 | H8: 0.17 | I8: 91577 | J8: =IF(T_Prestamos[[#This Row],[Garantía]]="","",T_Prestamos[[#This Row],[Pendiente]]/T_Prestamos[[#This Row],[Garantía]]) -> 0.074413049 | K8: Física | L8: Francés | M8: Silex | N8: Activos | Q8: =IF(T_Prestamos[[#This Row],[Situación]]="Cancelados",T_Prestamos[[#This Row],[Fecha cancelación]],TODAY())-T_Prestamos[[#This Row],[firma préstamo]] -> 3056 | R8: =IF(T_Prestamos[[#This Row],[Situación]]="Cancelada","",DATEDIF(T_Prestamos[[#This Row],[firma préstamo]],TODAY(),"m")) -> 100 | S8: =IF(T_Prestamos[[#This Row],[Situación]]="Cancelados",0,IF(T_Prestamos[[#This Row],[Tipo préstamo]]="Americano",T_Prestamos[[#This Row],[Importe]],T_Prestamos[[#This Row],[Importe]]+CUMPRINC(G8/12,E8*12,F8,1,R8,0))) -> 6814.5238 | T8: =IF(T_Prestamos[[#This Row],[Situación]]="Cancelados",0,IF(T_Prestamos[[#This Row],[Tipo préstamo]]="Americano",T_Prestamos[[#This Row],[Pendiente]]*T_Prestamos[[#This Row],[% interés ordinario]],-CUMIPMT(G8/12,E8*12,F8,R8,R8+11,0))) -> 810.28225 | U8: 0 | V8: =T_Prestamos[[#This Row],[% apertura]]*T_Prestamos[[#This Row],[Importe]] -> 0 | X8: Domingo Juan Santana Araya | Y8: =IF(T_Prestamos[[#This Row],[Situación]]="Activos",IF(T_Prestamos[[#This Row],[Tipo préstamo]]="Francés",DATEDIF(T_Prestamos[[#This Row],[firma préstamo]],DATE(YEAR(TODAY()),1,1),"m"),0),0) -> 98 | Z8: =IF(T_Prestamos[[#This Row],[Situación]]="Activos",IF(T_Prestamos[[#This Row],[Tipo préstamo]]="Americano",T_Prestamos[[#This Row],[Importe]]*T_Prestamos[[#This Row],[% interés ordinario]],-CUMIPMT(T_Prestamos[[#This Row],[% interés ordinario]]/12,T_Prestamos[[#This Row],[Años]]*12,T_Prestamos[[#This Row],[Importe]],T_Prestamos[[#This Row],[Primera cuota año]],T_Prestamos[[#This Row],[Primera cuota año]]+11,0)),0) -> 904.41767 | AA8: =IF(T_Prestamos[[#This Row],[firma préstamo]]>DATE(YEAR(TODAY())-1,MONTH(TODAY()),DAY(TODAY())),T_Prestamos[[#This Row],[Importe]]*T_Prestamos[[#This Row],[% apertura]],0) -> 0
B9: 2005 | C9: Préstamo Juan Melchor Torrens Pou | D9: 43054 | E9: 1 | F9: 14500 | G9: 0.15 | H9: 0.17 | J9: =IF(T_Prestamos[[#This Row],[Garantía]]="","",T_Prestamos[[#This Row],[Pendiente]]/T_Prestamos[[#This Row],[Garantía]]) | K9: Física | L9: Francés | M9: Silex | N9: Cancelados | O9: 43496 | Q9: =IF(T_Prestamos[[#This Row],[Situación]]="Cancelados",T_Prestamos[[#This Row],[Fecha cancelación]],TODAY())-T_Prestamos[[#This Row],[firma préstamo]] -> 442 | R9: =IF(T_Prestamos[[#This Row],[Situación]]="Cancelada","",DATEDIF(T_Prestamos[[#This Row],[firma préstamo]],TODAY(),"m")) -> 100 | S9: =IF(T_Prestamos[[#This Row],[Situación]]="Cancelados",0,IF(T_Prestamos[[#This Row],[Tipo préstamo]]="Americano",T_Prestamos[[#This Row],[Importe]],T_Prestamos[[#This Row],[Importe]]+CUMPRINC(G9/12,E9*12,F9,1,R9,0))) -> 0 | T9: =IF(T_Prestamos[[#This Row],[Situación]]="Cancelados",0,IF(T_Prestamos[[#This Row],[Tipo préstamo]]="Americano",T_Prestamos[[#This Row],[Pendiente]]*T_Prestamos[[#This Row],[% interés ordinario]],-CUMIPMT(G9/12,E9*12,F9,R9,R9+11,0))) -> 0 | U9: 0 | V9: =T_Prestamos[[#This Row],[% apertura]]*T_Prestamos[[#This Row],[Importe]] -> 0 | Y9: =IF(T_Prestamos[[#This Row],[Situación]]="Activos",IF(T_Prestamos[[#This Row],[Tipo préstamo]]="Francés",DATEDIF(T_Prestamos[[#This Row],[firma préstamo]],DATE(YEAR(TODAY()),1,1),"m"),0),0) -> 0 | Z9: =IF(T_Prestamos[[#This Row],[Situación]]="Activos",IF(T_Prestamos[[#This Row],[Tipo préstamo]]="Americano",T_Prestamos[[#This Row],[Importe]]*T_Prestamos[[#This Row],[% interés ordinario]],-CUMIPMT(T_Prestamos[[#This Row],[% interés ordinario]]/12,T_Prestamos[[#This Row],[Años]]*12,T_Prestamos[[#This Row],[Importe]],T_Prestamos[[#This Row],[Primera cuota año]],T_Prestamos[[#This Row],[Primera cuota año]]+11,0)),0) -> 0 | AA9: =IF(T_Prestamos[[#This Row],[firma préstamo]]>DATE(YEAR(TODAY())-1,MONTH(TODAY()),DAY(TODAY())),T_Prestamos[[#This Row],[Importe]]*T_Prestamos[[#This Row],[% apertura]],0) -> 0
B10: 2006 | C10: Préstamo Juliana Joval Esque | D10: 43055 | E10: 10 | F10: 13000 | G10: 0.15 | H10: 0.17 | J10: =IF(T_Prestamos[[#This Row],[Garantía]]="","",T_Prestamos[[#This Row],[Pendiente]]/T_Prestamos[[#This Row],[Garantía]]) | K10: Física | L10: Francés | M10: Silex | N10: Cancelados | O10: 45188 | Q10: =IF(T_Prestamos[[#This Row],[Situación]]="Cancelados",T_Prestamos[[#This Row],[Fecha cancelación]],TODAY())-T_Prestamos[[#This Row],[firma préstamo]] -> 2133 | R10: =IF(T_Prestamos[[#This Row],[Situación]]="Cancelada","",DATEDIF(T_Prestamos[[#This Row],[firma préstamo]],TODAY(),"m")) -> 99 | S10: =IF(T_Prestamos[[#This Row],[Situación]]="Cancelados",0,IF(T_Prestamos[[#This Row],[Tipo préstamo]]="Americano",T_Prestamos[[#This Row],[Importe]],T_Prestamos[[#This Row],[Importe]]+CUMPRINC(G10/12,E10*12,F10,1,R10,0))) -> 0 | T10: =IF(T_Prestamos[[#This Row],[Situación]]="Cancelados",0,IF(T_Prestamos[[#This Row],[Tipo préstamo]]="Americano",T_Prestamos[[#This Row],[Pendiente]]*T_Prestamos[[#This Row],[% interés ordinario]],-CUMIPMT(G10/12,E10*12,F10,R10,R10+11,0))) -> 0 | U10: 0 | V10: =T_Prestamos[[#This Row],[% apertura]]*T_Prestamos[[#This Row],[Importe]] -> 0 | Y10: =IF(T_Prestamos[[#This Row],[Situación]]="Activos",IF(T_Prestamos[[#This Row],[Tipo préstamo]]="Francés",DATEDIF(T_Prestamos[[#This Row],[firma préstamo]],DATE(YEAR(TODAY()),1,1),"m"),0),0) -> 0 | Z10: =IF(T_Prestamos[[#This Row],[Situación]]="Activos",IF(T_Prestamos[[#This Row],[Tipo préstamo]]="Americano",T_Prestamos[[#This Row],[Importe]]*T_Prestamos[[#This Row],[% interés ordinario]],-CUMIPMT(T_Prestamos[[#This Row],[% interés ordinario]]/12,T_Prestamos[[#This Row],[Años]]*12,T_Prestamos[[#This Row],[Importe]],T_Prestamos[[#This Row],[Primera cuota año]],T_Prestamos[[#This Row],[Primera cuota año]]+11,0)),0) -> 0 | AA10: =IF(T_Prestamos[[#This Row],[firma préstamo]]>DATE(YEAR(TODAY())-1,MONTH(TODAY()),DAY(TODAY())),T_Prestamos[[#This Row],[Importe]]*T_Prestamos[[#This Row],[% apertura]],0) -> 0
B11: 2007 | C11: Préstamo Mª Isabel González Sáres | D11: 43055 | E11: 5 | F11: 16500 | G11: 0.15 | H11: 0.17 | J11: =IF(T_Prestamos[[#This Row],[Garantía]]="","",T_Prestamos[[#This Row],[Pendiente]]/T_Prestamos[[#This Row],[Garantía]]) | K11: Física | L11: Francés | M11: Silex | N11: Cancelados | O11: 43171 | Q11: =IF(T_Prestamos[[#This Row],[Situación]]="Cancelados",T_Prestamos[[#This Row],[Fecha cancelación]],TODAY())-T_Prestamos[[#This Row],[firma préstamo]] -> 116 | R11: =IF(T_Prestamos[[#This Row],[Situación]]="Cancelada","",DATEDIF(T_Prestamos[[#This Row],[firma préstamo]],TODAY(),"m")) -> 99 | S11: =IF(T_Prestamos[[#This Row],[Situación]]="Cancelados",0,IF(T_Prestamos[[#This Row],[Tipo préstamo]]="Americano",T_Prestamos[[#This Row],[Importe]],T_Prestamos[[#This Row],[Importe]]+CUMPRINC(G11/12,E11*12,F11,1,R11,0))) -> 0 | T11: =IF(T_Prestamos[[#This Row],[Situación]]="Cancelados",0,IF(T_Prestamos[[#This Row],[Tipo préstamo]]="Americano",T_Prestamos[[#This Row],[Pendiente]]*T_Prestamos[[#This Row],[% interés ordinario]],-CUMIPMT(G11/12,E11*12,F11,R11,R11+11,0))) -> 0 | U11: 0 | V11: =T_Prestamos[[#This Row],[% apertura]]*T_Prestamos[[#This Row],[Importe]] -> 0 | Y11: =IF(T_Prestamos[[#This Row],[Situación]]="Activos",IF(T_Prestamos[[#This Row],[Tipo préstamo]]="Francés",DATEDIF(T_Prestamos[[#This Row],[firma préstamo]],DATE(YEAR(TODAY()),1,1),"m"),0),0) -> 0 | Z11: =IF(T_Prestamos[[#This Row],[Situación]]="Activos",IF(T_Prestamos[[#This Row],[Tipo préstamo]]="Americano",T_Prestamos[[#This Row],[Importe]]*T_Prestamos[[#This Row],[% interés ordinario]],-CUMIPMT(T_Prestamos[[#This Row],[% interés ordinario]]/12,T_Prestamos[[#This Row],[Años]]*12,T_Prestamos[[#This Row],[Importe]],T_Prestamos[[#This Row],[Primera cuota año]],T_Prestamos[[#This Row],[Primera cuota año]]+11,0)),0) -> 0 | AA11: =IF(T_Prestamos[[#This Row],[firma préstamo]]>DATE(YEAR(TODAY())-1,MONTH(TODAY()),DAY(TODAY())),T_Prestamos[[#This Row],[Importe]]*T_Prestamos[[#This Row],[% apertura]],0) -> 0
B12: 2008 | C12: Préstamo Vidal Yagüe - Ibiza | D12: 42797 | E12: 10 | F12: 26500 | G12: 0.15 | H12: 0.17 | J12: =IF(T_Prestamos[[#This Row],[Garantía]]="","",T_Prestamos[[#This Row],[Pendiente]]/T_Prestamos[[#This Row],[Garantía]]) | K12: Física | L12: Francés | M12: Silex | N12: Cancelados | O12: 43090 | Q12: =IF(T_Prestamos[[#This Row],[Situación]]="Cancelados",T_Prestamos[[#This Row],[Fecha cancelación]],TODAY())-T_Prestamos[[#This Row],[firma préstamo]] -> 293 | R12: =IF(T_Prestamos[[#This Row],[Situación]]="Cancelada","",DATEDIF(T_Prestamos[[#This Row],[firma préstamo]],TODAY(),"m")) -> 108 | S12: =IF(T_Prestamos[[#This Row],[Situación]]="Cancelados",0,IF(T_Prestamos[[#This Row],[Tipo préstamo]]="Americano",T_Prestamos[[#This Row],[Importe]],T_Prestamos[[#This Row],[Importe]]+CUMPRINC(G12/12,E12*12,F12,1,R12,0))) -> 0 | T12: =IF(T_Prestamos[[#This Row],[Situación]]="Cancelados",0,IF(T_Prestamos[[#This Row],[Tipo préstamo]]="Americano",T_Prestamos[[#This Row],[Pendiente]]*T_Prestamos[[#This Row],[% interés ordinario]],-CUMIPMT(G12/12,E12*12,F12,R12,R12+11,0))) -> 0 | U12: 0 | V12: =T_Prestamos[[#This Row],[% apertura]]*T_Prestamos[[#This Row],[Importe]] -> 0 | Y12: =IF(T_Prestamos[[#This Row],[Situación]]="Activos",IF(T_Prestamos[[#This Row],[Tipo préstamo]]="Francés",DATEDIF(T_Prestamos[[#This Row],[firma préstamo]],DATE(YEAR(TODAY()),1,1),"m"),0),0) -> 0 | Z12: =IF(T_Prestamos[[#This Row],[Situación]]="Activos",IF(T_Prestamos[[#This Row],[Tipo préstamo]]="Americano",T_Prestamos[[#This Row],[Importe]]*T_Prestamos[[#This Row],[% interés ordinario]],-CUMIPMT(T_Prestamos[[#This Row],[% interés ordinario]]/12,T_Prestamos[[#This Row],[Años]]*12,T_Prestamos[[#This Row],[Importe]],T_Prestamos[[#This Row],[Primera cuota año]],T_Prestamos[[#This Row],[Primera cuota año]]+11,0)),0) -> 0 | AA12: =IF(T_Prestamos[[#This Row],[firma préstamo]]>DATE(YEAR(TODAY())-1,MONTH(TODAY()),DAY(TODAY())),T_Prestamos[[#This Row],[Importe]]*T_Prestamos[[#This Row],[% apertura]],0) -> 0
B13: 2009 | C13: Préstamos Jaume Boixadós | D13: 42648 | E13: 3 | F13: 16000 | G13: 0.125 | H13: 0.125 | J13: =IF(T_Prestamos[[#This Row],[Garantía]]="","",T_Prestamos[[#This Row],[Pendiente]]/T_Prestamos[[#This Row],[Garantía]]) | K13: Física | L13: Americano | M13: Silex | N13: Cancelados | O13: 43586 | Q13: =IF(T_Prestamos[[#This Row],[Situación]]="Cancelados",T_Prestamos[[#This Row],[Fecha cancelación]],TODAY())-T_Prestamos[[#This Row],[firma préstamo]] -> 938 | R13: =IF(T_Prestamos[[#This Row],[Situación]]="Cancelada","",DATEDIF(T_Prestamos[[#This Row],[firma préstamo]],TODAY(),"m")) -> 113 | S13: =IF(T_Prestamos[[#This Row],[Situación]]="Cancelados",0,IF(T_Prestamos[[#This Row],[Tipo préstamo]]="Americano",T_Prestamos[[#This Row],[Importe]],T_Prestamos[[#This Row],[Importe]]+CUMPRINC(G13/12,E13*12,F13,1,R13,0))) -> 0 | T13: =IF(T_Prestamos[[#This Row],[Situación]]="Cancelados",0,IF(T_Prestamos[[#This Row],[Tipo préstamo]]="Americano",T_Prestamos[[#This Row],[Pendiente]]*T_Prestamos[[#This Row],[% interés ordinario]],-CUMIPMT(G13/12,E13*12,F13,R13,R13+11,0))) -> 0 | U13: 0 | V13: =T_Prestamos[[#This Row],[% apertura]]*T_Prestamos[[#This Row],[Importe]] -> 0 | Y13: =IF(T_Prestamos[[#This Row],[Situación]]="Activos",IF(T_Prestamos[[#This Row],[Tipo préstamo]]="Francés",DATEDIF(T_Prestamos[[#This Row],[firma préstamo]],DATE(YEAR(TODAY()),1,1),"m"),0),0) -> 0 | Z13: =IF(T_Prestamos[[#This Row],[Situación]]="Activos",IF(T_Prestamos[[#This Row],[Tipo préstamo]]="Americano",T_Prestamos[[#This Row],[Importe]]*T_Prestamos[[#This Row],[% interés ordinario]],-CUMIPMT(T_Prestamos[[#This Row],[% interés ordinario]]/12,T_Prestamos[[#This Row],[Años]]*12,T_Prestamos[[#This Row],[Importe]],T_Prestamos[[#This Row],[Primera cuota año]],T_Prestamos[[#This Row],[Primera cuota año]]+11,0)),0) -> 0 | AA13: =IF(T_Prestamos[[#This Row],[firma préstamo]]>DATE(YEAR(TODAY())-1,MONTH(TODAY()),DAY(TODAY())),T_Prestamos[[#This Row],[Importe]]*T_Prestamos[[#This Row],[% apertura]],0) -> 0
B14: 2010 | C14: Préstamo Jaume Solè Bardalet | D14: 43151 | E14: 1 | F14: 60375 | G14: 0.15 | H14: 0.17 | J14: =IF(T_Prestamos[[#This Row],[Garantía]]="","",T_Prestamos[[#This Row],[Pendiente]]/T_Prestamos[[#This Row],[Garantía]]) | K14: Física | L14: Francés | M14: Silex | N14: Cancelados | O14: 43742 | Q14: =IF(T_Prestamos[[#This Row],[Situación]]="Cancelados",T_Prestamos[[#This Row],[Fecha cancelación]],TODAY())-T_Prestamos[[#This Row],[firma préstamo]] -> 591 | R14: =IF(T_Prestamos[[#This Row],[Situación]]="Cancelada","",DATEDIF(T_Prestamos[[#This Row],[firma préstamo]],TODAY(),"m")) -> 96 | S14: =IF(T_Prestamos[[#This Row],[Situación]]="Cancelados",0,IF(T_Prestamos[[#This Row],[Tipo préstamo]]="Americano",T_Prestamos[[#This Row],[Importe]],T_Prestamos[[#This Row],[Importe]]+CUMPRINC(G14/12,E14*12,F14,1,R14,0))) -> 0 | T14: =IF(T_Prestamos[[#This Row],[Situación]]="Cancelados",0,IF(T_Prestamos[[#This Row],[Tipo préstamo]]="Americano",T_Prestamos[[#This Row],[Pendiente]]*T_Prestamos[[#This Row],[% interés ordinario]],-CUMIPMT(G14/12,E14*12,F14,R14,R14+11,0))) -> 0 | U14: 0 | V14: =T_Prestamos[[#This Row],[% apertura]]*T_Prestamos[[#This Row],[Importe]] -> 0 | Y14: =IF(T_Prestamos[[#This Row],[Situación]]="Activos",IF(T_Prestamos[[#This Row],[Tipo préstamo]]="Francés",DATEDIF(T_Prestamos[[#This Row],[firma préstamo]],DATE(YEAR(TODAY()),1,1),"m"),0),0) -> 0 | Z14: =IF(T_Prestamos[[#This Row],[Situación]]="Activos",IF(T_Prestamos[[#This Row],[Tipo préstamo]]="Americano",T_Prestamos[[#This Row],[Importe]]*T_Prestamos[[#This Row],[% interés ordinario]],-CUMIPMT(T_Prestamos[[#This Row],[% interés ordinario]]/12,T_Prestamos[[#This Row],[Años]]*12,T_Prestamos[[#This Row],[Importe]],T_Prestamos[[#This Row],[Primera cuota año]],T_Prestamos[[#This Row],[Primera cuota año]]+11,0)),0) -> 0 | AA14: =IF(T_Prestamos[[#This Row],[firma préstamo]]>DATE(YEAR(TODAY())-1,MONTH(TODAY()),DAY(TODAY())),T_Prestamos[[#This Row],[Importe]]*T_Prestamos[[#This Row],[% apertura]],0) -> 0
B15: 2011 | C15: Préstamo Rubén Gil de Blás | D15: 43167 | E15: 5 | F15: 14000 | G15: 0.125 | H15: 0.145 | J15: =IF(T_Prestamos[[#This Row],[Garantía]]="","",T_Prestamos[[#This Row],[Pendiente]]/T_Prestamos[[#This Row],[Garantía]]) | K15: Física | L15: Francés | M15: Silex | N15: Cancelados | O15: 44855 | Q15: =IF(T_Prestamos[[#This Row],[Situación]]="Cancelados",T_Prestamos[[#This Row],[Fecha cancelación]],TODAY())-T_Prestamos[[#This Row],[firma préstamo]] -> 1688 | R15: =IF(T_Prestamos[[#This Row],[Situación]]="Cancelada","",DATEDIF(T_Prestamos[[#This Row],[firma préstamo]],TODAY(),"m")) -> 96 | S15: =IF(T_Prestamos[[#This Row],[Situación]]="Cancelados",0,IF(T_Prestamos[[#This Row],[Tipo préstamo]]="Americano",T_Prestamos[[#This Row],[Importe]],T_Prestamos[[#This Row],[Importe]]+CUMPRINC(G15/12,E15*12,F15,1,R15,0))) -> 0 | T15: =IF(T_Prestamos[[#This Row],[Situación]]="Cancelados",0,IF(T_Prestamos[[#This Row],[Tipo préstamo]]="Americano",T_Prestamos[[#This Row],[Pendiente]]*T_Prestamos[[#This Row],[% interés ordinario]],-CUMIPMT(G15/12,E15*12,F15,R15,R15+11,0))) -> 0 | U15: 0 | V15: =T_Prestamos[[#This Row],[% apertura]]*T_Prestamos[[#This Row],[Importe]] -> 0 | Y15: =IF(T_Prestamos[[#This Row],[Situación]]="Activos",IF(T_Prestamos[[#This Row],[Tipo préstamo]]="Francés",DATEDIF(T_Prestamos[[#This Row],[firma préstamo]],DATE(YEAR(TODAY()),1,1),"m"),0),0) -> 0 | Z15: =IF(T_Prestamos[[#This Row],[Situación]]="Activos",IF(T_Prestamos[[#This Row],[Tipo préstamo]]="Americano",T_Prestamos[[#This Row],[Importe]]*T_Prestamos[[#This Row],[% interés ordinario]],-CUMIPMT(T_Prestamos[[#This Row],[% interés ordinario]]/12,T_Prestamos[[#This Row],[Años]]*12,T_Prestamos[[#This Row],[Importe]],T_Prestamos[[#This Row],[Primera cuota año]],T_Prestamos[[#This Row],[Primera cuota año]]+11,0)),0) -> 0 | AA15: =IF(T_Prestamos[[#This Row],[firma préstamo]]>DATE(YEAR(TODAY())-1,MONTH(TODAY()),DAY(TODAY())),T_Prestamos[[#This Row],[Importe]]*T_Prestamos[[#This Row],[% apertura]],0) -> 0
B16: 2012 | C16: Noia - Persona física | D16: 43168 | E16: 11 | F16: 34500 | G16: 0.135 | H16: =T_Prestamos[[#This Row],[% interés ordinario]]+3% -> 0.165 | I16: 91505 | J16: =IF(T_Prestamos[[#This Row],[Garantía]]="","",T_Prestamos[[#This Row],[Pendiente]]/T_Prestamos[[#This Row],[Garantía]]) -> 0.16198557 | K16: Física | L16: Francés | M16: Silex | N16: Activos | Q16: =IF(T_Prestamos[[#This Row],[Situación]]="Cancelados",T_Prestamos[[#This Row],[Fecha cancelación]],TODAY())-T_Prestamos[[#This Row],[firma préstamo]] -> 2928 | R16: =IF(T_Prestamos[[#This Row],[Situación]]="Cancelada","",DATEDIF(T_Prestamos[[#This Row],[firma préstamo]],TODAY(),"m")) -> 96 | S16: =IF(T_Prestamos[[#This Row],[Situación]]="Cancelados",0,IF(T_Prestamos[[#This Row],[Tipo préstamo]]="Americano",T_Prestamos[[#This Row],[Importe]],T_Prestamos[[#This Row],[Importe]]+CUMPRINC(G16/12,E16*12,F16,1,R16,0))) -> 14822.49 | T16: =IF(T_Prestamos[[#This Row],[Situación]]="Cancelados",0,IF(T_Prestamos[[#This Row],[Tipo préstamo]]="Americano",T_Prestamos[[#This Row],[Pendiente]]*T_Prestamos[[#This Row],[% interés ordinario]],-CUMIPMT(G16/12,E16*12,F16,R16,R16+11,0))) -> 1789.5383 | U16: 0 | V16: =T_Prestamos[[#This Row],[% apertura]]*T_Prestamos[[#This Row],[Importe]] -> 0 | W16: Carencia 12 meses | X16: Santiago Figueiras Soñora | Y16: =IF(T_Prestamos[[#This Row],[Situación]]="Activos",IF(T_Prestamos[[#This Row],[Tipo préstamo]]="Francés",DATEDIF(T_Prestamos[[#This Row],[firma préstamo]],DATE(YEAR(TODAY()),1,1),"m"),0),0) -> 93 | Z16: =IF(T_Prestamos[[#This Row],[Situación]]="Activos",IF(T_Prestamos[[#This Row],[Tipo préstamo]]="Americano",T_Prestamos[[#This Row],[Importe]]*T_Prestamos[[#This Row],[% interés ordinario]],-CUMIPMT(T_Prestamos[[#This Row],[% interés ordinario]]/12,T_Prestamos[[#This Row],[Años]]*12,T_Prestamos[[#This Row],[Importe]],T_Prestamos[[#This Row],[Primera cuota año]],T_Prestamos[[#This Row],[Primera cuota año]]+11,0)),0) -> 1929.6933 | AA16: =IF(T_Prestamos[[#This Row],[firma préstamo]]>DATE(YEAR(TODAY())-1,MONTH(TODAY()),DAY(TODAY())),T_Prestamos[[#This Row],[Importe]]*T_Prestamos[[#This Row],[% apertura]],0) -> 0
B17: 2013 | C17: Préstamo Gestión y Trámites - David Ferrer | D17: 42940 | E17: 3 | F17: 37000 | G17: 0.02 | H17: =T_Prestamos[[#This Row],[% interés ordinario]]+3% -> 0.05 | J17: =IF(T_Prestamos[[#This Row],[Garantía]]="","",T_Prestamos[[#This Row],[Pendiente]]/T_Prestamos[[#This Row],[Garantía]]) | K17: Física | L17: Americano | M17: Silex | N17: Cancelados | O17: 43650 | Q17: =IF(T_Prestamos[[#This Row],[Situación]]="Cancelados",T_Prestamos[[#This Row],[Fecha cancelación]],TODAY())-T_Prestamos[[#This Row],[firma préstamo]] -> 710 | R17: =IF(T_Prestamos[[#This Row],[Situación]]="Cancelada","",DATEDIF(T_Prestamos[[#This Row],[firma préstamo]],TODAY(),"m")) -> 103 | S17: =IF(T_Prestamos[[#This Row],[Situación]]="Cancelados",0,IF(T_Prestamos[[#This Row],[Tipo préstamo]]="Americano",T_Prestamos[[#This Row],[Importe]],T_Prestamos[[#This Row],[Importe]]+CUMPRINC(G17/12,E17*12,F17,1,R17,0))) -> 0 | T17: =IF(T_Prestamos[[#This Row],[Situación]]="Cancelados",0,IF(T_Prestamos[[#This Row],[Tipo préstamo]]="Americano",T_Prestamos[[#This Row],[Pendiente]]*T_Prestamos[[#This Row],[% interés ordinario]],-CUMIPMT(G17/12,E17*12,F17,R17,R17+11,0))) -> 0 | U17: 0 | V17: =T_Prestamos[[#This Row],[% apertura]]*T_Prestamos[[#This Row],[Importe]] -> 0 | Y17: =IF(T_Prestamos[[#This Row],[Situación]]="Activos",IF(T_Prestamos[[#This Row],[Tipo préstamo]]="Francés",DATEDIF(T_Prestamos[[#This Row],[firma préstamo]],DATE(YEAR(TODAY()),1,1),"m"),0),0) -> 0 | Z17: =IF(T_Prestamos[[#This Row],[Situación]]="Activos",IF(T_Prestamos[[#This Row],[Tipo préstamo]]="Americano",T_Prestamos[[#This Row],[Importe]]*T_Prestamos[[#This Row],[% interés ordinario]],-CUMIPMT(T_Prestamos[[#This Row],[% interés ordinario]]/12,T_Prestamos[[#This Row],[Años]]*12,T_Prestamos[[#This Row],[Importe]],T_Prestamos[[#This Row],[Primera cuota año]],T_Prestamos[[#This Row],[Primera cuota año]]+11,0)),0) -> 0 | AA17: =IF(T_Prestamos[[#This Row],[firma préstamo]]>DATE(YEAR(TODAY())-1,MONTH(TODAY()),DAY(TODAY())),T_Prestamos[[#This Row],[Importe]]*T_Prestamos[[#This Row],[% apertura]],0) -> 0
B18: 2014 | C18: Préstamo José Dominguez Caballero | D18: 43179 | E18: 10 | F18: 20000 | G18: 0.135 | H18: 0.155 | J18: =IF(T_Prestamos[[#This Row],[Garantía]]="","",T_Prestamos[[#This Row],[Pendiente]]/T_Prestamos[[#This Row],[Garantía]]) | K18: Física | L18: Francés | M18: Silex | N18: Cancelados | O18: 44978 | Q18: =IF(T_Prestamos[[#This Row],[Situación]]="Cancelados",T_Prestamos[[#This Row],[Fecha cancelación]],TODAY())-T_Prestamos[[#This Row],[firma préstamo]] -> 1799 | R18: =IF(T_Prestamos[[#This Row],[Situación]]="Cancelada","",DATEDIF(T_Prestamos[[#This Row],[firma préstamo]],TODAY(),"m")) -> 95 | S18: =IF(T_Prestamos[[#This Row],[Situación]]="Cancelados",0,IF(T_Prestamos[[#This Row],[Tipo préstamo]]="Americano",T_Prestamos[[#This Row],[Importe]],T_Prestamos[[#This Row],[Importe]]+CUMPRINC(G18/12,E18*12,F18,1,R18,0))) -> 0 | T18: =IF(T_Prestamos[[#This Row],[Situación]]="Cancelados",0,IF(T_Prestamos[[#This Row],[Tipo préstamo]]="Americano",T_Prestamos[[#This Row],[Pendiente]]*T_Prestamos[[#This Row],[% interés ordinario]],-CUMIPMT(G18/12,E18*12,F18,R18,R18+11,0))) -> 0 | U18: 0 | V18: =T_Prestamos[[#This Row],[% apertura]]*T_Prestamos[[#This Row],[Importe]] -> 0 | Y18: =IF(T_Prestamos[[#This Row],[Situación]]="Activos",IF(T_Prestamos[[#This Row],[Tipo préstamo]]="Francés",DATEDIF(T_Prestamos[[#This Row],[firma préstamo]],DATE(YEAR(TODAY()),1,1),"m"),0),0) -> 0 | Z18: =IF(T_Prestamos[[#This Row],[Situación]]="Activos",IF(T_Prestamos[[#This Row],[Tipo préstamo]]="Americano",T_Prestamos[[#This Row],[Importe]]*T_Prestamos[[#This Row],[% interés ordinario]],-CUMIPMT(T_Prestamos[[#This Row],[% interés ordinario]]/12,T_Prestamos[[#This Row],[Años]]*12,T_Prestamos[[#This Row],[Importe]],T_Prestamos[[#This Row],[Primera cuota año]],T_Prestamos[[#This Row],[Primera cuota año]]+11,0)),0) -> 0 | AA18: =IF(T_Prestamos[[#This Row],[firma préstamo]]>DATE(YEAR(TODAY())-1,MONTH(TODAY()),DAY(TODAY())),T_Prestamos[[#This Row],[Importe]]*T_Prestamos[[#This Row],[% apertura]],0) -> 0
B19: 2015 | C19: Préstamo M.Teresa Faure y David Zamora | D19: 43208 | E19: 10 | F19: 36500 | G19: 0.125 | H19: 0.145 | J19: =IF(T_Prestamos[[#This Row],[Garantía]]="","",T_Prestamos[[#This Row],[Pendiente]]/T_Prestamos[[#This Row],[Garantía]]) | K19: Física | L19: Francés | M19: Silex | N19: Cancelados | O19: 43448 | Q19: =IF(T_Prestamos[[#This Row],[Situación]]="Cancelados",T_Prestamos[[#This Row],[Fecha cancelación]],TODAY())-T_Prestamos[[#This Row],[firma préstamo]] -> 240 | R19: =IF(T_Prestamos[[#This Row],[Situación]]="Cancelada","",DATEDIF(T_Prestamos[[#This Row],[firma préstamo]],TODAY(),"m")) -> 94 | S19: =IF(T_Prestamos[[#This Row],[Situación]]="Cancelados",0,IF(T_Prestamos[[#This Row],[Tipo préstamo]]="Americano",T_Prestamos[[#This Row],[Importe]],T_Prestamos[[#This Row],[Importe]]+CUMPRINC(G19/12,E19*12,F19,1,R19,0))) -> 0 | T19: =IF(T_Prestamos[[#This Row],[Situación]]="Cancelados",0,IF(T_Prestamos[[#This Row],[Tipo préstamo]]="Americano",T_Prestamos[[#This Row],[Pendiente]]*T_Prestamos[[#This Row],[% interés ordinario]],-CUMIPMT(G19/12,E19*12,F19,R19,R19+11,0))) -> 0 | U19: 0 | V19: =T_Prestamos[[#This Row],[% apertura]]*T_Prestamos[[#This Row],[Importe]] -> 0 | Y19: =IF(T_Prestamos[[#This Row],[Situación]]="Activos",IF(T_Prestamos[[#This Row],[Tipo préstamo]]="Francés",DATEDIF(T_Prestamos[[#This Row],[firma préstamo]],DATE(YEAR(TODAY()),1,1),"m"),0),0) -> 0 | Z19: =IF(T_Prestamos[[#This Row],[Situación]]="Activos",IF(T_Prestamos[[#This Row],[Tipo préstamo]]="Americano",T_Prestamos[[#This Row],[Importe]]*T_Prestamos[[#This Row],[% interés ordinario]],-CUMIPMT(T_Prestamos[[#This Row],[% interés ordinario]]/12,T_Prestamos[[#This Row],[Años]]*12,T_Prestamos[[#This Row],[Importe]],T_Prestamos[[#This Row],[Primera cuota año]],T_Prestamos[[#This Row],[Primera cuota año]]+11,0)),0) -> 0 | AA19: =IF(T_Prestamos[[#This Row],[firma préstamo]]>DATE(YEAR(TODAY())-1,MONTH(TODAY()),DAY(TODAY())),T_Prestamos[[#This Row],[Importe]]*T_Prestamos[[#This Row],[% apertura]],0) -> 0
B20: 2016 | C20: Lorca - Murcia - Persona física | D20: 43279 | E20: 10 | F20: 24500 | G20: 0.13 | H20: =T_Prestamos[[#This Row],[% interés ordinario]]+3% -> 0.16 | I20: 89443 | J20: =IF(T_Prestamos[[#This Row],[Garantía]]="","",T_Prestamos[[#This Row],[Pendiente]]/T_Prestamos[[#This Row],[Garantía]]) -> 0.098323889 | K20: Física | L20: Francés | M20: Silex | N20: Activos | Q20: =IF(T_Prestamos[[#This Row],[Situación]]="Cancelados",T_Prestamos[[#This Row],[Fecha cancelación]],TODAY())-T_Prestamos[[#This Row],[firma préstamo]] -> 2817 | R20: =IF(T_Prestamos[[#This Row],[Situación]]="Cancelada","",DATEDIF(T_Prestamos[[#This Row],[firma préstamo]],TODAY(),"m")) -> 92 | S20: =IF(T_Prestamos[[#This Row],[Situación]]="Cancelados",0,IF(T_Prestamos[[#This Row],[Tipo préstamo]]="Americano",T_Prestamos[[#This Row],[Importe]],T_Prestamos[[#This Row],[Importe]]+CUMPRINC(G20/12,E20*12,F20,1,R20,0))) -> 8794.3836 | T20: =IF(T_Prestamos[[#This Row],[Situación]]="Cancelados",0,IF(T_Prestamos[[#This Row],[Tipo préstamo]]="Americano",T_Prestamos[[#This Row],[Pendiente]]*T_Prestamos[[#This Row],[% interés ordinario]],-CUMIPMT(G20/12,E20*12,F20,R20,R20+11,0))) -> 979.61913 | U20: 0 | V20: =T_Prestamos[[#This Row],[% apertura]]*T_Prestamos[[#This Row],[Importe]] -> 0 | X20: José Zamora Molina | Y20: =IF(T_Prestamos[[#This Row],[Situación]]="Activos",IF(T_Prestamos[[#This Row],[Tipo préstamo]]="Francés",DATEDIF(T_Prestamos[[#This Row],[firma préstamo]],DATE(YEAR(TODAY()),1,1),"m"),0),0) -> 90 | Z20: =IF(T_Prestamos[[#This Row],[Situación]]="Activos",IF(T_Prestamos[[#This Row],[Tipo préstamo]]="Americano",T_Prestamos[[#This Row],[Importe]]*T_Prestamos[[#This Row],[% interés ordinario]],-CUMIPMT(T_Prestamos[[#This Row],[% interés ordinario]]/12,T_Prestamos[[#This Row],[Años]]*12,T_Prestamos[[#This Row],[Importe]],T_Prestamos[[#This Row],[Primera cuota año]],T_Prestamos[[#This Row],[Primera cuota año]]+11,0)),0) -> 1052.3215 | AA20: =IF(T_Prestamos[[#This Row],[firma préstamo]]>DATE(YEAR(TODAY())-1,MONTH(TODAY()),DAY(TODAY())),T_Prestamos[[#This Row],[Importe]]*T_Prestamos[[#This Row],[% apertura]],0) -> 0
B21: 2017 | C21: Préstamo Jose Antonio García Mañanes | D21: 43208 | E21: 10 | F21: 36500 | G21: 0.125 | H21: 0.145 | J21: =IF(T_Prestamos[[#This Row],[Garantía]]="","",T_Prestamos[[#This Row],[Pendiente]]/T_Prestamos[[#This Row],[Garantía]]) | K21: Física | L21: Francés | M21: Silex | N21: Cancelados | O21: 43448 | Q21: =IF(T_Prestamos[[#This Row],[Situación]]="Cancelados",T_Prestamos[[#This Row],[Fecha cancelación]],TODAY())-T_Prestamos[[#This Row],[firma préstamo]] -> 240 | R21: =IF(T_Prestamos[[#This Row],[Situación]]="Cancelada","",DATEDIF(T_Prestamos[[#This Row],[firma préstamo]],TODAY(),"m")) -> 94 | S21: =IF(T_Prestamos[[#This Row],[Situación]]="Cancelados",0,IF(T_Prestamos[[#This Row],[Tipo préstamo]]="Americano",T_Prestamos[[#This Row],[Importe]],T_Prestamos[[#This Row],[Importe]]+CUMPRINC(G21/12,E21*12,F21,1,R21,0))) -> 0 | T21: =IF(T_Prestamos[[#This Row],[Situación]]="Cancelados",0,IF(T_Prestamos[[#This Row],[Tipo préstamo]]="Americano",T_Prestamos[[#This Row],[Pendiente]]*T_Prestamos[[#This Row],[% interés ordinario]],-CUMIPMT(G21/12,E21*12,F21,R21,R21+11,0))) -> 0 | U21: 0 | V21: =T_Prestamos[[#This Row],[% apertura]]*T_Prestamos[[#This Row],[Importe]] -> 0 | Y21: =IF(T_Prestamos[[#This Row],[Situación]]="Activos",IF(T_Prestamos[[#This Row],[Tipo préstamo]]="Francés",DATEDIF(T_Prestamos[[#This Row],[firma préstamo]],DATE(YEAR(TODAY()),1,1),"m"),0),0) -> 0 | Z21: =IF(T_Prestamos[[#This Row],[Situación]]="Activos",IF(T_Prestamos[[#This Row],[Tipo préstamo]]="Americano",T_Prestamos[[#This Row],[Importe]]*T_Prestamos[[#This Row],[% interés ordinario]],-CUMIPMT(T_Prestamos[[#This Row],[% interés ordinario]]/12,T_Prestamos[[#This Row],[Años]]*12,T_Prestamos[[#This Row],[Importe]],T_Prestamos[[#This Row],[Primera cuota año]],T_Prestamos[[#This Row],[Primera cuota año]]+11,0)),0) -> 0 | AA21: =IF(T_Prestamos[[#This Row],[firma préstamo]]>DATE(YEAR(TODAY())-1,MONTH(TODAY()),DAY(TODAY())),T_Prestamos[[#This Row],[Importe]]*T_Prestamos[[#This Row],[% apertura]],0) -> 0
B22: 2018 | C22: Préstamo Antonio Torres Marmol | D22: 43300 | E22: 10 | F22: 14500 | G22: 0.125 | H22: 0.145 | J22: =IF(T_Prestamos[[#This Row],[Garantía]]="","",T_Prestamos[[#This Row],[Pendiente]]/T_Prestamos[[#This Row],[Garantía]]) | K22: Física | L22: Francés | M22: Silex | N22: Cancelados | O22: 43796 | Q22: =IF(T_Prestamos[[#This Row],[Situación]]="Cancelados",T_Prestamos[[#This Row],[Fecha cancelación]],TODAY())-T_Prestamos[[#This Row],[firma préstamo]] -> 496 | R22: =IF(T_Prestamos[[#This Row],[Situación]]="Cancelada","",DATEDIF(T_Prestamos[[#This Row],[firma préstamo]],TODAY(),"m")) -> 91 | S22: =IF(T_Prestamos[[#This Row],[Situación]]="Cancelados",0,IF(T_Prestamos[[#This Row],[Tipo préstamo]]="Americano",T_Prestamos[[#This Row],[Importe]],T_Prestamos[[#This Row],[Importe]]+CUMPRINC(G22/12,E22*12,F22,1,R22,0))) -> 0 | T22: =IF(T_Prestamos[[#This Row],[Situación]]="Cancelados",0,IF(T_Prestamos[[#This Row],[Tipo préstamo]]="Americano",T_Prestamos[[#This Row],[Pendiente]]*T_Prestamos[[#This Row],[% interés ordinario]],-CUMIPMT(G22/12,E22*12,F22,R22,R22+11,0))) -> 0 | U22: 0 | V22: =T_Prestamos[[#This Row],[% apertura]]*T_Prestamos[[#This Row],[Importe]] -> 0 | Y22: =IF(T_Prestamos[[#This Row],[Situación]]="Activos",IF(T_Prestamos[[#This Row],[Tipo préstamo]]="Francés",DATEDIF(T_Prestamos[[#This Row],[firma préstamo]],DATE(YEAR(TODAY()),1,1),"m"),0),0) -> 0 | Z22: =IF(T_Prestamos[[#This Row],[Situación]]="Activos",IF(T_Prestamos[[#This Row],[Tipo préstamo]]="Americano",T_Prestamos[[#This Row],[Importe]]*T_Prestamos[[#This Row],[% interés ordinario]],-CUMIPMT(T_Prestamos[[#This Row],[% interés ordinario]]/12,T_Prestamos[[#This Row],[Años]]*12,T_Prestamos[[#This Row],[Importe]],T_Prestamos[[#This Row],[Primera cuota año]],T_Prestamos[[#This Row],[Primera cuota año]]+11,0)),0) -> 0 | AA22: =IF(T_Prestamos[[#This Row],[firma préstamo]]>DATE(YEAR(TODAY())-1,MONTH(TODAY()),DAY(TODAY())),T_Prestamos[[#This Row],[Importe]]*T_Prestamos[[#This Row],[% apertura]],0) -> 0
B23: 2019 | C23: Préstamo Jose Antonio López Oñate | D23: 43319 | E23: 10 | F23: 30500 | G23: 0.125 | H23: 0.145 | I23: 110101 | J23: =IF(T_Prestamos[[#This Row],[Garantía]]="","",T_Prestamos[[#This Row],[Pendiente]]/T_Prestamos[[#This Row],[Garantía]]) -> 0.10104167 | K23: Física | L23: Francés | M23: Silex | N23: Judicializados | Q23: =IF(T_Prestamos[[#This Row],[Situación]]="Cancelados",T_Prestamos[[#This Row],[Fecha cancelación]],TODAY())-T_Prestamos[[#This Row],[firma préstamo]] -> 2777 | R23: =IF(T_Prestamos[[#This Row],[Situación]]="Cancelada","",DATEDIF(T_Prestamos[[#This Row],[firma préstamo]],TODAY(),"m")) -> 91 | S23: =IF(T_Prestamos[[#This Row],[Situación]]="Cancelados",0,IF(T_Prestamos[[#This Row],[Tipo préstamo]]="Americano",T_Prestamos[[#This Row],[Importe]],T_Prestamos[[#This Row],[Importe]]+CUMPRINC(G23/12,E23*12,F23,1,R23,0))) -> 11124.789 | T23: =IF(T_Prestamos[[#This Row],[Situación]]="Cancelados",0,IF(T_Prestamos[[#This Row],[Tipo préstamo]]="Americano",T_Prestamos[[#This Row],[Pendiente]]*T_Prestamos[[#This Row],[% interés ordinario]],-CUMIPMT(G23/12,E23*12,F23,R23,R23+11,0))) -> 1198.5774 | U23: 0 | V23: =T_Prestamos[[#This Row],[% apertura]]*T_Prestamos[[#This Row],[Importe]] -> 0 | W23: En reclamación judicial | Y23: =IF(T_Prestamos[[#This Row],[Situación]]="Activos",IF(T_Prestamos[[#This Row],[Tipo préstamo]]="Francés",DATEDIF(T_Prestamos[[#This Row],[firma préstamo]],DATE(YEAR(TODAY()),1,1),"m"),0),0) -> 0 | Z23: =IF(T_Prestamos[[#This Row],[Situación]]="Activos",IF(T_Prestamos[[#This Row],[Tipo préstamo]]="Americano",T_Prestamos[[#This Row],[Importe]]*T_Prestamos[[#This Row],[% interés ordinario]],-CUMIPMT(T_Prestamos[[#This Row],[% interés ordinario]]/12,T_Prestamos[[#This Row],[Años]]*12,T_Prestamos[[#This Row],[Importe]],T_Prestamos[[#This Row],[Primera cuota año]],T_Prestamos[[#This Row],[Primera cuota año]]+11,0)),0) -> 0 | AA23: =IF(T_Prestamos[[#This Row],[firma préstamo]]>DATE(YEAR(TODAY())-1,MONTH(TODAY()),DAY(TODAY())),T_Prestamos[[#This Row],[Importe]]*T_Prestamos[[#This Row],[% apertura]],0) -> 0
B24: 2020 | C24: Préstamo Ana Isabel Otegui Aramburu | D24: 43353 | E24: 15 | F24: 19300 | G24: 0.125 | H24: 0.145 | J24: =IF(T_Prestamos[[#This Row],[Garantía]]="","",T_Prestamos[[#This Row],[Pendiente]]/T_Prestamos[[#This Row],[Garantía]]) | K24: Física | L24: Francés | M24: Silex | N24: Cancelados | O24: 43586 | Q24: =IF(T_Prestamos[[#This Row],[Situación]]="Cancelados",T_Prestamos[[#This Row],[Fecha cancelación]],TODAY())-T_Prestamos[[#This Row],[firma préstamo]] -> 233 | R24: =IF(T_Prestamos[[#This Row],[Situación]]="Cancelada","",DATEDIF(T_Prestamos[[#This Row],[firma préstamo]],TODAY(),"m")) -> 90 | S24: =IF(T_Prestamos[[#This Row],[Situación]]="Cancelados",0,IF(T_Prestamos[[#This Row],[Tipo préstamo]]="Americano",T_Prestamos[[#This Row],[Importe]],T_Prestamos[[#This Row],[Importe]]+CUMPRINC(G24/12,E24*12,F24,1,R24,0))) -> 0 | T24: =IF(T_Prestamos[[#This Row],[Situación]]="Cancelados",0,IF(T_Prestamos[[#This Row],[Tipo préstamo]]="Americano",T_Prestamos[[#This Row],[Pendiente]]*T_Prestamos[[#This Row],[% interés ordinario]],-CUMIPMT(G24/12,E24*12,F24,R24,R24+11,0))) -> 0 | U24: 0 | V24: =T_Prestamos[[#This Row],[% apertura]]*T_Prestamos[[#This Row],[Importe]] -> 0 | Y24: =IF(T_Prestamos[[#This Row],[Situación]]="Activos",IF(T_Prestamos[[#This Row],[Tipo préstamo]]="Francés",DATEDIF(T_Prestamos[[#This Row],[firma préstamo]],DATE(YEAR(TODAY()),1,1),"m"),0),0) -> 0 | Z24: =IF(T_Prestamos[[#This Row],[Situación]]="Activos",IF(T_Prestamos[[#This Row],[Tipo préstamo]]="Americano",T_Prestamos[[#This Row],[Importe]]*T_Prestamos[[#This Row],[% interés ordinario]],-CUMIPMT(T_Prestamos[[#This Row],[% interés ordinario]]/12,T_Prestamos[[#This Row],[Años]]*12,T_Prestamos[[#This Row],[Importe]],T_Prestamos[[#This Row],[Primera cuota año]],T_Prestamos[[#This Row],[Primera cuota año]]+11,0)),0) -> 0 | AA24: =IF(T_Prestamos[[#This Row],[firma préstamo]]>DATE(YEAR(TODAY())-1,MONTH(TODAY()),DAY(TODAY())),T_Prestamos[[#This Row],[Importe]]*T_Prestamos[[#This Row],[% apertura]],0) -> 0
B25: 2021 | C25: Préstamo Florentina González Martos | D25: 43375 | E25: 10 | F25: 15000 | G25: 0.135 | H25: 0.155 | I25: 111078 | J25: =IF(T_Prestamos[[#This Row],[Garantía]]="","",T_Prestamos[[#This Row],[Pendiente]]/T_Prestamos[[#This Row],[Garantía]]) -> 0.053565712 | K25: Física | L25: Francés | M25: Silex | N25: Judicializados | Q25: =IF(T_Prestamos[[#This Row],[Situación]]="Cancelados",T_Prestamos[[#This Row],[Fecha cancelación]],TODAY())-T_Prestamos[[#This Row],[firma préstamo]] -> 2721 | R25: =IF(T_Prestamos[[#This Row],[Situación]]="Cancelada","",DATEDIF(T_Prestamos[[#This Row],[firma préstamo]],TODAY(),"m")) -> 89 | S25: =IF(T_Prestamos[[#This Row],[Situación]]="Cancelados",0,IF(T_Prestamos[[#This Row],[Tipo préstamo]]="Americano",T_Prestamos[[#This Row],[Importe]],T_Prestamos[[#This Row],[Importe]]+CUMPRINC(G25/12,E25*12,F25,1,R25,0))) -> 5949.9722 | T25: =IF(T_Prestamos[[#This Row],[Situación]]="Cancelados",0,IF(T_Prestamos[[#This Row],[Tipo préstamo]]="Americano",T_Prestamos[[#This Row],[Pendiente]]*T_Prestamos[[#This Row],[% interés ordinario]],-CUMIPMT(G25/12,E25*12,F25,R25,R25+11,0))) -> 701.68132 | U25: 0 | V25: =T_Prestamos[[#This Row],[% apertura]]*T_Prestamos[[#This Row],[Importe]] -> 0 | W25: En reclamación judicial | Y25: =IF(T_Prestamos[[#This Row],[Situación]]="Activos",IF(T_Prestamos[[#This Row],[Tipo préstamo]]="Francés",DATEDIF(T_Prestamos[[#This Row],[firma préstamo]],DATE(YEAR(TODAY()),1,1),"m"),0),0) -> 0 | Z25: =IF(T_Prestamos[[#This Row],[Situación]]="Activos",IF(T_Prestamos[[#This Row],[Tipo préstamo]]="Americano",T_Prestamos[[#This Row],[Importe]]*T_Prestamos[[#This Row],[% interés ordinario]],-CUMIPMT(T_Prestamos[[#This Row],[% interés ordinario]]/12,T_Prestamos[[#This Row],[Años]]*12,T_Prestamos[[#This Row],[Importe]],T_Prestamos[[#This Row],[Primera cuota año]],T_Prestamos[[#This Row],[Primera cuota año]]+11,0)),0) -> 0 | AA25: =IF(T_Prestamos[[#This Row],[firma préstamo]]>DATE(YEAR(TODAY())-1,MONTH(TODAY()),DAY(TODAY())),T_Prestamos[[#This Row],[Importe]]*T_Prestamos[[#This Row],[% apertura]],0) -> 0
B26: 2022 | C26: Préstamo Victor Espejo Gines | D26: 43375 | E26: 15 | F26: 18500 | G26: 0.13 | H26: 0.15 | J26: =IF(T_Prestamos[[#This Row],[Garantía]]="","",T_Prestamos[[#This Row],[Pendiente]]/T_Prestamos[[#This Row],[Garantía]]) | K26: Física | L26: Francés | M26: Silex | N26: Cancelados | O26: 43670 | Q26: =IF(T_Prestamos[[#This Row],[Situación]]="Cancelados",T_Prestamos[[#This Row],[Fecha cancelación]],TODAY())-T_Prestamos[[#This Row],[firma préstamo]] -> 295 | R26: =IF(T_Prestamos[[#This Row],[Situación]]="Cancelada","",DATEDIF(T_Prestamos[[#This Row],[firma préstamo]],TODAY(),"m")) -> 89 | S26: =IF(T_Prestamos[[#This Row],[Situación]]="Cancelados",0,IF(T_Prestamos[[#This Row],[Tipo préstamo]]="Americano",T_Prestamos[[#This Row],[Importe]],T_Prestamos[[#This Row],[Importe]]+CUMPRINC(G26/12,E26*12,F26,1,R26,0))) -> 0 | T26: =IF(T_Prestamos[[#This Row],[Situación]]="Cancelados",0,IF(T_Prestamos[[#This Row],[Tipo préstamo]]="Americano",T_Prestamos[[#This Row],[Pendiente]]*T_Prestamos[[#This Row],[% interés ordinario]],-CUMIPMT(G26/12,E26*12,F26,R26,R26+11,0))) -> 0 | U26: 0 | V26: =T_Prestamos[[#This Row],[% apertura]]*T_Prestamos[[#This Row],[Importe]] -> 0 | Y26: =IF(T_Prestamos[[#This Row],[Situación]]="Activos",IF(T_Prestamos[[#This Row],[Tipo préstamo]]="Francés",DATEDIF(T_Prestamos[[#This Row],[firma préstamo]],DATE(YEAR(TODAY()),1,1),"m"),0),0) -> 0 | Z26: =IF(T_Prestamos[[#This Row],[Situación]]="Activos",IF(T_Prestamos[[#This Row],[Tipo préstamo]]="Americano",T_Prestamos[[#This Row],[Importe]]*T_Prestamos[[#This Row],[% interés ordinario]],-CUMIPMT(T_Prestamos[[#This Row],[% interés ordinario]]/12,T_Prestamos[[#This Row],[Años]]*12,T_Prestamos[[#This Row],[Importe]],T_Prestamos[[#This Row],[Primera cuota año]],T_Prestamos[[#This Row],[Primera cuota año]]+11,0)),0) -> 0 | AA26: =IF(T_Prestamos[[#This Row],[firma préstamo]]>DATE(YEAR(TODAY())-1,MONTH(TODAY()),DAY(TODAY())),T_Prestamos[[#This Row],[Importe]]*T_Prestamos[[#This Row],[% apertura]],0) -> 0
B27: 2023 | C27: 2º Préstamo Juliana Joval Esque | D27: 43382 | E27: 15 | F27: 27990.94 | G27: 0.15 | H27: 0.17 | J27: =IF(T_Prestamos[[#This Row],[Garantía]]="","",T_Prestamos[[#This Row],[Pendiente]]/T_Prestamos[[#This Row],[Garantía]]) | K27: Física | L27: Francés | M27: Silex | N27: Cancelados | O27: 45007 | Q27: =IF(T_Prestamos[[#This Row],[Situación]]="Cancelados",T_Prestamos[[#This Row],[Fecha cancelación]],TODAY())-T_Prestamos[[#This Row],[firma préstamo]] -> 1625 | R27: =IF(T_Prestamos[[#This Row],[Situación]]="Cancelada","",DATEDIF(T_Prestamos[[#This Row],[firma préstamo]],TODAY(),"m")) -> 89 | S27: =IF(T_Prestamos[[#This Row],[Situación]]="Cancelados",0,IF(T_Prestamos[[#This Row],[Tipo préstamo]]="Americano",T_Prestamos[[#This Row],[Importe]],T_Prestamos[[#This Row],[Importe]]+CUMPRINC(G27/12,E27*12,F27,1,R27,0))) -> 0 | T27: =IF(T_Prestamos[[#This Row],[Situación]]="Cancelados",0,IF(T_Prestamos[[#This Row],[Tipo préstamo]]="Americano",T_Prestamos[[#This Row],[Pendiente]]*T_Prestamos[[#This Row],[% interés ordinario]],-CUMIPMT(G27/12,E27*12,F27,R27,R27+11,0))) -> 0 | U27: 0 | V27: =T_Prestamos[[#This Row],[% apertura]]*T_Prestamos[[#This Row],[Importe]] -> 0 | Y27: =IF(T_Prestamos[[#This Row],[Situación]]="Activos",IF(T_Prestamos[[#This Row],[Tipo préstamo]]="Francés",DATEDIF(T_Prestamos[[#This Row],[firma préstamo]],DATE(YEAR(TODAY()),1,1),"m"),0),0) -> 0 | Z27: =IF(T_Prestamos[[#This Row],[Situación]]="Activos",IF(T_Prestamos[[#This Row],[Tipo préstamo]]="Americano",T_Prestamos[[#This Row],[Importe]]*T_Prestamos[[#This Row],[% interés ordinario]],-CUMIPMT(T_Prestamos[[#This Row],[% interés ordinario]]/12,T_Prestamos[[#This Row],[Años]]*12,T_Prestamos[[#This Row],[Importe]],T_Prestamos[[#This Row],[Primera cuota año]],T_Prestamos[[#This Row],[Primera cuota año]]+11,0)),0) -> 0 | AA27: =IF(T_Prestamos[[#This Row],[firma préstamo]]>DATE(YEAR(TODAY())-1,MONTH(TODAY()),DAY(TODAY())),T_Prestamos[[#This Row],[Importe]]*T_Prestamos[[#This Row],[% apertura]],0) -> 0
B28: 2024 | C28: Préstamo Gustavo Alberto Fernández de la Puebla | D28: 43503 | E28: 10 | F28: 20000 | G28: 0.125 | H28: 0.145 | J28: =IF(T_Prestamos[[#This Row],[Garantía]]="","",T_Prestamos[[#This Row],[Pendiente]]/T_Prestamos[[#This Row],[Garantía]]) | K28: Física | L28: Francés | M28: Silex | N28: Cancelados | O28: 44742 | Q28: =IF(T_Prestamos[[#This Row],[Situación]]="Cancelados",T_Prestamos[[#This Row],[Fecha cancelación]],TODAY())-T_Prestamos[[#This Row],[firma préstamo]] -> 1239 | R28: =IF(T_Prestamos[[#This Row],[Situación]]="Cancelada","",DATEDIF(T_Prestamos[[#This Row],[firma préstamo]],TODAY(),"m")) -> 85 | S28: =IF(T_Prestamos[[#This Row],[Situación]]="Cancelados",0,IF(T_Prestamos[[#This Row],[Tipo préstamo]]="Americano",T_Prestamos[[#This Row],[Importe]],T_Prestamos[[#This Row],[Importe]]+CUMPRINC(G28/12,E28*12,F28,1,R28,0))) -> 0 | T28: =IF(T_Prestamos[[#This Row],[Situación]]="Cancelados",0,IF(T_Prestamos[[#This Row],[Tipo préstamo]]="Americano",T_Prestamos[[#This Row],[Pendiente]]*T_Prestamos[[#This Row],[% interés ordinario]],-CUMIPMT(G28/12,E28*12,F28,R28,R28+11,0))) -> 0 | U28: 0 | V28: =T_Prestamos[[#This Row],[% apertura]]*T_Prestamos[[#This Row],[Importe]] -> 0 | Y28: =IF(T_Prestamos[[#This Row],[Situación]]="Activos",IF(T_Prestamos[[#This Row],[Tipo préstamo]]="Francés",DATEDIF(T_Prestamos[[#This Row],[firma préstamo]],DATE(YEAR(TODAY()),1,1),"m"),0),0) -> 0 | Z28: =IF(T_Prestamos[[#This Row],[Situación]]="Activos",IF(T_Prestamos[[#This Row],[Tipo préstamo]]="Americano",T_Prestamos[[#This Row],[Importe]]*T_Prestamos[[#This Row],[% interés ordinario]],-CUMIPMT(T_Prestamos[[#This Row],[% interés ordinario]]/12,T_Prestamos[[#This Row],[Años]]*12,T_Prestamos[[#This Row],[Importe]],T_Prestamos[[#This Row],[Primera cuota año]],T_Prestamos[[#This Row],[Primera cuota año]]+11,0)),0) -> 0 | AA28: =IF(T_Prestamos[[#This Row],[firma préstamo]]>DATE(YEAR(TODAY())-1,MONTH(TODAY()),DAY(TODAY())),T_Prestamos[[#This Row],[Importe]]*T_Prestamos[[#This Row],[% apertura]],0) -> 0
B29: 2025 | C29: Préstamo Concepción Saiz Saiz | D29: 43503 | E29: 10 | F29: 11100 | G29: 0.125 | H29: 0.145 | J29: =IF(T_Prestamos[[#This Row],[Garantía]]="","",T_Prestamos[[#This Row],[Pendiente]]/T_Prestamos[[#This Row],[Garantía]]) | K29: Física | L29: Francés | M29: Silex | N29: Cancelados | O29: 44134 | Q29: =IF(T_Prestamos[[#This Row],[Situación]]="Cancelados",T_Prestamos[[#This Row],[Fecha cancelación]],TODAY())-T_Prestamos[[#This Row],[firma préstamo]] -> 631 | R29: =IF(T_Prestamos[[#This Row],[Situación]]="Cancelada","",DATEDIF(T_Prestamos[[#This Row],[firma préstamo]],TODAY(),"m")) -> 85 | S29: =IF(T_Prestamos[[#This Row],[Situación]]="Cancelados",0,IF(T_Prestamos[[#This Row],[Tipo préstamo]]="Americano",T_Prestamos[[#This Row],[Importe]],T_Prestamos[[#This Row],[Importe]]+CUMPRINC(G29/12,E29*12,F29,1,R29,0))) -> 0 | T29: =IF(T_Prestamos[[#This Row],[Situación]]="Cancelados",0,IF(T_Prestamos[[#This Row],[Tipo préstamo]]="Americano",T_Prestamos[[#This Row],[Pendiente]]*T_Prestamos[[#This Row],[% interés ordinario]],-CUMIPMT(G29/12,E29*12,F29,R29,R29+11,0))) -> 0 | U29: 0 | V29: =T_Prestamos[[#This Row],[% apertura]]*T_Prestamos[[#This Row],[Importe]] -> 0 | Y29: =IF(T_Prestamos[[#This Row],[Situación]]="Activos",IF(T_Prestamos[[#This Row],[Tipo préstamo]]="Francés",DATEDIF(T_Prestamos[[#This Row],[firma préstamo]],DATE(YEAR(TODAY()),1,1),"m"),0),0) -> 0 | Z29: =IF(T_Prestamos[[#This Row],[Situación]]="Activos",IF(T_Prestamos[[#This Row],[Tipo préstamo]]="Americano",T_Prestamos[[#This Row],[Importe]]*T_Prestamos[[#This Row],[% interés ordinario]],-CUMIPMT(T_Prestamos[[#This Row],[% interés ordinario]]/12,T_Prestamos[[#This Row],[Años]]*12,T_Prestamos[[#This Row],[Importe]],T_Prestamos[[#This Row],[Primera cuota año]],T_Prestamos[[#This Row],[Primera cuota año]]+11,0)),0) -> 0 | AA29: =IF(T_Prestamos[[#This Row],[firma préstamo]]>DATE(YEAR(TODAY())-1,MONTH(TODAY()),DAY(TODAY())),T_Prestamos[[#This Row],[Importe]]*T_Prestamos[[#This Row],[% apertura]],0) -> 0
B30: 2026 | C30: Boró - Rivas_Vaciamadrid - Persona física | D30: 43524 | E30: 15 | F30: 18000 | G30: 0.125 | H30: 0.145 | I30: =167565/40500*18000 -> 74473.333 | J30: =IF(T_Prestamos[[#This Row],[Garantía]]="","",T_Prestamos[[#This Row],[Pendiente]]/T_Prestamos[[#This Row],[Garantía]]) -> 0.18022908 | K30: Física | L30: Francés | M30: Silex | N30: Activos | Q30: =IF(T_Prestamos[[#This Row],[Situación]]="Cancelados",T_Prestamos[[#This Row],[Fecha cancelación]],TODAY())-T_Prestamos[[#This Row],[firma préstamo]] -> 2572 | R30: =IF(T_Prestamos[[#This Row],[Situación]]="Cancelada","",DATEDIF(T_Prestamos[[#This Row],[firma préstamo]],TODAY(),"m")) -> 84 | S30: =IF(T_Prestamos[[#This Row],[Situación]]="Cancelados",0,IF(T_Prestamos[[#This Row],[Tipo préstamo]]="Americano",T_Prestamos[[#This Row],[Importe]],T_Prestamos[[#This Row],[Importe]]+CUMPRINC(G30/12,E30*12,F30,1,R30,0))) -> 13422.26 | T30: =IF(T_Prestamos[[#This Row],[Situación]]="Cancelados",0,IF(T_Prestamos[[#This Row],[Tipo préstamo]]="Americano",T_Prestamos[[#This Row],[Pendiente]]*T_Prestamos[[#This Row],[% interés ordinario]],-CUMIPMT(G30/12,E30*12,F30,R30,R30+11,0))) -> 1630.1271 | U30: 0 | V30: =T_Prestamos[[#This Row],[% apertura]]*T_Prestamos[[#This Row],[Importe]] -> 0 | X30: Tomasa Palacios Torres | Y30: =IF(T_Prestamos[[#This Row],[Situación]]="Activos",IF(T_Prestamos[[#This Row],[Tipo préstamo]]="Francés",DATEDIF(T_Prestamos[[#This Row],[firma préstamo]],DATE(YEAR(TODAY()),1,1),"m"),0),0) -> 82 | Z30: =IF(T_Prestamos[[#This Row],[Situación]]="Activos",IF(T_Prestamos[[#This Row],[Tipo préstamo]]="Americano",T_Prestamos[[#This Row],[Importe]]*T_Prestamos[[#This Row],[% interés ordinario]],-CUMIPMT(T_Prestamos[[#This Row],[% interés ordinario]]/12,T_Prestamos[[#This Row],[Años]]*12,T_Prestamos[[#This Row],[Importe]],T_Prestamos[[#This Row],[Primera cuota año]],T_Prestamos[[#This Row],[Primera cuota año]]+11,0)),0) -> 1651.2982 | AA30: =IF(T_Prestamos[[#This Row],[firma préstamo]]>DATE(YEAR(TODAY())-1,MONTH(TODAY()),DAY(TODAY())),T_Prestamos[[#This Row],[Importe]]*T_Prestamos[[#This Row],[% apertura]],0) -> 0
B31: 2027 | C31: Préstamo María del Mar Miguel León | D31: 43529 | E31: 15 | F31: 27500 | G31: 0.125 | H31: 0.145 | J31: =IF(T_Prestamos[[#This Row],[Garantía]]="","",T_Prestamos[[#This Row],[Pendiente]]/T_Prestamos[[#This Row],[Garantía]]) | K31: Física | L31: Francés | M31: Silex | N31: Cancelados | O31: 43799 | Q31: =IF(T_Prestamos[[#This Row],[Situación]]="Cancelados",T_Prestamos[[#This Row],[Fecha cancelación]],TODAY())-T_Prestamos[[#This Row],[firma préstamo]] -> 270 | R31: =IF(T_Prestamos[[#This Row],[Situación]]="Cancelada","",DATEDIF(T_Prestamos[[#This Row],[firma préstamo]],TODAY(),"m")) -> 84 | S31: =IF(T_Prestamos[[#This Row],[Situación]]="Cancelados",0,IF(T_Prestamos[[#This Row],[Tipo préstamo]]="Americano",T_Prestamos[[#This Row],[Importe]],T_Prestamos[[#This Row],[Importe]]+CUMPRINC(G31/12,E31*12,F31,1,R31,0))) -> 0 | T31: =IF(T_Prestamos[[#This Row],[Situación]]="Cancelados",0,IF(T_Prestamos[[#This Row],[Tipo préstamo]]="Americano",T_Prestamos[[#This Row],[Pendiente]]*T_Prestamos[[#This Row],[% interés ordinario]],-CUMIPMT(G31/12,E31*12,F31,R31,R31+11,0))) -> 0 | U31: 0 | V31: =T_Prestamos[[#This Row],[% apertura]]*T_Prestamos[[#This Row],[Importe]] -> 0 | Y31: =IF(T_Prestamos[[#This Row],[Situación]]="Activos",IF(T_Prestamos[[#This Row],[Tipo préstamo]]="Francés",DATEDIF(T_Prestamos[[#This Row],[firma préstamo]],DATE(YEAR(TODAY()),1,1),"m"),0),0) -> 0 | Z31: =IF(T_Prestamos[[#This Row],[Situación]]="Activos",IF(T_Prestamos[[#This Row],[Tipo préstamo]]="Americano",T_Prestamos[[#This Row],[Importe]]*T_Prestamos[[#This Row],[% interés ordinario]],-CUMIPMT(T_Prestamos[[#This Row],[% interés ordinario]]/12,T_Prestamos[[#This Row],[Años]]*12,T_Prestamos[[#This Row],[Importe]],T_Prestamos[[#This Row],[Primera cuota año]],T_Prestamos[[#This Row],[Primera cuota año]]+11,0)),0) -> 0 | AA31: =IF(T_Prestamos[[#This Row],[firma préstamo]]>DATE(YEAR(TODAY())-1,MONTH(TODAY()),DAY(TODAY())),T_Prestamos[[#This Row],[Importe]]*T_Prestamos[[#This Row],[% apertura]],0) -> 0
B32: 2028 | C32: Boró - Rivas_Vaciamadrid 2 - Persona física | D32: 43543 | E32: 15 | F32: 22500 | G32: 0.125 | H32: 0.145 | I32: =167565/40500*22500 -> 93091.667 | J32: =IF(T_Prestamos[[#This Row],[Garantía]]="","",T_Prestamos[[#This Row],[Pendiente]]/T_Prestamos[[#This Row],[Garantía]]) -> 0.18131931 | K32: Física | L32: Francés | M32: Silex | N32: Activos | Q32: =IF(T_Prestamos[[#This Row],[Situación]]="Cancelados",T_Prestamos[[#This Row],[Fecha cancelación]],TODAY())-T_Prestamos[[#This Row],[firma préstamo]] -> 2553 | R32: =IF(T_Prestamos[[#This Row],[Situación]]="Cancelada","",DATEDIF(T_Prestamos[[#This Row],[firma préstamo]],TODAY(),"m")) -> 83 | S32: =IF(T_Prestamos[[#This Row],[Situación]]="Cancelados",0,IF(T_Prestamos[[#This Row],[Tipo préstamo]]="Americano",T_Prestamos[[#This Row],[Importe]],T_Prestamos[[#This Row],[Importe]]+CUMPRINC(G32/12,E32*12,F32,1,R32,0))) -> 16879.317 | T32: =IF(T_Prestamos[[#This Row],[Situación]]="Cancelados",0,IF(T_Prestamos[[#This Row],[Tipo préstamo]]="Americano",T_Prestamos[[#This Row],[Pendiente]]*T_Prestamos[[#This Row],[% interés ordinario]],-CUMIPMT(G32/12,E32*12,F32,R32,R32+11,0))) -> 2050.9594 | U32: 0 | V32: =T_Prestamos[[#This Row],[% apertura]]*T_Prestamos[[#This Row],[Importe]] -> 0 | X32: Tomasa Palacios Torres | Y32: =IF(T_Prestamos[[#This Row],[Situación]]="Activos",IF(T_Prestamos[[#This Row],[Tipo préstamo]]="Francés",DATEDIF(T_Prestamos[[#This Row],[firma préstamo]],DATE(YEAR(TODAY()),1,1),"m"),0),0) -> 81 | Z32: =IF(T_Prestamos[[#This Row],[Situación]]="Activos",IF(T_Prestamos[[#This Row],[Tipo préstamo]]="Americano",T_Prestamos[[#This Row],[Importe]]*T_Prestamos[[#This Row],[% interés ordinario]],-CUMIPMT(T_Prestamos[[#This Row],[% interés ordinario]]/12,T_Prestamos[[#This Row],[Años]]*12,T_Prestamos[[#This Row],[Importe]],T_Prestamos[[#This Row],[Primera cuota año]],T_Prestamos[[#This Row],[Primera cuota año]]+11,0)),0) -> 2077.1505 | AA32: =IF(T_Prestamos[[#This Row],[firma préstamo]]>DATE(YEAR(TODAY())-1,MONTH(TODAY()),DAY(TODAY())),T_Prestamos[[#This Row],[Importe]]*T_Prestamos[[#This Row],[% apertura]],0) -> 0
B33: 2029 | C33: Préstamo Mónica Rodríguez López | D33: 43565 | E33: 6 | F33: 24600 | G33: 0.125 | H33: 0.145 | J33: =IF(T_Prestamos[[#This Row],[Garantía]]="","",T_Prestamos[[#This Row],[Pendiente]]/T_Prestamos[[#This Row],[Garantía]]) | K33: Física | L33: Francés | M33: Silex | N33: Cancelados | O33: 43719 | Q33: =IF(T_Prestamos[[#This Row],[Situación]]="Cancelados",T_Prestamos[[#This Row],[Fecha cancelación]],TODAY())-T_Prestamos[[#This Row],[firma préstamo]] -> 154 | R33: =IF(T_Prestamos[[#This Row],[Situación]]="Cancelada","",DATEDIF(T_Prestamos[[#This Row],[firma préstamo]],TODAY(),"m")) -> 83 | S33: =IF(T_Prestamos[[#This Row],[Situación]]="Cancelados",0,IF(T_Prestamos[[#This Row],[Tipo préstamo]]="Americano",T_Prestamos[[#This Row],[Importe]],T_Prestamos[[#This Row],[Importe]]+CUMPRINC(G33/12,E33*12,F33,1,R33,0))) -> 0 | T33: =IF(T_Prestamos[[#This Row],[Situación]]="Cancelados",0,IF(T_Prestamos[[#This Row],[Tipo préstamo]]="Americano",T_Prestamos[[#This Row],[Pendiente]]*T_Prestamos[[#This Row],[% interés ordinario]],-CUMIPMT(G33/12,E33*12,F33,R33,R33+11,0))) -> 0 | U33: 0 | V33: =T_Prestamos[[#This Row],[% apertura]]*T_Prestamos[[#This Row],[Importe]] -> 0 | Y33: =IF(T_Prestamos[[#This Row],[Situación]]="Activos",IF(T_Prestamos[[#This Row],[Tipo préstamo]]="Francés",DATEDIF(T_Prestamos[[#This Row],[firma préstamo]],DATE(YEAR(TODAY()),1,1),"m"),0),0) -> 0 | Z33: =IF(T_Prestamos[[#This Row],[Situación]]="Activos",IF(T_Prestamos[[#This Row],[Tipo préstamo]]="Americano",T_Prestamos[[#This Row],[Importe]]*T_Prestamos[[#This Row],[% interés ordinario]],-CUMIPMT(T_Prestamos[[#This Row],[% interés ordinario]]/12,T_Prestamos[[#This Row],[Años]]*12,T_Prestamos[[#This Row],[Importe]],T_Prestamos[[#This Row],[Primera cuota año]],T_Prestamos[[#This Row],[Primera cuota año]]+11,0)),0) -> 0 | AA33: =IF(T_Prestamos[[#This Row],[firma préstamo]]>DATE(YEAR(TODAY())-1,MONTH(TODAY()),DAY(TODAY())),T_Prestamos[[#This Row],[Importe]]*T_Prestamos[[#This Row],[% apertura]],0) -> 0
B34: 2030 | C34: Préstamo Lourdes Bartolome Martínez | D34: 43609 | E34: 15 | F34: 14700 | G34: 0.125 | H34: 0.155 | J34: =IF(T_Prestamos[[#This Row],[Garantía]]="","",T_Prestamos[[#This Row],[Pendiente]]/T_Prestamos[[#This Row],[Garantía]]) | K34: Física | L34: Francés | M34: Silex | N34: Cancelados | O34: 43972 | Q34: =IF(T_Prestamos[[#This Row],[Situación]]="Cancelados",T_Prestamos[[#This Row],[Fecha cancelación]],TODAY())-T_Prestamos[[#This Row],[firma préstamo]] -> 363 | R34: =IF(T_Prestamos[[#This Row],[Situación]]="Cancelada","",DATEDIF(T_Prestamos[[#This Row],[firma préstamo]],TODAY(),"m")) -> 81 | S34: =IF(T_Prestamos[[#This Row],[Situación]]="Cancelados",0,IF(T_Prestamos[[#This Row],[Tipo préstamo]]="Americano",T_Prestamos[[#This Row],[Importe]],T_Prestamos[[#This Row],[Importe]]+CUMPRINC(G34/12,E34*12,F34,1,R34,0))) -> 0 | T34: =IF(T_Prestamos[[#This Row],[Situación]]="Cancelados",0,IF(T_Prestamos[[#This Row],[Tipo préstamo]]="Americano",T_Prestamos[[#This Row],[Pendiente]]*T_Prestamos[[#This Row],[% interés ordinario]],-CUMIPMT(G34/12,E34*12,F34,R34,R34+11,0))) -> 0 | U34: 0 | V34: =T_Prestamos[[#This Row],[% apertura]]*T_Prestamos[[#This Row],[Importe]] -> 0 | Y34: =IF(T_Prestamos[[#This Row],[Situación]]="Activos",IF(T_Prestamos[[#This Row],[Tipo préstamo]]="Francés",DATEDIF(T_Prestamos[[#This Row],[firma préstamo]],DATE(YEAR(TODAY()),1,1),"m"),0),0) -> 0 | Z34: =IF(T_Prestamos[[#This Row],[Situación]]="Activos",IF(T_Prestamos[[#This Row],[Tipo préstamo]]="Americano",T_Prestamos[[#This Row],[Importe]]*T_Prestamos[[#This Row],[% interés ordinario]],-CUMIPMT(T_Prestamos[[#This Row],[% interés ordinario]]/12,T_Prestamos[[#This Row],[Años]]*12,T_Prestamos[[#This Row],[Importe]],T_Prestamos[[#This Row],[Primera cuota año]],T_Prestamos[[#This Row],[Primera cuota año]]+11,0)),0) -> 0 | AA34: =IF(T_Prestamos[[#This Row],[firma préstamo]]>DATE(YEAR(TODAY())-1,MONTH(TODAY()),DAY(TODAY())),T_Prestamos[[#This Row],[Importe]]*T_Prestamos[[#This Row],[% apertura]],0) -> 0
B35: 2031 | C35: Préstamo Juan Jiménez Artacho | D35: 43617 | E35: 20 | F35: 33000 | G35: 0.125 | H35: 0.145 | J35: =IF(T_Prestamos[[#This Row],[Garantía]]="","",T_Prestamos[[#This Row],[Pendiente]]/T_Prestamos[[#This Row],[Garantía]]) | K35: Física | L35: Francés | M35: Silex | N35: Cancelados | O35: 44320 | Q35: =IF(T_Prestamos[[#This Row],[Situación]]="Cancelados",T_Prestamos[[#This Row],[Fecha cancelación]],TODAY())-T_Prestamos[[#This Row],[firma préstamo]] -> 703 | R35: =IF(T_Prestamos[[#This Row],[Situación]]="Cancelada","",DATEDIF(T_Prestamos[[#This Row],[firma préstamo]],TODAY(),"m")) -> 81 | S35: =IF(T_Prestamos[[#This Row],[Situación]]="Cancelados",0,IF(T_Prestamos[[#This Row],[Tipo préstamo]]="Americano",T_Prestamos[[#This Row],[Importe]],T_Prestamos[[#This Row],[Importe]]+CUMPRINC(G35/12,E35*12,F35,1,R35,0))) -> 0 | T35: =IF(T_Prestamos[[#This Row],[Situación]]="Cancelados",0,IF(T_Prestamos[[#This Row],[Tipo préstamo]]="Americano",T_Prestamos[[#This Row],[Pendiente]]*T_Prestamos[[#This Row],[% interés ordinario]],-CUMIPMT(G35/12,E35*12,F35,R35,R35+11,0))) -> 0 | U35: 0 | V35: =T_Prestamos[[#This Row],[% apertura]]*T_Prestamos[[#This Row],[Importe]] -> 0 | Y35: =IF(T_Prestamos[[#This Row],[Situación]]="Activos",IF(T_Prestamos[[#This Row],[Tipo préstamo]]="Francés",DATEDIF(T_Prestamos[[#This Row],[firma préstamo]],DATE(YEAR(TODAY()),1,1),"m"),0),0) -> 0 | Z35: =IF(T_Prestamos[[#This Row],[Situación]]="Activos",IF(T_Prestamos[[#This Row],[Tipo préstamo]]="Americano",T_Prestamos[[#This Row],[Importe]]*T_Prestamos[[#This Row],[% interés ordinario]],-CUMIPMT(T_Prestamos[[#This Row],[% interés ordinario]]/12,T_Prestamos[[#This Row],[Años]]*12,T_Prestamos[[#This Row],[Importe]],T_Prestamos[[#This Row],[Primera cuota año]],T_Prestamos[[#This Row],[Primera cuota año]]+11,0)),0) -> 0 | AA35: =IF(T_Prestamos[[#This Row],[firma préstamo]]>DATE(YEAR(TODAY())-1,MONTH(TODAY()),DAY(TODAY())),T_Prestamos[[#This Row],[Importe]]*T_Prestamos[[#This Row],[% apertura]],0) -> 0
B36: 2032 | C36: Péstamo José Eleuterio Navarro Mira | D36: 43622 | E36: 15 | F36: 19000 | G36: 0.125 | H36: 0.1475 | J36: =IF(T_Prestamos[[#This Row],[Garantía]]="","",T_Prestamos[[#This Row],[Pendiente]]/T_Prestamos[[#This Row],[Garantía]]) | K36: Física | L36: Francés | M36: Silex | N36: Cancelados | O36: 44060 | Q36: =IF(T_Prestamos[[#This Row],[Situación]]="Cancelados",T_Prestamos[[#This Row],[Fecha cancelación]],TODAY())-T_Prestamos[[#This Row],[firma préstamo]] -> 438 | R36: =IF(T_Prestamos[[#This Row],[Situación]]="Cancelada","",DATEDIF(T_Prestamos[[#This Row],[firma préstamo]],TODAY(),"m")) -> 81 | S36: =IF(T_Prestamos[[#This Row],[Situación]]="Cancelados",0,IF(T_Prestamos[[#This Row],[Tipo préstamo]]="Americano",T_Prestamos[[#This Row],[Importe]],T_Prestamos[[#This Row],[Importe]]+CUMPRINC(G36/12,E36*12,F36,1,R36,0))) -> 0 | T36: =IF(T_Prestamos[[#This Row],[Situación]]="Cancelados",0,IF(T_Prestamos[[#This Row],[Tipo préstamo]]="Americano",T_Prestamos[[#This Row],[Pendiente]]*T_Prestamos[[#This Row],[% interés ordinario]],-CUMIPMT(G36/12,E36*12,F36,R36,R36+11,0))) -> 0 | U36: 0 | V36: =T_Prestamos[[#This Row],[% apertura]]*T_Prestamos[[#This Row],[Importe]] -> 0 | Y36: =IF(T_Prestamos[[#This Row],[Situación]]="Activos",IF(T_Prestamos[[#This Row],[Tipo préstamo]]="Francés",DATEDIF(T_Prestamos[[#This Row],[firma préstamo]],DATE(YEAR(TODAY()),1,1),"m"),0),0) -> 0 | Z36: =IF(T_Prestamos[[#This Row],[Situación]]="Activos",IF(T_Prestamos[[#This Row],[Tipo préstamo]]="Americano",T_Prestamos[[#This Row],[Importe]]*T_Prestamos[[#This Row],[% interés ordinario]],-CUMIPMT(T_Prestamos[[#This Row],[% interés ordinario]]/12,T_Prestamos[[#This Row],[Años]]*12,T_Prestamos[[#This Row],[Importe]],T_Prestamos[[#This Row],[Primera cuota año]],T_Prestamos[[#This Row],[Primera cuota año]]+11,0)),0) -> 0 | AA36: =IF(T_Prestamos[[#This Row],[firma préstamo]]>DATE(YEAR(TODAY())-1,MONTH(TODAY()),DAY(TODAY())),T_Prestamos[[#This Row],[Importe]]*T_Prestamos[[#This Row],[% apertura]],0) -> 0
B37: 2033 | C37: Préstamo Adela Rueda García | D37: 43621 | E37: 15 | F37: 14800 | G37: 0.125 | H37: 0.145 | I37: 126608 | J37: =IF(T_Prestamos[[#This Row],[Garantía]]="","",T_Prestamos[[#This Row],[Pendiente]]/T_Prestamos[[#This Row],[Garantía]]) -> 0.088732934 | K37: Física | L37: Francés | M37: Silex | N37: Judicializados | Q37: =IF(T_Prestamos[[#This Row],[Situación]]="Cancelados",T_Prestamos[[#This Row],[Fecha cancelación]],TODAY())-T_Prestamos[[#This Row],[firma préstamo]] -> 2475 | R37: =IF(T_Prestamos[[#This Row],[Situación]]="Cancelada","",DATEDIF(T_Prestamos[[#This Row],[firma préstamo]],TODAY(),"m")) -> 81 | S37: =IF(T_Prestamos[[#This Row],[Situación]]="Cancelados",0,IF(T_Prestamos[[#This Row],[Tipo préstamo]]="Americano",T_Prestamos[[#This Row],[Importe]],T_Prestamos[[#This Row],[Importe]]+CUMPRINC(G37/12,E37*12,F37,1,R37,0))) -> 11234.299 | T37: =IF(T_Prestamos[[#This Row],[Situación]]="Cancelados",0,IF(T_Prestamos[[#This Row],[Tipo préstamo]]="Americano",T_Prestamos[[#This Row],[Pendiente]]*T_Prestamos[[#This Row],[% interés ordinario]],-CUMIPMT(G37/12,E37*12,F37,R37,R37+11,0))) -> 1366.3034 | U37: 0 | V37: =T_Prestamos[[#This Row],[% apertura]]*T_Prestamos[[#This Row],[Importe]] -> 0 | W37: En reclamación judicial | Y37: =IF(T_Prestamos[[#This Row],[Situación]]="Activos",IF(T_Prestamos[[#This Row],[Tipo préstamo]]="Francés",DATEDIF(T_Prestamos[[#This Row],[firma préstamo]],DATE(YEAR(TODAY()),1,1),"m"),0),0) -> 0 | Z37: =IF(T_Prestamos[[#This Row],[Situación]]="Activos",IF(T_Prestamos[[#This Row],[Tipo préstamo]]="Americano",T_Prestamos[[#This Row],[Importe]]*T_Prestamos[[#This Row],[% interés ordinario]],-CUMIPMT(T_Prestamos[[#This Row],[% interés ordinario]]/12,T_Prestamos[[#This Row],[Años]]*12,T_Prestamos[[#This Row],[Importe]],T_Prestamos[[#This Row],[Primera cuota año]],T_Prestamos[[#This Row],[Primera cuota año]]+11,0)),0) -> 0 | AA37: =IF(T_Prestamos[[#This Row],[firma préstamo]]>DATE(YEAR(TODAY())-1,MONTH(TODAY()),DAY(TODAY())),T_Prestamos[[#This Row],[Importe]]*T_Prestamos[[#This Row],[% apertura]],0) -> 0
B38: 2034 | C38: Valencia - Persona física | D38: 43628 | E38: 10 | F38: 10000 | G38: 0.125 | H38: =T_Prestamos[[#This Row],[% interés ordinario]]+3% -> 0.155 | I38: 171312 | J38: =IF(T_Prestamos[[#This Row],[Garantía]]="","",T_Prestamos[[#This Row],[Pendiente]]/T_Prestamos[[#This Row],[Garantía]]) -> 0.02727011 | K38: Física | L38: Francés | M38: Silex | N38: Activos | Q38: =IF(T_Prestamos[[#This Row],[Situación]]="Cancelados",T_Prestamos[[#This Row],[Fecha cancelación]],TODAY())-T_Prestamos[[#This Row],[firma préstamo]] -> 2468 | R38: =IF(T_Prestamos[[#This Row],[Situación]]="Cancelada","",DATEDIF(T_Prestamos[[#This Row],[firma préstamo]],TODAY(),"m")) -> 81 | S38: =IF(T_Prestamos[[#This Row],[Situación]]="Cancelados",0,IF(T_Prestamos[[#This Row],[Tipo préstamo]]="Americano",T_Prestamos[[#This Row],[Importe]],T_Prestamos[[#This Row],[Importe]]+CUMPRINC(G38/12,E38*12,F38,1,R38,0))) -> 4671.697 | T38: =IF(T_Prestamos[[#This Row],[Situación]]="Cancelados",0,IF(T_Prestamos[[#This Row],[Tipo préstamo]]="Americano",T_Prestamos[[#This Row],[Pendiente]]*T_Prestamos[[#This Row],[% interés ordinario]],-CUMIPMT(G38/12,E38*12,F38,R38,R38+11,0))) -> 527.20187 | U38: 0 | V38: =T_Prestamos[[#This Row],[% apertura]]*T_Prestamos[[#This Row],[Importe]] -> 0 | X38: María Carmen Orrico Teruel | Y38: =IF(T_Prestamos[[#This Row],[Situación]]="Activos",IF(T_Prestamos[[#This Row],[Tipo préstamo]]="Francés",DATEDIF(T_Prestamos[[#This Row],[firma préstamo]],DATE(YEAR(TODAY()),1,1),"m"),0),0) -> 78 | Z38: =IF(T_Prestamos[[#This Row],[Situación]]="Activos",IF(T_Prestamos[[#This Row],[Tipo préstamo]]="Americano",T_Prestamos[[#This Row],[Importe]]*T_Prestamos[[#This Row],[% interés ordinario]],-CUMIPMT(T_Prestamos[[#This Row],[% interés ordinario]]/12,T_Prestamos[[#This Row],[Años]]*12,T_Prestamos[[#This Row],[Importe]],T_Prestamos[[#This Row],[Primera cuota año]],T_Prestamos[[#This Row],[Primera cuota año]]+11,0)),0) -> 564.83122 | AA38: =IF(T_Prestamos[[#This Row],[firma préstamo]]>DATE(YEAR(TODAY())-1,MONTH(TODAY()),DAY(TODAY())),T_Prestamos[[#This Row],[Importe]]*T_Prestamos[[#This Row],[% apertura]],0) -> 0
B39: 2035 | C39: Préstamo Pablo Pedro Benitez Perez | D39: 43629 | E39: 5 | F39: 13500 | G39: 0.125 | H39: 0.1475 | J39: =IF(T_Prestamos[[#This Row],[Garantía]]="","",T_Prestamos[[#This Row],[Pendiente]]/T_Prestamos[[#This Row],[Garantía]]) | K39: Física | L39: Francés | M39: Silex | N39: Cancelados | O39: 45456 | Q39: =IF(T_Prestamos[[#This Row],[Situación]]="Cancelados",T_Prestamos[[#This Row],[Fecha cancelación]],TODAY())-T_Prestamos[[#This Row],[firma préstamo]] -> 1827 | R39: =IF(T_Prestamos[[#This Row],[Situación]]="Cancelada","",DATEDIF(T_Prestamos[[#This Row],[firma préstamo]],TODAY(),"m")) -> 81 | S39: =IF(T_Prestamos[[#This Row],[Situación]]="Cancelados",0,IF(T_Prestamos[[#This Row],[Tipo préstamo]]="Americano",T_Prestamos[[#This Row],[Importe]],T_Prestamos[[#This Row],[Importe]]+CUMPRINC(G39/12,E39*12,F39,1,R39,0))) -> 0 | T39: =IF(T_Prestamos[[#This Row],[Situación]]="Cancelados",0,IF(T_Prestamos[[#This Row],[Tipo préstamo]]="Americano",T_Prestamos[[#This Row],[Pendiente]]*T_Prestamos[[#This Row],[% interés ordinario]],-CUMIPMT(G39/12,E39*12,F39,R39,R39+11,0))) -> 0 | U39: 0 | V39: =T_Prestamos[[#This Row],[% apertura]]*T_Prestamos[[#This Row],[Importe]] -> 0 | Y39: =IF(T_Prestamos[[#This Row],[Situación]]="Activos",IF(T_Prestamos[[#This Row],[Tipo préstamo]]="Francés",DATEDIF(T_Prestamos[[#This Row],[firma préstamo]],DATE(YEAR(TODAY()),1,1),"m"),0),0) -> 0 | Z39: =IF(T_Prestamos[[#This Row],[Situación]]="Activos",IF(T_Prestamos[[#This Row],[Tipo préstamo]]="Americano",T_Prestamos[[#This Row],[Importe]]*T_Prestamos[[#This Row],[% interés ordinario]],-CUMIPMT(T_Prestamos[[#This Row],[% interés ordinario]]/12,T_Prestamos[[#This Row],[Años]]*12,T_Prestamos[[#This Row],[Importe]],T_Prestamos[[#This Row],[Primera cuota año]],T_Prestamos[[#This Row],[Primera cuota año]]+11,0)),0) -> 0 | AA39: =IF(T_Prestamos[[#This Row],[firma préstamo]]>DATE(YEAR(TODAY())-1,MONTH(TODAY()),DAY(TODAY())),T_Prestamos[[#This Row],[Importe]]*T_Prestamos[[#This Row],[% apertura]],0) -> 0
B40: 2036 | C40: Préstamo Mª Flora Echevarria Sesmilo | D40: 43777 | E40: 6 | F40: 16500 | G40: 0.125 | H40: 0.155 | J40: =IF(T_Prestamos[[#This Row],[Garantía]]="","",T_Prestamos[[#This Row],[Pendiente]]/T_Prestamos[[#This Row],[Garantía]]) | K40: Física | L40: Francés | M40: Silex | N40: Cancelados | O40: 44581 | Q40: =IF(T_Prestamos[[#This Row],[Situación]]="Cancelados",T_Prestamos[[#This Row],[Fecha cancelación]],TODAY())-T_Prestamos[[#This Row],[firma préstamo]] -> 804 | R40: =IF(T_Prestamos[[#This Row],[Situación]]="Cancelada","",DATEDIF(T_Prestamos[[#This Row],[firma préstamo]],TODAY(),"m")) -> 76 | S40: =IF(T_Prestamos[[#This Row],[Situación]]="Cancelados",0,IF(T_Prestamos[[#This Row],[Tipo préstamo]]="Americano",T_Prestamos[[#This Row],[Importe]],T_Prestamos[[#This Row],[Importe]]+CUMPRINC(G40/12,E40*12,F40,1,R40,0))) -> 0 | T40: =IF(T_Prestamos[[#This Row],[Situación]]="Cancelados",0,IF(T_Prestamos[[#This Row],[Tipo préstamo]]="Americano",T_Prestamos[[#This Row],[Pendiente]]*T_Prestamos[[#This Row],[% interés ordinario]],-CUMIPMT(G40/12,E40*12,F40,R40,R40+11,0))) -> 0 | U40: 0 | V40: =T_Prestamos[[#This Row],[% apertura]]*T_Prestamos[[#This Row],[Importe]] -> 0 | Y40: =IF(T_Prestamos[[#This Row],[Situación]]="Activos",IF(T_Prestamos[[#This Row],[Tipo préstamo]]="Francés",DATEDIF(T_Prestamos[[#This Row],[firma préstamo]],DATE(YEAR(TODAY()),1,1),"m"),0),0) -> 0 | Z40: =IF(T_Prestamos[[#This Row],[Situación]]="Activos",IF(T_Prestamos[[#This Row],[Tipo préstamo]]="Americano",T_Prestamos[[#This Row],[Importe]]*T_Prestamos[[#This Row],[% interés ordinario]],-CUMIPMT(T_Prestamos[[#This Row],[% interés ordinario]]/12,T_Prestamos[[#This Row],[Años]]*12,T_Prestamos[[#This Row],[Importe]],T_Prestamos[[#This Row],[Primera cuota año]],T_Prestamos[[#This Row],[Primera cuota año]]+11,0)),0) -> 0 | AA40: =IF(T_Prestamos[[#This Row],[firma préstamo]]>DATE(YEAR(TODAY())-1,MONTH(TODAY()),DAY(TODAY())),T_Prestamos[[#This Row],[Importe]]*T_Prestamos[[#This Row],[% apertura]],0) -> 0
B41: 2037 | C41: Préstamo Yolanda de Blas Sánchez | D41: 43784 | E41: 15 | F41: 40000 | G41: 0.125 | H41: 0.155 | J41: =IF(T_Prestamos[[#This Row],[Garantía]]="","",T_Prestamos[[#This Row],[Pendiente]]/T_Prestamos[[#This Row],[Garantía]]) | K41: Física | L41: Francés | M41: Silex | N41: Cancelados | O41: 45225 | Q41: =IF(T_Prestamos[[#This Row],[Situación]]="Cancelados",T_Prestamos[[#This Row],[Fecha cancelación]],TODAY())-T_Prestamos[[#This Row],[firma préstamo]] -> 1441 | R41: =IF(T_Prestamos[[#This Row],[Situación]]="Cancelada","",DATEDIF(T_Prestamos[[#This Row],[firma préstamo]],TODAY(),"m")) -> 76 | S41: =IF(T_Prestamos[[#This Row],[Situación]]="Cancelados",0,IF(T_Prestamos[[#This Row],[Tipo préstamo]]="Americano",T_Prestamos[[#This Row],[Importe]],T_Prestamos[[#This Row],[Importe]]+CUMPRINC(G41/12,E41*12,F41,1,R41,0))) -> 0 | T41: =IF(T_Prestamos[[#This Row],[Situación]]="Cancelados",0,IF(T_Prestamos[[#This Row],[Tipo préstamo]]="Americano",T_Prestamos[[#This Row],[Pendiente]]*T_Prestamos[[#This Row],[% interés ordinario]],-CUMIPMT(G41/12,E41*12,F41,R41,R41+11,0))) -> 0 | U41: 0 | V41: =T_Prestamos[[#This Row],[% apertura]]*T_Prestamos[[#This Row],[Importe]] -> 0 | Y41: =IF(T_Prestamos[[#This Row],[Situación]]="Activos",IF(T_Prestamos[[#This Row],[Tipo préstamo]]="Francés",DATEDIF(T_Prestamos[[#This Row],[firma préstamo]],DATE(YEAR(TODAY()),1,1),"m"),0),0) -> 0 | Z41: =IF(T_Prestamos[[#This Row],[Situación]]="Activos",IF(T_Prestamos[[#This Row],[Tipo préstamo]]="Americano",T_Prestamos[[#This Row],[Importe]]*T_Prestamos[[#This Row],[% interés ordinario]],-CUMIPMT(T_Prestamos[[#This Row],[% interés ordinario]]/12,T_Prestamos[[#This Row],[Años]]*12,T_Prestamos[[#This Row],[Importe]],T_Prestamos[[#This Row],[Primera cuota año]],T_Prestamos[[#This Row],[Primera cuota año]]+11,0)),0) -> 0 | AA41: =IF(T_Prestamos[[#This Row],[firma préstamo]]>DATE(YEAR(TODAY())-1,MONTH(TODAY()),DAY(TODAY())),T_Prestamos[[#This Row],[Importe]]*T_Prestamos[[#This Row],[% apertura]],0) -> 0
B42: 2038 | C42: Avanza -Puerto Portals- Mallorca | D42: 43798 | E42: 1.5 | F42: 30000 | G42: =12.9%-3% -> 0.099 | H42: =14.9%-3% -> 0.119 | I42: 74117 | J42: =IF(T_Prestamos[[#This Row],[Garantía]]="","",T_Prestamos[[#This Row],[Pendiente]]/T_Prestamos[[#This Row],[Garantía]]) -> 0.40476544 | K42: Jurídica | L42: Americano | M42: Avanza | N42: Judicializados | Q42: =IF(T_Prestamos[[#This Row],[Situación]]="Cancelados",T_Prestamos[[#This Row],[Fecha cancelación]],TODAY())-T_Prestamos[[#This Row],[firma préstamo]] -> 2298 | R42: =IF(T_Prestamos[[#This Row],[Situación]]="Cancelada","",DATEDIF(T_Prestamos[[#This Row],[firma préstamo]],TODAY(),"m")) -> 75 | S42: =IF(T_Prestamos[[#This Row],[Situación]]="Cancelados",0,IF(T_Prestamos[[#This Row],[Tipo préstamo]]="Americano",T_Prestamos[[#This Row],[Importe]],T_Prestamos[[#This Row],[Importe]]+CUMPRINC(G42/12,E42*12,F42,1,R42,0))) -> 30000 | T42: =IF(T_Prestamos[[#This Row],[Situación]]="Cancelados",0,IF(T_Prestamos[[#This Row],[Tipo préstamo]]="Americano",T_Prestamos[[#This Row],[Pendiente]]*T_Prestamos[[#This Row],[% interés ordinario]],-CUMIPMT(G42/12,E42*12,F42,R42,R42+11,0))) -> 2970 | U42: 0 | V42: =T_Prestamos[[#This Row],[% apertura]]*T_Prestamos[[#This Row],[Importe]] -> 0 | Y42: =IF(T_Prestamos[[#This Row],[Situación]]="Activos",IF(T_Prestamos[[#This Row],[Tipo préstamo]]="Francés",DATEDIF(T_Prestamos[[#This Row],[firma préstamo]],DATE(YEAR(TODAY()),1,1),"m"),0),0) -> 0 | Z42: =IF(T_Prestamos[[#This Row],[Situación]]="Activos",IF(T_Prestamos[[#This Row],[Tipo préstamo]]="Americano",T_Prestamos[[#This Row],[Importe]]*T_Prestamos[[#This Row],[% interés ordinario]],-CUMIPMT(T_Prestamos[[#This Row],[% interés ordinario]]/12,T_Prestamos[[#This Row],[Años]]*12,T_Prestamos[[#This Row],[Importe]],T_Prestamos[[#This Row],[Primera cuota año]],T_Prestamos[[#This Row],[Primera cuota año]]+11,0)),0) -> 0 | AA42: =IF(T_Prestamos[[#This Row],[firma préstamo]]>DATE(YEAR(TODAY())-1,MONTH(TODAY()),DAY(TODAY())),T_Prestamos[[#This Row],[Importe]]*T_Prestamos[[#This Row],[% apertura]],0) -> 0
B43: 2040 | C43: Parla 1 | D43: 44599 | E43: 10 | F43: 107425 | G43: 0.1095 | H43: =T_Prestamos[[#This Row],[% interés ordinario]]+3% -> 0.1395 | J43: =IF(T_Prestamos[[#This Row],[Garantía]]="","",T_Prestamos[[#This Row],[Pendiente]]/T_Prestamos[[#This Row],[Garantía]]) | K43: Jurídica | L43: Americano | M43: Kontactalia | N43: Cancelados | O43: 44974 | Q43: =IF(T_Prestamos[[#This Row],[Situación]]="Cancelados",T_Prestamos[[#This Row],[Fecha cancelación]],TODAY())-T_Prestamos[[#This Row],[firma préstamo]] -> 375 | R43: =IF(T_Prestamos[[#This Row],[Situación]]="Cancelada","",DATEDIF(T_Prestamos[[#This Row],[firma préstamo]],TODAY(),"m")) -> 49 | S43: =IF(T_Prestamos[[#This Row],[Situación]]="Cancelados",0,IF(T_Prestamos[[#This Row],[Tipo préstamo]]="Americano",T_Prestamos[[#This Row],[Importe]],T_Prestamos[[#This Row],[Importe]]+CUMPRINC(G43/12,E43*12,F43,1,R43,0))) -> 0 | T43: =IF(T_Prestamos[[#This Row],[Situación]]="Cancelados",0,IF(T_Prestamos[[#This Row],[Tipo préstamo]]="Americano",T_Prestamos[[#This Row],[Pendiente]]*T_Prestamos[[#This Row],[% interés ordinario]],-CUMIPMT(G43/12,E43*12,F43,R43,R43+11,0))) -> 0 | U43: 0.01 | V43: =T_Prestamos[[#This Row],[% apertura]]*T_Prestamos[[#This Row],[Importe]] -> 1074.25 | X43: PROGELAN Y URBITEC | Y43: =IF(T_Prestamos[[#This Row],[Situación]]="Activos",IF(T_Prestamos[[#This Row],[Tipo préstamo]]="Francés",DATEDIF(T_Prestamos[[#This Row],[firma préstamo]],DATE(YEAR(TODAY()),1,1),"m"),0),0) -> 0 | Z43: =IF(T_Prestamos[[#This Row],[Situación]]="Activos",IF(T_Prestamos[[#This Row],[Tipo préstamo]]="Americano",T_Prestamos[[#This Row],[Importe]]*T_Prestamos[[#This Row],[% interés ordinario]],-CUMIPMT(T_Prestamos[[#This Row],[% interés ordinario]]/12,T_Prestamos[[#This Row],[Años]]*12,T_Prestamos[[#This Row],[Importe]],T_Prestamos[[#This Row],[Primera cuota año]],T_Prestamos[[#This Row],[Primera cuota año]]+11,0)),0) -> 0 | AA43: =IF(T_Prestamos[[#This Row],[firma préstamo]]>DATE(YEAR(TODAY())-1,MONTH(TODAY()),DAY(TODAY())),T_Prestamos[[#This Row],[Importe]]*T_Prestamos[[#This Row],[% apertura]],0) -> 0
B44: 2041 | C44: Avanza -Torre Azul- Mallorca | D44: 44553 | E44: 2 | F44: 42000 | G44: =13.75%-3% -> 0.1075 | H44: =T_Prestamos[[#This Row],[% interés ordinario]]+3% -> 0.1375 | I44: 293345 | J44: =IF(T_Prestamos[[#This Row],[Garantía]]="","",T_Prestamos[[#This Row],[Pendiente]]/T_Prestamos[[#This Row],[Garantía]]) -> 0.14317612 | K44: Jurídica | L44: Americano | M44: Avanza | N44: Activos | Q44: =IF(T_Prestamos[[#This Row],[Situación]]="Cancelados",T_Prestamos[[#This Row],[Fecha cancelación]],TODAY())-T_Prestamos[[#This Row],[firma préstamo]] -> 1543 | R44: =IF(T_Prestamos[[#This Row],[Situación]]="Cancelada","",DATEDIF(T_Prestamos[[#This Row],[firma préstamo]],TODAY(),"m")) -> 50 | S44: =IF(T_Prestamos[[#This Row],[Situación]]="Cancelados",0,IF(T_Prestamos[[#This Row],[Tipo préstamo]]="Americano",T_Prestamos[[#This Row],[Importe]],T_Prestamos[[#This Row],[Importe]]+CUMPRINC(G44/12,E44*12,F44,1,R44,0))) -> 42000 | T44: =IF(T_Prestamos[[#This Row],[Situación]]="Cancelados",0,IF(T_Prestamos[[#This Row],[Tipo préstamo]]="Americano",T_Prestamos[[#This Row],[Pendiente]]*T_Prestamos[[#This Row],[% interés ordinario]],-CUMIPMT(G44/12,E44*12,F44,R44,R44+11,0))) -> 4515 | U44: 0 | V44: =T_Prestamos[[#This Row],[% apertura]]*T_Prestamos[[#This Row],[Importe]] -> 0 | Y44: =IF(T_Prestamos[[#This Row],[Situación]]="Activos",IF(T_Prestamos[[#This Row],[Tipo préstamo]]="Francés",DATEDIF(T_Prestamos[[#This Row],[firma préstamo]],DATE(YEAR(TODAY()),1,1),"m"),0),0) -> 0 | Z44: =IF(T_Prestamos[[#This Row],[Situación]]="Activos",IF(T_Prestamos[[#This Row],[Tipo préstamo]]="Americano",T_Prestamos[[#This Row],[Importe]]*T_Prestamos[[#This Row],[% interés ordinario]],-CUMIPMT(T_Prestamos[[#This Row],[% interés ordinario]]/12,T_Prestamos[[#This Row],[Años]]*12,T_Prestamos[[#This Row],[Importe]],T_Prestamos[[#This Row],[Primera cuota año]],T_Prestamos[[#This Row],[Primera cuota año]]+11,0)),0) -> 4515 | AA44: =IF(T_Prestamos[[#This Row],[firma préstamo]]>DATE(YEAR(TODAY())-1,MONTH(TODAY()),DAY(TODAY())),T_Prestamos[[#This Row],[Importe]]*T_Prestamos[[#This Row],[% apertura]],0) -> 0
B45: 2042 | C45: Parla 2 | D45: 44709 | E45: 10 | F45: 107425 | G45: 0.1095 | H45: =T_Prestamos[[#This Row],[% interés ordinario]]+3% -> 0.1395 | I45: =473711/2 -> 236855.5 | J45: =IF(T_Prestamos[[#This Row],[Garantía]]="","",T_Prestamos[[#This Row],[Pendiente]]/T_Prestamos[[#This Row],[Garantía]]) -> 0.45354657 | K45: Jurídica | L45: Americano | M45: Kontactalia | N45: Activos | Q45: =IF(T_Prestamos[[#This Row],[Situación]]="Cancelados",T_Prestamos[[#This Row],[Fecha cancelación]],TODAY())-T_Prestamos[[#This Row],[firma préstamo]] -> 1387 | R45: =IF(T_Prestamos[[#This Row],[Situación]]="Cancelada","",DATEDIF(T_Prestamos[[#This Row],[firma préstamo]],TODAY(),"m")) -> 45 | S45: =IF(T_Prestamos[[#This Row],[Situación]]="Cancelados",0,IF(T_Prestamos[[#This Row],[Tipo préstamo]]="Americano",T_Prestamos[[#This Row],[Importe]],T_Prestamos[[#This Row],[Importe]]+CUMPRINC(G45/12,E45*12,F45,1,R45,0))) -> 107425 | T45: =IF(T_Prestamos[[#This Row],[Situación]]="Cancelados",0,IF(T_Prestamos[[#This Row],[Tipo préstamo]]="Americano",T_Prestamos[[#This Row],[Pendiente]]*T_Prestamos[[#This Row],[% interés ordinario]],-CUMIPMT(G45/12,E45*12,F45,R45,R45+11,0))) -> 11763.038 | U45: 0.01 | V45: =T_Prestamos[[#This Row],[% apertura]]*T_Prestamos[[#This Row],[Importe]] -> 1074.25 | X45: PROGELAN Y URBITEC | Y45: =IF(T_Prestamos[[#This Row],[Situación]]="Activos",IF(T_Prestamos[[#This Row],[Tipo préstamo]]="Francés",DATEDIF(T_Prestamos[[#This Row],[firma préstamo]],DATE(YEAR(TODAY()),1,1),"m"),0),0) -> 0 | Z45: =IF(T_Prestamos[[#This Row],[Situación]]="Activos",IF(T_Prestamos[[#This Row],[Tipo préstamo]]="Americano",T_Prestamos[[#This Row],[Importe]]*T_Prestamos[[#This Row],[% interés ordinario]],-CUMIPMT(T_Prestamos[[#This Row],[% interés ordinario]]/12,T_Prestamos[[#This Row],[Años]]*12,T_Prestamos[[#This Row],[Importe]],T_Prestamos[[#This Row],[Primera cuota año]],T_Prestamos[[#This Row],[Primera cuota año]]+11,0)),0) -> 11763.038 | AA45: =IF(T_Prestamos[[#This Row],[firma préstamo]]>DATE(YEAR(TODAY())-1,MONTH(TODAY()),DAY(TODAY())),T_Prestamos[[#This Row],[Importe]]*T_Prestamos[[#This Row],[% apertura]],0) -> 0
B46: 2043 | C46: Avanza -Sa Bassa Rotja- Mallorca | D46: 44708 | E46: 2 | F46: 50000 | G46: 0.09 | H46: =T_Prestamos[[#This Row],[% interés ordinario]]+3% -> 0.12 | J46: =IF(T_Prestamos[[#This Row],[Garantía]]="","",T_Prestamos[[#This Row],[Pendiente]]/T_Prestamos[[#This Row],[Garantía]]) | K46: Jurídica | L46: Americano | M46: Avanza | N46: Cancelados | O46: 45198 | Q46: =IF(T_Prestamos[[#This Row],[Situación]]="Cancelados",T_Prestamos[[#This Row],[Fecha cancelación]],TODAY())-T_Prestamos[[#This Row],[firma préstamo]] -> 490 | R46: =IF(T_Prestamos[[#This Row],[Situación]]="Cancelada","",DATEDIF(T_Prestamos[[#This Row],[firma préstamo]],TODAY(),"m")) -> 45 | S46: =IF(T_Prestamos[[#This Row],[Situación]]="Cancelados",0,IF(T_Prestamos[[#This Row],[Tipo préstamo]]="Americano",T_Prestamos[[#This Row],[Importe]],T_Prestamos[[#This Row],[Importe]]+CUMPRINC(G46/12,E46*12,F46,1,R46,0))) -> 0 | T46: =IF(T_Prestamos[[#This Row],[Situación]]="Cancelados",0,IF(T_Prestamos[[#This Row],[Tipo préstamo]]="Americano",T_Prestamos[[#This Row],[Pendiente]]*T_Prestamos[[#This Row],[% interés ordinario]],-CUMIPMT(G46/12,E46*12,F46,R46,R46+11,0))) -> 0 | U46: 0 | V46: =T_Prestamos[[#This Row],[% apertura]]*T_Prestamos[[#This Row],[Importe]] -> 0 | Y46: =IF(T_Prestamos[[#This Row],[Situación]]="Activos",IF(T_Prestamos[[#This Row],[Tipo préstamo]]="Francés",DATEDIF(T_Prestamos[[#This Row],[firma préstamo]],DATE(YEAR(TODAY()),1,1),"m"),0),0) -> 0 | Z46: =IF(T_Prestamos[[#This Row],[Situación]]="Activos",IF(T_Prestamos[[#This Row],[Tipo préstamo]]="Americano",T_Prestamos[[#This Row],[Importe]]*T_Prestamos[[#This Row],[% interés ordinario]],-CUMIPMT(T_Prestamos[[#This Row],[% interés ordinario]]/12,T_Prestamos[[#This Row],[Años]]*12,T_Prestamos[[#This Row],[Importe]],T_Prestamos[[#This Row],[Primera cuota año]],T_Prestamos[[#This Row],[Primera cuota año]]+11,0)),0) -> 0 | AA46: =IF(T_Prestamos[[#This Row],[firma préstamo]]>DATE(YEAR(TODAY())-1,MONTH(TODAY()),DAY(TODAY())),T_Prestamos[[#This Row],[Importe]]*T_Prestamos[[#This Row],[% apertura]],0) -> 0
B47: 2044 | C47: Castelldefels | D47: 44979 | E47: 5 | F47: 229425 | G47: 0.0995 | H47: =T_Prestamos[[#This Row],[% interés ordinario]]+3% -> 0.1295 | J47: =IF(T_Prestamos[[#This Row],[Garantía]]="","",T_Prestamos[[#This Row],[Pendiente]]/T_Prestamos[[#This Row],[Garantía]]) | K47: Jurídica | L47: Americano | M47: Kontactalia | N47: Cancelados | O47: 45164 | Q47: =IF(T_Prestamos[[#This Row],[Situación]]="Cancelados",T_Prestamos[[#This Row],[Fecha cancelación]],TODAY())-T_Prestamos[[#This Row],[firma préstamo]] -> 185 | R47: =IF(T_Prestamos[[#This Row],[Situación]]="Cancelada","",DATEDIF(T_Prestamos[[#This Row],[firma préstamo]],TODAY(),"m")) -> 36 | S47: =IF(T_Prestamos[[#This Row],[Situación]]="Cancelados",0,IF(T_Prestamos[[#This Row],[Tipo préstamo]]="Americano",T_Prestamos[[#This Row],[Importe]],T_Prestamos[[#This Row],[Importe]]+CUMPRINC(G47/12,E47*12,F47,1,R47,0))) -> 0 | T47: =IF(T_Prestamos[[#This Row],[Situación]]="Cancelados",0,IF(T_Prestamos[[#This Row],[Tipo préstamo]]="Americano",T_Prestamos[[#This Row],[Pendiente]]*T_Prestamos[[#This Row],[% interés ordinario]],-CUMIPMT(G47/12,E47*12,F47,R47,R47+11,0))) -> 0 | U47: 0.01 | V47: =T_Prestamos[[#This Row],[% apertura]]*T_Prestamos[[#This Row],[Importe]] -> 2294.25 | Y47: =IF(T_Prestamos[[#This Row],[Situación]]="Activos",IF(T_Prestamos[[#This Row],[Tipo préstamo]]="Francés",DATEDIF(T_Prestamos[[#This Row],[firma préstamo]],DATE(YEAR(TODAY()),1,1),"m"),0),0) -> 0 | Z47: =IF(T_Prestamos[[#This Row],[Situación]]="Activos",IF(T_Prestamos[[#This Row],[Tipo préstamo]]="Americano",T_Prestamos[[#This Row],[Importe]]*T_Prestamos[[#This Row],[% interés ordinario]],-CUMIPMT(T_Prestamos[[#This Row],[% interés ordinario]]/12,T_Prestamos[[#This Row],[Años]]*12,T_Prestamos[[#This Row],[Importe]],T_Prestamos[[#This Row],[Primera cuota año]],T_Prestamos[[#This Row],[Primera cuota año]]+11,0)),0) -> 0 | AA47: =IF(T_Prestamos[[#This Row],[firma préstamo]]>DATE(YEAR(TODAY())-1,MONTH(TODAY()),DAY(TODAY())),T_Prestamos[[#This Row],[Importe]]*T_Prestamos[[#This Row],[% apertura]],0) -> 0
B48: 2045 | C48: Avanza - Pino Centinela-Boadilla del Monte | D48: 45237 | E48: 2 | F48: 10000 | G48: 0.0907 | H48: =T_Prestamos[[#This Row],[% interés ordinario]]+3% -> 0.1207 | J48: =IF(T_Prestamos[[#This Row],[Garantía]]="","",T_Prestamos[[#This Row],[Pendiente]]/T_Prestamos[[#This Row],[Garantía]]) | K48: Jurídica | L48: Americano | M48: Avanza | N48: Cancelados | O48: 45401 | Q48: =IF(T_Prestamos[[#This Row],[Situación]]="Cancelados",T_Prestamos[[#This Row],[Fecha cancelación]],TODAY())-T_Prestamos[[#This Row],[firma préstamo]] -> 164 | R48: =IF(T_Prestamos[[#This Row],[Situación]]="Cancelada","",DATEDIF(T_Prestamos[[#This Row],[firma préstamo]],TODAY(),"m")) -> 28 | S48: =IF(T_Prestamos[[#This Row],[Situación]]="Cancelados",0,IF(T_Prestamos[[#This Row],[Tipo préstamo]]="Americano",T_Prestamos[[#This Row],[Importe]],T_Prestamos[[#This Row],[Importe]]+CUMPRINC(G48/12,E48*12,F48,1,R48,0))) -> 0 | T48: =IF(T_Prestamos[[#This Row],[Situación]]="Cancelados",0,IF(T_Prestamos[[#This Row],[Tipo préstamo]]="Americano",T_Prestamos[[#This Row],[Pendiente]]*T_Prestamos[[#This Row],[% interés ordinario]],-CUMIPMT(G48/12,E48*12,F48,R48,R48+11,0))) -> 0 | U48: 0 | V48: =T_Prestamos[[#This Row],[% apertura]]*T_Prestamos[[#This Row],[Importe]] -> 0 | Y48: =IF(T_Prestamos[[#This Row],[Situación]]="Activos",IF(T_Prestamos[[#This Row],[Tipo préstamo]]="Francés",DATEDIF(T_Prestamos[[#This Row],[firma préstamo]],DATE(YEAR(TODAY()),1,1),"m"),0),0) -> 0 | Z48: =IF(T_Prestamos[[#This Row],[Situación]]="Activos",IF(T_Prestamos[[#This Row],[Tipo préstamo]]="Americano",T_Prestamos[[#This Row],[Importe]]*T_Prestamos[[#This Row],[% interés ordinario]],-CUMIPMT(T_Prestamos[[#This Row],[% interés ordinario]]/12,T_Prestamos[[#This Row],[Años]]*12,T_Prestamos[[#This Row],[Importe]],T_Prestamos[[#This Row],[Primera cuota año]],T_Prestamos[[#This Row],[Primera cuota año]]+11,0)),0) -> 0 | AA48: =IF(T_Prestamos[[#This Row],[firma préstamo]]>DATE(YEAR(TODAY())-1,MONTH(TODAY()),DAY(TODAY())),T_Prestamos[[#This Row],[Importe]]*T_Prestamos[[#This Row],[% apertura]],0) -> 0
B49: 2046 | C49: Avanza - Santa Ponsa - Mallorca | D49: 45244 | E49: 2 | F49: 10000 | G49: 0.0974 | H49: =T_Prestamos[[#This Row],[% interés ordinario]]+3% -> 0.1274 | J49: =IF(T_Prestamos[[#This Row],[Garantía]]="","",T_Prestamos[[#This Row],[Pendiente]]/T_Prestamos[[#This Row],[Garantía]]) | K49: Jurídica | L49: Americano | M49: Avanza | N49: Cancelados | O49: 45499 | Q49: =IF(T_Prestamos[[#This Row],[Situación]]="Cancelados",T_Prestamos[[#This Row],[Fecha cancelación]],TODAY())-T_Prestamos[[#This Row],[firma préstamo]] -> 255 | R49: =IF(T_Prestamos[[#This Row],[Situación]]="Cancelada","",DATEDIF(T_Prestamos[[#This Row],[firma préstamo]],TODAY(),"m")) -> 28 | S49: =IF(T_Prestamos[[#This Row],[Situación]]="Cancelados",0,IF(T_Prestamos[[#This Row],[Tipo préstamo]]="Americano",T_Prestamos[[#This Row],[Importe]],T_Prestamos[[#This Row],[Importe]]+CUMPRINC(G49/12,E49*12,F49,1,R49,0))) -> 0 | T49: =IF(T_Prestamos[[#This Row],[Situación]]="Cancelados",0,IF(T_Prestamos[[#This Row],[Tipo préstamo]]="Americano",T_Prestamos[[#This Row],[Pendiente]]*T_Prestamos[[#This Row],[% interés ordinario]],-CUMIPMT(G49/12,E49*12,F49,R49,R49+11,0))) -> 0 | U49: 0 | V49: =T_Prestamos[[#This Row],[% apertura]]*T_Prestamos[[#This Row],[Importe]] -> 0 | Y49: =IF(T_Prestamos[[#This Row],[Situación]]="Activos",IF(T_Prestamos[[#This Row],[Tipo préstamo]]="Francés",DATEDIF(T_Prestamos[[#This Row],[firma préstamo]],DATE(YEAR(TODAY()),1,1),"m"),0),0) -> 0 | Z49: =IF(T_Prestamos[[#This Row],[Situación]]="Activos",IF(T_Prestamos[[#This Row],[Tipo préstamo]]="Americano",T_Prestamos[[#This Row],[Importe]]*T_Prestamos[[#This Row],[% interés ordinario]],-CUMIPMT(T_Prestamos[[#This Row],[% interés ordinario]]/12,T_Prestamos[[#This Row],[Años]]*12,T_Prestamos[[#This Row],[Importe]],T_Prestamos[[#This Row],[Primera cuota año]],T_Prestamos[[#This Row],[Primera cuota año]]+11,0)),0) -> 0 | AA49: =IF(T_Prestamos[[#This Row],[firma préstamo]]>DATE(YEAR(TODAY())-1,MONTH(TODAY()),DAY(TODAY())),T_Prestamos[[#This Row],[Importe]]*T_Prestamos[[#This Row],[% apertura]],0) -> 0
B50: 2047 | C50: Jerez | D50: 45254 | E50: 10 | F50: 124595 | G50: 0.115 | H50: =T_Prestamos[[#This Row],[% interés ordinario]]+3% -> 0.145 | J50: =IF(T_Prestamos[[#This Row],[Garantía]]="","",T_Prestamos[[#This Row],[Pendiente]]/T_Prestamos[[#This Row],[Garantía]]) | K50: Jurídica | L50: Americano | M50: Kontactalia | N50: Cancelados | O50: 45589 | Q50: =IF(T_Prestamos[[#This Row],[Situación]]="Cancelados",T_Prestamos[[#This Row],[Fecha cancelación]],TODAY())-T_Prestamos[[#This Row],[firma préstamo]] -> 335 | R50: =IF(T_Prestamos[[#This Row],[Situación]]="Cancelada","",DATEDIF(T_Prestamos[[#This Row],[firma préstamo]],TODAY(),"m")) -> 27 | S50: =IF(T_Prestamos[[#This Row],[Situación]]="Cancelados",0,IF(T_Prestamos[[#This Row],[Tipo préstamo]]="Americano",T_Prestamos[[#This Row],[Importe]],T_Prestamos[[#This Row],[Importe]]+CUMPRINC(G50/12,E50*12,F50,1,R50,0))) -> 0 | T50: =IF(T_Prestamos[[#This Row],[Situación]]="Cancelados",0,IF(T_Prestamos[[#This Row],[Tipo préstamo]]="Americano",T_Prestamos[[#This Row],[Pendiente]]*T_Prestamos[[#This Row],[% interés ordinario]],-CUMIPMT(G50/12,E50*12,F50,R50,R50+11,0))) -> 0 | U50: 0.01 | V50: =T_Prestamos[[#This Row],[% apertura]]*T_Prestamos[[#This Row],[Importe]] -> 1245.95 | X50: JARALU | Y50: =IF(T_Prestamos[[#This Row],[Situación]]="Activos",IF(T_Prestamos[[#This Row],[Tipo préstamo]]="Francés",DATEDIF(T_Prestamos[[#This Row],[firma préstamo]],DATE(YEAR(TODAY()),1,1),"m"),0),0) -> 0 | Z50: =IF(T_Prestamos[[#This Row],[Situación]]="Activos",IF(T_Prestamos[[#This Row],[Tipo préstamo]]="Americano",T_Prestamos[[#This Row],[Importe]]*T_Prestamos[[#This Row],[% interés ordinario]],-CUMIPMT(T_Prestamos[[#This Row],[% interés ordinario]]/12,T_Prestamos[[#This Row],[Años]]*12,T_Prestamos[[#This Row],[Importe]],T_Prestamos[[#This Row],[Primera cuota año]],T_Prestamos[[#This Row],[Primera cuota año]]+11,0)),0) -> 0 | AA50: =IF(T_Prestamos[[#This Row],[firma préstamo]]>DATE(YEAR(TODAY())-1,MONTH(TODAY()),DAY(TODAY())),T_Prestamos[[#This Row],[Importe]]*T_Prestamos[[#This Row],[% apertura]],0) -> 0
B51: 2048 | C51: Sitges | D51: 45258 | E51: 10 | F51: 172975 | G51: 0.105 | H51: =T_Prestamos[[#This Row],[% interés ordinario]]+3% -> 0.135 | I51: 545912 | J51: =IF(T_Prestamos[[#This Row],[Garantía]]="","",T_Prestamos[[#This Row],[Pendiente]]/T_Prestamos[[#This Row],[Garantía]]) -> 0.27130295 | K51: Jurídica | L51: Francés | M51: Kontactalia | N51: Activos | P51: =T_Prestamos[[#This Row],[Importe]]*T_Prestamos[[#This Row],[% interés ordinario]]/12 -> 1513.5312 | Q51: =IF(T_Prestamos[[#This Row],[Situación]]="Cancelados",T_Prestamos[[#This Row],[Fecha cancelación]],TODAY())-T_Prestamos[[#This Row],[firma préstamo]] -> 838 | R51: =IF(T_Prestamos[[#This Row],[Situación]]="Cancelada","",DATEDIF(T_Prestamos[[#This Row],[firma préstamo]],TODAY(),"m")) -> 27 | S51: =IF(T_Prestamos[[#This Row],[Situación]]="Cancelados",0,IF(T_Prestamos[[#This Row],[Tipo préstamo]]="Americano",T_Prestamos[[#This Row],[Importe]],T_Prestamos[[#This Row],[Importe]]+CUMPRINC(G51/12,E51*12,F51,1,R51,0))) -> 148107.54 | T51: =IF(T_Prestamos[[#This Row],[Situación]]="Cancelados",0,IF(T_Prestamos[[#This Row],[Tipo préstamo]]="Americano",T_Prestamos[[#This Row],[Pendiente]]*T_Prestamos[[#This Row],[% interés ordinario]],-CUMIPMT(G51/12,E51*12,F51,R51,R51+11,0))) -> 15047.365 | U51: 0.01 | V51: =T_Prestamos[[#This Row],[% apertura]]*T_Prestamos[[#This Row],[Importe]] -> 1729.75 | X51: MAXTANER | Y51: =IF(T_Prestamos[[#This Row],[Situación]]="Activos",IF(T_Prestamos[[#This Row],[Tipo préstamo]]="Francés",DATEDIF(T_Prestamos[[#This Row],[firma préstamo]],DATE(YEAR(TODAY()),1,1),"m"),0),0) -> 25 | Z51: =IF(T_Prestamos[[#This Row],[Situación]]="Activos",IF(T_Prestamos[[#This Row],[Tipo préstamo]]="Americano",T_Prestamos[[#This Row],[Importe]]*T_Prestamos[[#This Row],[% interés ordinario]],-CUMIPMT(T_Prestamos[[#This Row],[% interés ordinario]]/12,T_Prestamos[[#This Row],[Años]]*12,T_Prestamos[[#This Row],[Importe]],T_Prestamos[[#This Row],[Primera cuota año]],T_Prestamos[[#This Row],[Primera cuota año]]+11,0)),0) -> 15271.242 | AA51: =IF(T_Prestamos[[#This Row],[firma préstamo]]>DATE(YEAR(TODAY())-1,MONTH(TODAY()),DAY(TODAY())),T_Prestamos[[#This Row],[Importe]]*T_Prestamos[[#This Row],[% apertura]],0) -> 0
B52: 2049 | C52: Avanza -Santa María - Mallorca | D52: 45258 | E52: 2 | F52: 10000 | G52: 0.1109 | H52: =T_Prestamos[[#This Row],[% interés ordinario]]+3% -> 0.1409 | J52: =IF(T_Prestamos[[#This Row],[Garantía]]="","",T_Prestamos[[#This Row],[Pendiente]]/T_Prestamos[[#This Row],[Garantía]]) | K52: Jurídica | L52: Americano | M52: Avanza | N52: Cancelados | O52: 45737 | Q52: =IF(T_Prestamos[[#This Row],[Situación]]="Cancelados",T_Prestamos[[#This Row],[Fecha cancelación]],TODAY())-T_Prestamos[[#This Row],[firma préstamo]] -> 479 | R52: =IF(T_Prestamos[[#This Row],[Situación]]="Cancelada","",DATEDIF(T_Prestamos[[#This Row],[firma préstamo]],TODAY(),"m")) -> 27 | S52: =IF(T_Prestamos[[#This Row],[Situación]]="Cancelados",0,IF(T_Prestamos[[#This Row],[Tipo préstamo]]="Americano",T_Prestamos[[#This Row],[Importe]],T_Prestamos[[#This Row],[Importe]]+CUMPRINC(G52/12,E52*12,F52,1,R52,0))) -> 0 | T52: =IF(T_Prestamos[[#This Row],[Situación]]="Cancelados",0,IF(T_Prestamos[[#This Row],[Tipo préstamo]]="Americano",T_Prestamos[[#This Row],[Pendiente]]*T_Prestamos[[#This Row],[% interés ordinario]],-CUMIPMT(G52/12,E52*12,F52,R52,R52+11,0))) -> 0 | U52: 0 | V52: =T_Prestamos[[#This Row],[% apertura]]*T_Prestamos[[#This Row],[Importe]] -> 0 | Y52: =IF(T_Prestamos[[#This Row],[Situación]]="Activos",IF(T_Prestamos[[#This Row],[Tipo préstamo]]="Francés",DATEDIF(T_Prestamos[[#This Row],[firma préstamo]],DATE(YEAR(TODAY()),1,1),"m"),0),0) -> 0 | Z52: =IF(T_Prestamos[[#This Row],[Situación]]="Activos",IF(T_Prestamos[[#This Row],[Tipo préstamo]]="Americano",T_Prestamos[[#This Row],[Importe]]*T_Prestamos[[#This Row],[% interés ordinario]],-CUMIPMT(T_Prestamos[[#This Row],[% interés ordinario]]/12,T_Prestamos[[#This Row],[Años]]*12,T_Prestamos[[#This Row],[Importe]],T_Prestamos[[#This Row],[Primera cuota año]],T_Prestamos[[#This Row],[Primera cuota año]]+11,0)),0) -> 0 | AA52: =IF(T_Prestamos[[#This Row],[firma préstamo]]>DATE(YEAR(TODAY())-1,MONTH(TODAY()),DAY(TODAY())),T_Prestamos[[#This Row],[Importe]]*T_Prestamos[[#This Row],[% apertura]],0) -> 0
B53: 2050 | C53: Avanza - Calvia - Mallorca | D53: 45282 | E53: 2 | F53: 10000 | G53: 0.0974 | H53: =T_Prestamos[[#This Row],[% interés ordinario]]+3% -> 0.1274 | J53: =IF(T_Prestamos[[#This Row],[Garantía]]="","",T_Prestamos[[#This Row],[Pendiente]]/T_Prestamos[[#This Row],[Garantía]]) | K53: Jurídica | L53: Americano | M53: Avanza | N53: Cancelados | O53: 45615 | Q53: =IF(T_Prestamos[[#This Row],[Situación]]="Cancelados",T_Prestamos[[#This Row],[Fecha cancelación]],TODAY())-T_Prestamos[[#This Row],[firma préstamo]] -> 333 | R53: =IF(T_Prestamos[[#This Row],[Situación]]="Cancelada","",DATEDIF(T_Prestamos[[#This Row],[firma préstamo]],TODAY(),"m")) -> 26 | S53: =IF(T_Prestamos[[#This Row],[Situación]]="Cancelados",0,IF(T_Prestamos[[#This Row],[Tipo préstamo]]="Americano",T_Prestamos[[#This Row],[Importe]],T_Prestamos[[#This Row],[Importe]]+CUMPRINC(G53/12,E53*12,F53,1,R53,0))) -> 0 | T53: =IF(T_Prestamos[[#This Row],[Situación]]="Cancelados",0,IF(T_Prestamos[[#This Row],[Tipo préstamo]]="Americano",T_Prestamos[[#This Row],[Pendiente]]*T_Prestamos[[#This Row],[% interés ordinario]],-CUMIPMT(G53/12,E53*12,F53,R53,R53+11,0))) -> 0 | U53: 0 | V53: =T_Prestamos[[#This Row],[% apertura]]*T_Prestamos[[#This Row],[Importe]] -> 0 | Y53: =IF(T_Prestamos[[#This Row],[Situación]]="Activos",IF(T_Prestamos[[#This Row],[Tipo préstamo]]="Francés",DATEDIF(T_Prestamos[[#This Row],[firma préstamo]],DATE(YEAR(TODAY()),1,1),"m"),0),0) -> 0 | Z53: =IF(T_Prestamos[[#This Row],[Situación]]="Activos",IF(T_Prestamos[[#This Row],[Tipo préstamo]]="Americano",T_Prestamos[[#This Row],[Importe]]*T_Prestamos[[#This Row],[% interés ordinario]],-CUMIPMT(T_Prestamos[[#This Row],[% interés ordinario]]/12,T_Prestamos[[#This Row],[Años]]*12,T_Prestamos[[#This Row],[Importe]],T_Prestamos[[#This Row],[Primera cuota año]],T_Prestamos[[#This Row],[Primera cuota año]]+11,0)),0) -> 0 | AA53: =IF(T_Prestamos[[#This Row],[firma préstamo]]>DATE(YEAR(TODAY())-1,MONTH(TODAY()),DAY(TODAY())),T_Prestamos[[#This Row],[Importe]]*T_Prestamos[[#This Row],[% apertura]],0) -> 0
B54: 2051 | C54: Avanza - La Quinta - Marbella | D54: 45287 | E54: 2 | F54: 10000 | G54: 0.1128 | H54: =T_Prestamos[[#This Row],[% interés ordinario]]+3% -> 0.1428 | J54: =IF(T_Prestamos[[#This Row],[Garantía]]="","",T_Prestamos[[#This Row],[Pendiente]]/T_Prestamos[[#This Row],[Garantía]]) | K54: Jurídica | L54: Americano | M54: Avanza | N54: Cancelados | O54: 45733 | Q54: =IF(T_Prestamos[[#This Row],[Situación]]="Cancelados",T_Prestamos[[#This Row],[Fecha cancelación]],TODAY())-T_Prestamos[[#This Row],[firma préstamo]] -> 446 | R54: =IF(T_Prestamos[[#This Row],[Situación]]="Cancelada","",DATEDIF(T_Prestamos[[#This Row],[firma préstamo]],TODAY(),"m")) -> 26 | S54: =IF(T_Prestamos[[#This Row],[Situación]]="Cancelados",0,IF(T_Prestamos[[#This Row],[Tipo préstamo]]="Americano",T_Prestamos[[#This Row],[Importe]],T_Prestamos[[#This Row],[Importe]]+CUMPRINC(G54/12,E54*12,F54,1,R54,0))) -> 0 | T54: =IF(T_Prestamos[[#This Row],[Situación]]="Cancelados",0,IF(T_Prestamos[[#This Row],[Tipo préstamo]]="Americano",T_Prestamos[[#This Row],[Pendiente]]*T_Prestamos[[#This Row],[% interés ordinario]],-CUMIPMT(G54/12,E54*12,F54,R54,R54+11,0))) -> 0 | U54: 0 | V54: =T_Prestamos[[#This Row],[% apertura]]*T_Prestamos[[#This Row],[Importe]] -> 0 | Y54: =IF(T_Prestamos[[#This Row],[Situación]]="Activos",IF(T_Prestamos[[#This Row],[Tipo préstamo]]="Francés",DATEDIF(T_Prestamos[[#This Row],[firma préstamo]],DATE(YEAR(TODAY()),1,1),"m"),0),0) -> 0 | Z54: =IF(T_Prestamos[[#This Row],[Situación]]="Activos",IF(T_Prestamos[[#This Row],[Tipo préstamo]]="Americano",T_Prestamos[[#This Row],[Importe]]*T_Prestamos[[#This Row],[% interés ordinario]],-CUMIPMT(T_Prestamos[[#This Row],[% interés ordinario]]/12,T_Prestamos[[#This Row],[Años]]*12,T_Prestamos[[#This Row],[Importe]],T_Prestamos[[#This Row],[Primera cuota año]],T_Prestamos[[#This Row],[Primera cuota año]]+11,0)),0) -> 0 | AA54: =IF(T_Prestamos[[#This Row],[firma préstamo]]>DATE(YEAR(TODAY())-1,MONTH(TODAY()),DAY(TODAY())),T_Prestamos[[#This Row],[Importe]]*T_Prestamos[[#This Row],[% apertura]],0) -> 0
B55: 2053 | C55: Oropesa | D55: 45366 | E55: 5 | F55: 59745 | G55: 0.1095 | H55: =T_Prestamos[[#This Row],[% interés ordinario]]+3% -> 0.1395 | J55: =IF(T_Prestamos[[#This Row],[Garantía]]="","",T_Prestamos[[#This Row],[Pendiente]]/T_Prestamos[[#This Row],[Garantía]]) | K55: Jurídica | L55: Americano | M55: Kontactalia | N55: Cancelados | O55: 45684 | Q55: =IF(T_Prestamos[[#This Row],[Situación]]="Cancelados",T_Prestamos[[#This Row],[Fecha cancelación]],TODAY())-T_Prestamos[[#This Row],[firma préstamo]] -> 318 | R55: =IF(T_Prestamos[[#This Row],[Situación]]="Cancelada","",DATEDIF(T_Prestamos[[#This Row],[firma préstamo]],TODAY(),"m")) -> 24 | S55: =IF(T_Prestamos[[#This Row],[Situación]]="Cancelados",0,IF(T_Prestamos[[#This Row],[Tipo préstamo]]="Americano",T_Prestamos[[#This Row],[Importe]],T_Prestamos[[#This Row],[Importe]]+CUMPRINC(G55/12,E55*12,F55,1,R55,0))) -> 0 | T55: =IF(T_Prestamos[[#This Row],[Situación]]="Cancelados",0,IF(T_Prestamos[[#This Row],[Tipo préstamo]]="Americano",T_Prestamos[[#This Row],[Pendiente]]*T_Prestamos[[#This Row],[% interés ordinario]],-CUMIPMT(G55/12,E55*12,F55,R55,R55+11,0))) -> 0 | U55: 0.01 | V55: =T_Prestamos[[#This Row],[% apertura]]*T_Prestamos[[#This Row],[Importe]] -> 597.45 | X55: INVERSIONES ARANDA | Y55: =IF(T_Prestamos[[#This Row],[Situación]]="Activos",IF(T_Prestamos[[#This Row],[Tipo préstamo]]="Francés",DATEDIF(T_Prestamos[[#This Row],[firma préstamo]],DATE(YEAR(TODAY()),1,1),"m"),0),0) -> 0 | Z55: =IF(T_Prestamos[[#This Row],[Situación]]="Activos",IF(T_Prestamos[[#This Row],[Tipo préstamo]]="Americano",T_Prestamos[[#This Row],[Importe]]*T_Prestamos[[#This Row],[% interés ordinario]],-CUMIPMT(T_Prestamos[[#This Row],[% interés ordinario]]/12,T_Prestamos[[#This Row],[Años]]*12,T_Prestamos[[#This Row],[Importe]],T_Prestamos[[#This Row],[Primera cuota año]],T_Prestamos[[#This Row],[Primera cuota año]]+11,0)),0) -> 0 | AA55: =IF(T_Prestamos[[#This Row],[firma préstamo]]>DATE(YEAR(TODAY())-1,MONTH(TODAY()),DAY(TODAY())),T_Prestamos[[#This Row],[Importe]]*T_Prestamos[[#This Row],[% apertura]],0) -> 0
B56: 2054 | C56: Sierra Madrid | D56: 45366 | E56: 5 | F56: 118495 | G56: 0.1095 | H56: =T_Prestamos[[#This Row],[% interés ordinario]]+3% -> 0.1395 | J56: =IF(T_Prestamos[[#This Row],[Garantía]]="","",T_Prestamos[[#This Row],[Pendiente]]/T_Prestamos[[#This Row],[Garantía]]) | K56: Jurídica | L56: Americano | M56: Kontactalia | N56: Cancelados | O56: 45489 | Q56: =IF(T_Prestamos[[#This Row],[Situación]]="Cancelados",T_Prestamos[[#This Row],[Fecha cancelación]],TODAY())-T_Prestamos[[#This Row],[firma préstamo]] -> 123 | R56: =IF(T_Prestamos[[#This Row],[Situación]]="Cancelada","",DATEDIF(T_Prestamos[[#This Row],[firma préstamo]],TODAY(),"m")) -> 24 | S56: =IF(T_Prestamos[[#This Row],[Situación]]="Cancelados",0,IF(T_Prestamos[[#This Row],[Tipo préstamo]]="Americano",T_Prestamos[[#This Row],[Importe]],T_Prestamos[[#This Row],[Importe]]+CUMPRINC(G56/12,E56*12,F56,1,R56,0))) -> 0 | T56: =IF(T_Prestamos[[#This Row],[Situación]]="Cancelados",0,IF(T_Prestamos[[#This Row],[Tipo préstamo]]="Americano",T_Prestamos[[#This Row],[Pendiente]]*T_Prestamos[[#This Row],[% interés ordinario]],-CUMIPMT(G56/12,E56*12,F56,R56,R56+11,0))) -> 0 | U56: 0.01 | V56: =T_Prestamos[[#This Row],[% apertura]]*T_Prestamos[[#This Row],[Importe]] -> 1184.95 | X56: ACTI VIDA | Y56: =IF(T_Prestamos[[#This Row],[Situación]]="Activos",IF(T_Prestamos[[#This Row],[Tipo préstamo]]="Francés",DATEDIF(T_Prestamos[[#This Row],[firma préstamo]],DATE(YEAR(TODAY()),1,1),"m"),0),0) -> 0 | Z56: =IF(T_Prestamos[[#This Row],[Situación]]="Activos",IF(T_Prestamos[[#This Row],[Tipo préstamo]]="Americano",T_Prestamos[[#This Row],[Importe]]*T_Prestamos[[#This Row],[% interés ordinario]],-CUMIPMT(T_Prestamos[[#This Row],[% interés ordinario]]/12,T_Prestamos[[#This Row],[Años]]*12,T_Prestamos[[#This Row],[Importe]],T_Prestamos[[#This Row],[Primera cuota año]],T_Prestamos[[#This Row],[Primera cuota año]]+11,0)),0) -> 0 | AA56: =IF(T_Prestamos[[#This Row],[firma préstamo]]>DATE(YEAR(TODAY())-1,MONTH(TODAY()),DAY(TODAY())),T_Prestamos[[#This Row],[Importe]]*T_Prestamos[[#This Row],[% apertura]],0) -> 0
B57: 2055 | C57: Zona Franca | D57: 45385 | E57: 5 | F57: 110000 | G57: 0.1 | H57: =T_Prestamos[[#This Row],[% interés ordinario]]+3% -> 0.13 | I57: 280239 | J57: =IF(T_Prestamos[[#This Row],[Garantía]]="","",T_Prestamos[[#This Row],[Pendiente]]/T_Prestamos[[#This Row],[Garantía]]) -> 0.3925221 | K57: Jurídica | L57: Americano | M57: Five Rodri | N57: Activos | Q57: =IF(T_Prestamos[[#This Row],[Situación]]="Cancelados",T_Prestamos[[#This Row],[Fecha cancelación]],TODAY())-T_Prestamos[[#This Row],[firma préstamo]] -> 711 | R57: =IF(T_Prestamos[[#This Row],[Situación]]="Cancelada","",DATEDIF(T_Prestamos[[#This Row],[firma préstamo]],TODAY(),"m")) -> 23 | S57: =IF(T_Prestamos[[#This Row],[Situación]]="Cancelados",0,IF(T_Prestamos[[#This Row],[Tipo préstamo]]="Americano",T_Prestamos[[#This Row],[Importe]],T_Prestamos[[#This Row],[Importe]]+CUMPRINC(G57/12,E57*12,F57,1,R57,0))) -> 110000 | T57: =IF(T_Prestamos[[#This Row],[Situación]]="Cancelados",0,IF(T_Prestamos[[#This Row],[Tipo préstamo]]="Americano",T_Prestamos[[#This Row],[Pendiente]]*T_Prestamos[[#This Row],[% interés ordinario]],-CUMIPMT(G57/12,E57*12,F57,R57,R57+11,0))) -> 11000 | U57: 0.01 | V57: =T_Prestamos[[#This Row],[% apertura]]*T_Prestamos[[#This Row],[Importe]] -> 1100 | X57: FIVE RODRIS | Y57: =IF(T_Prestamos[[#This Row],[Situación]]="Activos",IF(T_Prestamos[[#This Row],[Tipo préstamo]]="Francés",DATEDIF(T_Prestamos[[#This Row],[firma préstamo]],DATE(YEAR(TODAY()),1,1),"m"),0),0) -> 0 | Z57: =IF(T_Prestamos[[#This Row],[Situación]]="Activos",IF(T_Prestamos[[#This Row],[Tipo préstamo]]="Americano",T_Prestamos[[#This Row],[Importe]]*T_Prestamos[[#This Row],[% interés ordinario]],-CUMIPMT(T_Prestamos[[#This Row],[% interés ordinario]]/12,T_Prestamos[[#This Row],[Años]]*12,T_Prestamos[[#This Row],[Importe]],T_Prestamos[[#This Row],[Primera cuota año]],T_Prestamos[[#This Row],[Primera cuota año]]+11,0)),0) -> 11000 | AA57: =IF(T_Prestamos[[#This Row],[firma préstamo]]>DATE(YEAR(TODAY())-1,MONTH(TODAY()),DAY(TODAY())),T_Prestamos[[#This Row],[Importe]]*T_Prestamos[[#This Row],[% apertura]],0) -> 0
B58: 2056 | C58: Parla 3 | D58: 45470 | E58: 10 | F58: 160000 | G58: 0.115 | H58: =T_Prestamos[[#This Row],[% interés ordinario]]+3% -> 0.145 | I58: 400639 | J58: =IF(T_Prestamos[[#This Row],[Garantía]]="","",T_Prestamos[[#This Row],[Pendiente]]/T_Prestamos[[#This Row],[Garantía]]) -> 0.39936202 | K58: Jurídica | L58: Americano | M58: Kontactalia | N58: Activos | Q58: =IF(T_Prestamos[[#This Row],[Situación]]="Cancelados",T_Prestamos[[#This Row],[Fecha cancelación]],TODAY())-T_Prestamos[[#This Row],[firma préstamo]] -> 626 | R58: =IF(T_Prestamos[[#This Row],[Situación]]="Cancelada","",DATEDIF(T_Prestamos[[#This Row],[firma préstamo]],TODAY(),"m")) -> 20 | S58: =IF(T_Prestamos[[#This Row],[Situación]]="Cancelados",0,IF(T_Prestamos[[#This Row],[Tipo préstamo]]="Americano",T_Prestamos[[#This Row],[Importe]],T_Prestamos[[#This Row],[Importe]]+CUMPRINC(G58/12,E58*12,F58,1,R58,0))) -> 160000 | T58: =IF(T_Prestamos[[#This Row],[Situación]]="Cancelados",0,IF(T_Prestamos[[#This Row],[Tipo préstamo]]="Americano",T_Prestamos[[#This Row],[Pendiente]]*T_Prestamos[[#This Row],[% interés ordinario]],-CUMIPMT(G58/12,E58*12,F58,R58,R58+11,0))) -> 18400 | U58: 0.01 | V58: =T_Prestamos[[#This Row],[% apertura]]*T_Prestamos[[#This Row],[Importe]] -> 1600 | X58: PROGELAN Y URBITEC | Y58: =IF(T_Prestamos[[#This Row],[Situación]]="Activos",IF(T_Prestamos[[#This Row],[Tipo préstamo]]="Francés",DATEDIF(T_Prestamos[[#This Row],[firma préstamo]],DATE(YEAR(TODAY()),1,1),"m"),0),0) -> 0 | Z58: =IF(T_Prestamos[[#This Row],[Situación]]="Activos",IF(T_Prestamos[[#This Row],[Tipo préstamo]]="Americano",T_Prestamos[[#This Row],[Importe]]*T_Prestamos[[#This Row],[% interés ordinario]],-CUMIPMT(T_Prestamos[[#This Row],[% interés ordinario]]/12,T_Prestamos[[#This Row],[Años]]*12,T_Prestamos[[#This Row],[Importe]],T_Prestamos[[#This Row],[Primera cuota año]],T_Prestamos[[#This Row],[Primera cuota año]]+11,0)),0) -> 18400 | AA58: =IF(T_Prestamos[[#This Row],[firma préstamo]]>DATE(YEAR(TODAY())-1,MONTH(TODAY()),DAY(TODAY())),T_Prestamos[[#This Row],[Importe]]*T_Prestamos[[#This Row],[% apertura]],0) -> 0
B59: 2057 | C59: Blanes | D59: 45561 | E59: 5 | F59: 114020 | G59: 0.1095 | H59: =T_Prestamos[[#This Row],[% interés ordinario]]+3% -> 0.1395 | I59: 327927 | J59: =IF(T_Prestamos[[#This Row],[Garantía]]="","",T_Prestamos[[#This Row],[Pendiente]]/T_Prestamos[[#This Row],[Garantía]]) -> 0.34769934 | K59: Jurídica | L59: Americano | M59: Kontactalia | N59: Activos | Q59: =IF(T_Prestamos[[#This Row],[Situación]]="Cancelados",T_Prestamos[[#This Row],[Fecha cancelación]],TODAY())-T_Prestamos[[#This Row],[firma préstamo]] -> 535 | R59: =IF(T_Prestamos[[#This Row],[Situación]]="Cancelada","",DATEDIF(T_Prestamos[[#This Row],[firma préstamo]],TODAY(),"m")) -> 17 | S59: =IF(T_Prestamos[[#This Row],[Situación]]="Cancelados",0,IF(T_Prestamos[[#This Row],[Tipo préstamo]]="Americano",T_Prestamos[[#This Row],[Importe]],T_Prestamos[[#This Row],[Importe]]+CUMPRINC(G59/12,E59*12,F59,1,R59,0))) -> 114020 | T59: =IF(T_Prestamos[[#This Row],[Situación]]="Cancelados",0,IF(T_Prestamos[[#This Row],[Tipo préstamo]]="Americano",T_Prestamos[[#This Row],[Pendiente]]*T_Prestamos[[#This Row],[% interés ordinario]],-CUMIPMT(G59/12,E59*12,F59,R59,R59+11,0))) -> 12485.19 | U59: 0.01 | V59: =T_Prestamos[[#This Row],[% apertura]]*T_Prestamos[[#This Row],[Importe]] -> 1140.2 | X59: QUANTUM ENERGY | Y59: =IF(T_Prestamos[[#This Row],[Situación]]="Activos",IF(T_Prestamos[[#This Row],[Tipo préstamo]]="Francés",DATEDIF(T_Prestamos[[#This Row],[firma préstamo]],DATE(YEAR(TODAY()),1,1),"m"),0),0) -> 0 | Z59: =IF(T_Prestamos[[#This Row],[Situación]]="Activos",IF(T_Prestamos[[#This Row],[Tipo préstamo]]="Americano",T_Prestamos[[#This Row],[Importe]]*T_Prestamos[[#This Row],[% interés ordinario]],-CUMIPMT(T_Prestamos[[#This Row],[% interés ordinario]]/12,T_Prestamos[[#This Row],[Años]]*12,T_Prestamos[[#This Row],[Importe]],T_Prestamos[[#This Row],[Primera cuota año]],T_Prestamos[[#This Row],[Primera cuota año]]+11,0)),0) -> 12485.19 | AA59: =IF(T_Prestamos[[#This Row],[firma préstamo]]>DATE(YEAR(TODAY())-1,MONTH(TODAY()),DAY(TODAY())),T_Prestamos[[#This Row],[Importe]]*T_Prestamos[[#This Row],[% apertura]],0) -> 0
B60: 2058 | C60: Avanza - Juan de Austria - Tarifa | D60: 45714 | E60: 2 | F60: 20000 | G60: 0.11 | H60: 0.17 | I60: =T_Prestamos[[#This Row],[Importe]]/39.53% -> 50594.485 | J60: =IF(T_Prestamos[[#This Row],[Garantía]]="","",T_Prestamos[[#This Row],[Pendiente]]/T_Prestamos[[#This Row],[Garantía]]) -> 0.3953 | K60: Jurídica | L60: Americano | M60: Avanza | N60: Activos | Q60: =IF(T_Prestamos[[#This Row],[Situación]]="Cancelados",T_Prestamos[[#This Row],[Fecha cancelación]],TODAY())-T_Prestamos[[#This Row],[firma préstamo]] -> 382 | R60: =IF(T_Prestamos[[#This Row],[Situación]]="Cancelada","",DATEDIF(T_Prestamos[[#This Row],[firma préstamo]],TODAY(),"m")) -> 12 | S60: =IF(T_Prestamos[[#This Row],[Situación]]="Cancelados",0,IF(T_Prestamos[[#This Row],[Tipo préstamo]]="Americano",T_Prestamos[[#This Row],[Importe]],T_Prestamos[[#This Row],[Importe]]+CUMPRINC(G60/12,E60*12,F60,1,R60,0))) -> 20000 | T60: =IF(T_Prestamos[[#This Row],[Situación]]="Cancelados",0,IF(T_Prestamos[[#This Row],[Tipo préstamo]]="Americano",T_Prestamos[[#This Row],[Pendiente]]*T_Prestamos[[#This Row],[% interés ordinario]],-CUMIPMT(G60/12,E60*12,F60,R60,R60+11,0))) -> 2200 | U60: 0 | V60: =T_Prestamos[[#This Row],[% apertura]]*T_Prestamos[[#This Row],[Importe]] -> 0 | Y60: =IF(T_Prestamos[[#This Row],[Situación]]="Activos",IF(T_Prestamos[[#This Row],[Tipo préstamo]]="Francés",DATEDIF(T_Prestamos[[#This Row],[firma préstamo]],DATE(YEAR(TODAY()),1,1),"m"),0),0) -> 0 | Z60: =IF(T_Prestamos[[#This Row],[Situación]]="Activos",IF(T_Prestamos[[#This Row],[Tipo préstamo]]="Americano",T_Prestamos[[#This Row],[Importe]]*T_Prestamos[[#This Row],[% interés ordinario]],-CUMIPMT(T_Prestamos[[#This Row],[% interés ordinario]]/12,T_Prestamos[[#This Row],[Años]]*12,T_Prestamos[[#This Row],[Importe]],T_Prestamos[[#This Row],[Primera cuota año]],T_Prestamos[[#This Row],[Primera cuota año]]+11,0)),0) -> 2200 | AA60: =IF(T_Prestamos[[#This Row],[firma préstamo]]>DATE(YEAR(TODAY())-1,MONTH(TODAY()),DAY(TODAY())),T_Prestamos[[#This Row],[Importe]]*T_Prestamos[[#This Row],[% apertura]],0) -> 0
B61: 2059 | C61: Avanza - Sant Andreu de Llavaneres - Barcelona | D61: 45709 | E61: 2 | F61: 20000 | G61: 0.11 | H61: 0.17 | I61: =T_Prestamos[[#This Row],[Importe]]/36.33% -> 55050.922 | J61: =IF(T_Prestamos[[#This Row],[Garantía]]="","",T_Prestamos[[#This Row],[Pendiente]]/T_Prestamos[[#This Row],[Garantía]]) -> 0.3633 | K61: Jurídica | L61: Americano | M61: Avanza | N61: Activos | Q61: =IF(T_Prestamos[[#This Row],[Situación]]="Cancelados",T_Prestamos[[#This Row],[Fecha cancelación]],TODAY())-T_Prestamos[[#This Row],[firma préstamo]] -> 387 | R61: =IF(T_Prestamos[[#This Row],[Situación]]="Cancelada","",DATEDIF(T_Prestamos[[#This Row],[firma préstamo]],TODAY(),"m")) -> 12 | S61: =IF(T_Prestamos[[#This Row],[Situación]]="Cancelados",0,IF(T_Prestamos[[#This Row],[Tipo préstamo]]="Americano",T_Prestamos[[#This Row],[Importe]],T_Prestamos[[#This Row],[Importe]]+CUMPRINC(G61/12,E61*12,F61,1,R61,0))) -> 20000 | T61: =IF(T_Prestamos[[#This Row],[Situación]]="Cancelados",0,IF(T_Prestamos[[#This Row],[Tipo préstamo]]="Americano",T_Prestamos[[#This Row],[Pendiente]]*T_Prestamos[[#This Row],[% interés ordinario]],-CUMIPMT(G61/12,E61*12,F61,R61,R61+11,0))) -> 2200 | U61: 0 | V61: =T_Prestamos[[#This Row],[% apertura]]*T_Prestamos[[#This Row],[Importe]] -> 0 | Y61: =IF(T_Prestamos[[#This Row],[Situación]]="Activos",IF(T_Prestamos[[#This Row],[Tipo préstamo]]="Francés",DATEDIF(T_Prestamos[[#This Row],[firma préstamo]],DATE(YEAR(TODAY()),1,1),"m"),0),0) -> 0 | Z61: =IF(T_Prestamos[[#This Row],[Situación]]="Activos",IF(T_Prestamos[[#This Row],[Tipo préstamo]]="Americano",T_Prestamos[[#This Row],[Importe]]*T_Prestamos[[#This Row],[% interés ordinario]],-CUMIPMT(T_Prestamos[[#This Row],[% interés ordinario]]/12,T_Prestamos[[#This Row],[Años]]*12,T_Prestamos[[#This Row],[Importe]],T_Prestamos[[#This Row],[Primera cuota año]],T_Prestamos[[#This Row],[Primera cuota año]]+11,0)),0) -> 2200 | AA61: =IF(T_Prestamos[[#This Row],[firma préstamo]]>DATE(YEAR(TODAY())-1,MONTH(TODAY()),DAY(TODAY())),T_Prestamos[[#This Row],[Importe]]*T_Prestamos[[#This Row],[% apertura]],0) -> 0
B62: 2060 | C62: Málaga 1 | D62: 45713 | E62: 5 | F62: 71940 | G62: 0.1095 | H62: =T_Prestamos[[#This Row],[% interés ordinario]]+3% -> 0.1395 | I62: 298382 | J62: =IF(T_Prestamos[[#This Row],[Garantía]]="","",T_Prestamos[[#This Row],[Pendiente]]/T_Prestamos[[#This Row],[Garantía]]) -> 0.24110033 | K62: Jurídica | L62: Americano | M62: Kontactalia | N62: Activos | Q62: =IF(T_Prestamos[[#This Row],[Situación]]="Cancelados",T_Prestamos[[#This Row],[Fecha cancelación]],TODAY())-T_Prestamos[[#This Row],[firma préstamo]] -> 383 | R62: =IF(T_Prestamos[[#This Row],[Situación]]="Cancelada","",DATEDIF(T_Prestamos[[#This Row],[firma préstamo]],TODAY(),"m")) -> 12 | S62: =IF(T_Prestamos[[#This Row],[Situación]]="Cancelados",0,IF(T_Prestamos[[#This Row],[Tipo préstamo]]="Americano",T_Prestamos[[#This Row],[Importe]],T_Prestamos[[#This Row],[Importe]]+CUMPRINC(G62/12,E62*12,F62,1,R62,0))) -> 71940 | T62: =IF(T_Prestamos[[#This Row],[Situación]]="Cancelados",0,IF(T_Prestamos[[#This Row],[Tipo préstamo]]="Americano",T_Prestamos[[#This Row],[Pendiente]]*T_Prestamos[[#This Row],[% interés ordinario]],-CUMIPMT(G62/12,E62*12,F62,R62,R62+11,0))) -> 7877.43 | U62: 0.01 | V62: =T_Prestamos[[#This Row],[% apertura]]*T_Prestamos[[#This Row],[Importe]] -> 719.4 | X62: LOOKING 4 PERFECTION | Y62: =IF(T_Prestamos[[#This Row],[Situación]]="Activos",IF(T_Prestamos[[#This Row],[Tipo préstamo]]="Francés",DATEDIF(T_Prestamos[[#This Row],[firma préstamo]],DATE(YEAR(TODAY()),1,1),"m"),0),0) -> 0 | Z62: =IF(T_Prestamos[[#This Row],[Situación]]="Activos",IF(T_Prestamos[[#This Row],[Tipo préstamo]]="Americano",T_Prestamos[[#This Row],[Importe]]*T_Prestamos[[#This Row],[% interés ordinario]],-CUMIPMT(T_Prestamos[[#This Row],[% interés ordinario]]/12,T_Prestamos[[#This Row],[Años]]*12,T_Prestamos[[#This Row],[Importe]],T_Prestamos[[#This Row],[Primera cuota año]],T_Prestamos[[#This Row],[Primera cuota año]]+11,0)),0) -> 7877.43 | AA62: =IF(T_Prestamos[[#This Row],[firma préstamo]]>DATE(YEAR(TODAY())-1,MONTH(TODAY()),DAY(TODAY())),T_Prestamos[[#This Row],[Importe]]*T_Prestamos[[#This Row],[% apertura]],0) -> 0
B63: 2061 | C63: Carabanchel | D63: 45742 | E63: 5 | F63: 143990 | G63: 0.1095 | H63: =T_Prestamos[[#This Row],[% interés ordinario]]+3% -> 0.1395 | I63: 335500 | J63: =IF(T_Prestamos[[#This Row],[Garantía]]="","",T_Prestamos[[#This Row],[Pendiente]]/T_Prestamos[[#This Row],[Garantía]]) -> 0.42918033 | K63: Jurídica | L63: Americano | M63: Kontactalia | N63: Activos | Q63: =IF(T_Prestamos[[#This Row],[Situación]]="Cancelados",T_Prestamos[[#This Row],[Fecha cancelación]],TODAY())-T_Prestamos[[#This Row],[firma préstamo]] -> 354 | R63: =IF(T_Prestamos[[#This Row],[Situación]]="Cancelada","",DATEDIF(T_Prestamos[[#This Row],[firma préstamo]],TODAY(),"m")) -> 11 | S63: =IF(T_Prestamos[[#This Row],[Situación]]="Cancelados",0,IF(T_Prestamos[[#This Row],[Tipo préstamo]]="Americano",T_Prestamos[[#This Row],[Importe]],T_Prestamos[[#This Row],[Importe]]+CUMPRINC(G63/12,E63*12,F63,1,R63,0))) -> 143990 | T63: =IF(T_Prestamos[[#This Row],[Situación]]="Cancelados",0,IF(T_Prestamos[[#This Row],[Tipo préstamo]]="Americano",T_Prestamos[[#This Row],[Pendiente]]*T_Prestamos[[#This Row],[% interés ordinario]],-CUMIPMT(G63/12,E63*12,F63,R63,R63+11,0))) -> 15766.905 | U63: 0.01 | V63: =T_Prestamos[[#This Row],[% apertura]]*T_Prestamos[[#This Row],[Importe]] -> 1439.9 | X63: MAS MADRID | Y63: =IF(T_Prestamos[[#This Row],[Situación]]="Activos",IF(T_Prestamos[[#This Row],[Tipo préstamo]]="Francés",DATEDIF(T_Prestamos[[#This Row],[firma préstamo]],DATE(YEAR(TODAY()),1,1),"m"),0),0) -> 0 | Z63: =IF(T_Prestamos[[#This Row],[Situación]]="Activos",IF(T_Prestamos[[#This Row],[Tipo préstamo]]="Americano",T_Prestamos[[#This Row],[Importe]]*T_Prestamos[[#This Row],[% interés ordinario]],-CUMIPMT(T_Prestamos[[#This Row],[% interés ordinario]]/12,T_Prestamos[[#This Row],[Años]]*12,T_Prestamos[[#This Row],[Importe]],T_Prestamos[[#This Row],[Primera cuota año]],T_Prestamos[[#This Row],[Primera cuota año]]+11,0)),0) -> 15766.905 | AA63: =IF(T_Prestamos[[#This Row],[firma préstamo]]>DATE(YEAR(TODAY())-1,MONTH(TODAY()),DAY(TODAY())),T_Prestamos[[#This Row],[Importe]]*T_Prestamos[[#This Row],[% apertura]],0) -> 1439.9
B64: 2062 | C64: Málaga 2 | D64: 45791 | E64: 5 | F64: 398880 | G64: 0.1095 | H64: =T_Prestamos[[#This Row],[% interés ordinario]]+3% -> 0.1395 | I64: 1202665 | J64: =IF(T_Prestamos[[#This Row],[Garantía]]="","",T_Prestamos[[#This Row],[Pendiente]]/T_Prestamos[[#This Row],[Garantía]]) -> 0.33166343 | K64: Jurídica | L64: Americano | M64: Kontactalia | N64: Activos | Q64: =IF(T_Prestamos[[#This Row],[Situación]]="Cancelados",T_Prestamos[[#This Row],[Fecha cancelación]],TODAY())-T_Prestamos[[#This Row],[firma préstamo]] -> 305 | R64: =IF(T_Prestamos[[#This Row],[Situación]]="Cancelada","",DATEDIF(T_Prestamos[[#This Row],[firma préstamo]],TODAY(),"m")) -> 10 | S64: =IF(T_Prestamos[[#This Row],[Situación]]="Cancelados",0,IF(T_Prestamos[[#This Row],[Tipo préstamo]]="Americano",T_Prestamos[[#This Row],[Importe]],T_Prestamos[[#This Row],[Importe]]+CUMPRINC(G64/12,E64*12,F64,1,R64,0))) -> 398880 | T64: =IF(T_Prestamos[[#This Row],[Situación]]="Cancelados",0,IF(T_Prestamos[[#This Row],[Tipo préstamo]]="Americano",T_Prestamos[[#This Row],[Pendiente]]*T_Prestamos[[#This Row],[% interés ordinario]],-CUMIPMT(G64/12,E64*12,F64,R64,R64+11,0))) -> 43677.36 | U64: 0.01 | V64: =T_Prestamos[[#This Row],[% apertura]]*T_Prestamos[[#This Row],[Importe]] -> 3988.8 | X64: LOOKING 4 PERFECTION | Y64: =IF(T_Prestamos[[#This Row],[Situación]]="Activos",IF(T_Prestamos[[#This Row],[Tipo préstamo]]="Francés",DATEDIF(T_Prestamos[[#This Row],[firma préstamo]],DATE(YEAR(TODAY()),1,1),"m"),0),0) -> 0 | Z64: =IF(T_Prestamos[[#This Row],[Situación]]="Activos",IF(T_Prestamos[[#This Row],[Tipo préstamo]]="Americano",T_Prestamos[[#This Row],[Importe]]*T_Prestamos[[#This Row],[% interés ordinario]],-CUMIPMT(T_Prestamos[[#This Row],[% interés ordinario]]/12,T_Prestamos[[#This Row],[Años]]*12,T_Prestamos[[#This Row],[Importe]],T_Prestamos[[#This Row],[Primera cuota año]],T_Prestamos[[#This Row],[Primera cuota año]]+11,0)),0) -> 43677.36 | AA64: =IF(T_Prestamos[[#This Row],[firma préstamo]]>DATE(YEAR(TODAY())-1,MONTH(TODAY()),DAY(TODAY())),T_Prestamos[[#This Row],[Importe]]*T_Prestamos[[#This Row],[% apertura]],0) -> 3988.8
B65: 2063 | C65: Mallorca | D65: 45853 | E65: 5 | F65: 167150 | G65: 0.115 | H65: =T_Prestamos[[#This Row],[% interés ordinario]]+3% -> 0.145 | I65: 2106785 | J65: =IF(T_Prestamos[[#This Row],[Garantía]]="","",T_Prestamos[[#This Row],[Pendiente]]/T_Prestamos[[#This Row],[Garantía]]) -> 0.079338898 | K65: Jurídica | L65: Americano | M65: Fueslo Partners | N65: Activos | Q65: =IF(T_Prestamos[[#This Row],[Situación]]="Cancelados",T_Prestamos[[#This Row],[Fecha cancelación]],TODAY())-T_Prestamos[[#This Row],[firma préstamo]] -> 243 | R65: =IF(T_Prestamos[[#This Row],[Situación]]="Cancelada","",DATEDIF(T_Prestamos[[#This Row],[firma préstamo]],TODAY(),"m")) -> 8 | S65: =IF(T_Prestamos[[#This Row],[Situación]]="Cancelados",0,IF(T_Prestamos[[#This Row],[Tipo préstamo]]="Americano",T_Prestamos[[#This Row],[Importe]],T_Prestamos[[#This Row],[Importe]]+CUMPRINC(G65/12,E65*12,F65,1,R65,0))) -> 167150 | T65: =IF(T_Prestamos[[#This Row],[Situación]]="Cancelados",0,IF(T_Prestamos[[#This Row],[Tipo préstamo]]="Americano",T_Prestamos[[#This Row],[Pendiente]]*T_Prestamos[[#This Row],[% interés ordinario]],-CUMIPMT(G65/12,E65*12,F65,R65,R65+11,0))) -> 19222.25 | U65: 0.01 | V65: =T_Prestamos[[#This Row],[% apertura]]*T_Prestamos[[#This Row],[Importe]] -> 1671.5 | X65: JAIDI INVERSIONES | Y65: =IF(T_Prestamos[[#This Row],[Situación]]="Activos",IF(T_Prestamos[[#This Row],[Tipo préstamo]]="Francés",DATEDIF(T_Prestamos[[#This Row],[firma préstamo]],DATE(YEAR(TODAY()),1,1),"m"),0),0) -> 0 | Z65: =IF(T_Prestamos[[#This Row],[Situación]]="Activos",IF(T_Prestamos[[#This Row],[Tipo préstamo]]="Americano",T_Prestamos[[#This Row],[Importe]]*T_Prestamos[[#This Row],[% interés ordinario]],-CUMIPMT(T_Prestamos[[#This Row],[% interés ordinario]]/12,T_Prestamos[[#This Row],[Años]]*12,T_Prestamos[[#This Row],[Importe]],T_Prestamos[[#This Row],[Primera cuota año]],T_Prestamos[[#This Row],[Primera cuota año]]+11,0)),0) -> 19222.25 | AA65: =IF(T_Prestamos[[#This Row],[firma préstamo]]>DATE(YEAR(TODAY())-1,MONTH(TODAY()),DAY(TODAY())),T_Prestamos[[#This Row],[Importe]]*T_Prestamos[[#This Row],[% apertura]],0) -> 1671.5
B66: 2064 | C66: Parla 4 | D66: 45860 | E66: 10 | F66: 162220 | G66: 0.115 | H66: =T_Prestamos[[#This Row],[% interés ordinario]]+3% -> 0.145 | I66: 427170 | J66: =IF(T_Prestamos[[#This Row],[Garantía]]="","",T_Prestamos[[#This Row],[Pendiente]]/T_Prestamos[[#This Row],[Garantía]]) -> 0.37975513 | K66: Jurídica | L66: Americano | M66: Kontactalia | N66: Activos | Q66: =IF(T_Prestamos[[#This Row],[Situación]]="Cancelados",T_Prestamos[[#This Row],[Fecha cancelación]],TODAY())-T_Prestamos[[#This Row],[firma préstamo]] -> 236 | R66: =IF(T_Prestamos[[#This Row],[Situación]]="Cancelada","",DATEDIF(T_Prestamos[[#This Row],[firma préstamo]],TODAY(),"m")) -> 7 | S66: =IF(T_Prestamos[[#This Row],[Situación]]="Cancelados",0,IF(T_Prestamos[[#This Row],[Tipo préstamo]]="Americano",T_Prestamos[[#This Row],[Importe]],T_Prestamos[[#This Row],[Importe]]+CUMPRINC(G66/12,E66*12,F66,1,R66,0))) -> 162220 | T66: =IF(T_Prestamos[[#This Row],[Situación]]="Cancelados",0,IF(T_Prestamos[[#This Row],[Tipo préstamo]]="Americano",T_Prestamos[[#This Row],[Pendiente]]*T_Prestamos[[#This Row],[% interés ordinario]],-CUMIPMT(G66/12,E66*12,F66,R66,R66+11,0))) -> 18655.3 | U66: 0.01 | V66: =T_Prestamos[[#This Row],[% apertura]]*T_Prestamos[[#This Row],[Importe]] -> 1622.2 | X66: PROGELAN Y URBITEC | Y66: =IF(T_Prestamos[[#This Row],[Situación]]="Activos",IF(T_Prestamos[[#This Row],[Tipo préstamo]]="Francés",DATEDIF(T_Prestamos[[#This Row],[firma préstamo]],DATE(YEAR(TODAY()),1,1),"m"),0),0) -> 0 | Z66: =IF(T_Prestamos[[#This Row],[Situación]]="Activos",IF(T_Prestamos[[#This Row],[Tipo préstamo]]="Americano",T_Prestamos[[#This Row],[Importe]]*T_Prestamos[[#This Row],[% interés ordinario]],-CUMIPMT(T_Prestamos[[#This Row],[% interés ordinario]]/12,T_Prestamos[[#This Row],[Años]]*12,T_Prestamos[[#This Row],[Importe]],T_Prestamos[[#This Row],[Primera cuota año]],T_Prestamos[[#This Row],[Primera cuota año]]+11,0)),0) -> 18655.3 | AA66: =IF(T_Prestamos[[#This Row],[firma préstamo]]>DATE(YEAR(TODAY())-1,MONTH(TODAY()),DAY(TODAY())),T_Prestamos[[#This Row],[Importe]]*T_Prestamos[[#This Row],[% apertura]],0) -> 1622.2
B67: 2065 | C67: Málaga 3 | D67: 45961 | E67: 5 | F67: 139760 | G67: 0.115 | H67: =T_Prestamos[[#This Row],[% interés ordinario]]+3% -> 0.145 | I67: 350766 | J67: =IF(T_Prestamos[[#This Row],[Garantía]]="","",T_Prestamos[[#This Row],[Pendiente]]/T_Prestamos[[#This Row],[Garantía]]) -> 0.39844227 | K67: Jurídica | L67: Americano | M67: Kontactalia | N67: Activos | Q67: =IF(T_Prestamos[[#This Row],[Situación]]="Cancelados",T_Prestamos[[#This Row],[Fecha cancelación]],TODAY())-T_Prestamos[[#This Row],[firma préstamo]] -> 135 | R67: =IF(T_Prestamos[[#This Row],[Situación]]="Cancelada","",DATEDIF(T_Prestamos[[#This Row],[firma préstamo]],TODAY(),"m")) -> 4 | S67: =IF(T_Prestamos[[#This Row],[Situación]]="Cancelados",0,IF(T_Prestamos[[#This Row],[Tipo préstamo]]="Americano",T_Prestamos[[#This Row],[Importe]],T_Prestamos[[#This Row],[Importe]]+CUMPRINC(G67/12,E67*12,F67,1,R67,0))) -> 139760 | T67: =IF(T_Prestamos[[#This Row],[Situación]]="Cancelados",0,IF(T_Prestamos[[#This Row],[Tipo préstamo]]="Americano",T_Prestamos[[#This Row],[Pendiente]]*T_Prestamos[[#This Row],[% interés ordinario]],-CUMIPMT(G67/12,E67*12,F67,R67,R67+11,0))) -> 16072.4 | U67: 0.02 | V67: =T_Prestamos[[#This Row],[% apertura]]*T_Prestamos[[#This Row],[Importe]] -> 2795.2 | X67: LOOKING 4 PERFECTION | Y67: =IF(T_Prestamos[[#This Row],[Situación]]="Activos",IF(T_Prestamos[[#This Row],[Tipo préstamo]]="Francés",DATEDIF(T_Prestamos[[#This Row],[firma préstamo]],DATE(YEAR(TODAY()),1,1),"m"),0),0) -> 0 | Z67: =IF(T_Prestamos[[#This Row],[Situación]]="Activos",IF(T_Prestamos[[#This Row],[Tipo préstamo]]="Americano",T_Prestamos[[#This Row],[Importe]]*T_Prestamos[[#This Row],[% interés ordinario]],-CUMIPMT(T_Prestamos[[#This Row],[% interés ordinario]]/12,T_Prestamos[[#This Row],[Años]]*12,T_Prestamos[[#This Row],[Importe]],T_Prestamos[[#This Row],[Primera cuota año]],T_Prestamos[[#This Row],[Primera cuota año]]+11,0)),0) -> 16072.4 | AA67: =IF(T_Prestamos[[#This Row],[firma préstamo]]>DATE(YEAR(TODAY())-1,MONTH(TODAY()),DAY(TODAY())),T_Prestamos[[#This Row],[Importe]]*T_Prestamos[[#This Row],[% apertura]],0) -> 2795.2
B68: 2066 | C68: Almería | D68: 46001 | E68: 3 | F68: 176950 | G68: 0.11 | H68: =T_Prestamos[[#This Row],[% interés ordinario]]+3% -> 0.14 | I68: 495721 | J68: =IF(T_Prestamos[[#This Row],[Garantía]]="","",T_Prestamos[[#This Row],[Pendiente]]/T_Prestamos[[#This Row],[Garantía]]) -> 0.35695482 | K68: Jurídica | L68: Americano | M68: Barnacredit | N68: Activos | Q68: =IF(T_Prestamos[[#This Row],[Situación]]="Cancelados",T_Prestamos[[#This Row],[Fecha cancelación]],TODAY())-T_Prestamos[[#This Row],[firma préstamo]] -> 95 | R68: =IF(T_Prestamos[[#This Row],[Situación]]="Cancelada","",DATEDIF(T_Prestamos[[#This Row],[firma préstamo]],TODAY(),"m")) -> 3 | S68: =IF(T_Prestamos[[#This Row],[Situación]]="Cancelados",0,IF(T_Prestamos[[#This Row],[Tipo préstamo]]="Americano",T_Prestamos[[#This Row],[Importe]],T_Prestamos[[#This Row],[Importe]]+CUMPRINC(G68/12,E68*12,F68,1,R68,0))) -> 176950 | T68: =IF(T_Prestamos[[#This Row],[Situación]]="Cancelados",0,IF(T_Prestamos[[#This Row],[Tipo préstamo]]="Americano",T_Prestamos[[#This Row],[Pendiente]]*T_Prestamos[[#This Row],[% interés ordinario]],-CUMIPMT(G68/12,E68*12,F68,R68,R68+11,0))) -> 19464.5 | U68: 0.0175 | V68: =T_Prestamos[[#This Row],[% apertura]]*T_Prestamos[[#This Row],[Importe]] -> 3096.625 | X68: INMOBILIARIA BENARES PERTÍN | Y68: =IF(T_Prestamos[[#This Row],[Situación]]="Activos",IF(T_Prestamos[[#This Row],[Tipo préstamo]]="Francés",DATEDIF(T_Prestamos[[#This Row],[firma préstamo]],DATE(YEAR(TODAY()),1,1),"m"),0),0) -> 0 | Z68: =IF(T_Prestamos[[#This Row],[Situación]]="Activos",IF(T_Prestamos[[#This Row],[Tipo préstamo]]="Americano",T_Prestamos[[#This Row],[Importe]]*T_Prestamos[[#This Row],[% interés ordinario]],-CUMIPMT(T_Prestamos[[#This Row],[% interés ordinario]]/12,T_Prestamos[[#This Row],[Años]]*12,T_Prestamos[[#This Row],[Importe]],T_Prestamos[[#This Row],[Primera cuota año]],T_Prestamos[[#This Row],[Primera cuota año]]+11,0)),0) -> 19464.5 | AA68: =IF(T_Prestamos[[#This Row],[firma préstamo]]>DATE(YEAR(TODAY())-1,MONTH(TODAY()),DAY(TODAY())),T_Prestamos[[#This Row],[Importe]]*T_Prestamos[[#This Row],[% apertura]],0) -> 3096.625
B69: 2067 | C69: Casares | D69: 46009 | E69: 3 | F69: 549900 | G69: 0.115 | H69: =T_Prestamos[[#This Row],[% interés ordinario]]+3% -> 0.145 | I69: 2483971.8 | J69: =IF(T_Prestamos[[#This Row],[Garantía]]="","",T_Prestamos[[#This Row],[Pendiente]]/T_Prestamos[[#This Row],[Garantía]]) -> 0.22137932 | K69: Jurídica | L69: Americano | M69: Kontactalia | N69: Activos | Q69: =IF(T_Prestamos[[#This Row],[Situación]]="Cancelados",T_Prestamos[[#This Row],[Fecha cancelación]],TODAY())-T_Prestamos[[#This Row],[firma préstamo]] -> 87 | R69: =IF(T_Prestamos[[#This Row],[Situación]]="Cancelada","",DATEDIF(T_Prestamos[[#This Row],[firma préstamo]],TODAY(),"m")) -> 2 | S69: =IF(T_Prestamos[[#This Row],[Situación]]="Cancelados",0,IF(T_Prestamos[[#This Row],[Tipo préstamo]]="Americano",T_Prestamos[[#This Row],[Importe]],T_Prestamos[[#This Row],[Importe]]+CUMPRINC(G69/12,E69*12,F69,1,R69,0))) -> 549900 | T69: =IF(T_Prestamos[[#This Row],[Situación]]="Cancelados",0,IF(T_Prestamos[[#This Row],[Tipo préstamo]]="Americano",T_Prestamos[[#This Row],[Pendiente]]*T_Prestamos[[#This Row],[% interés ordinario]],-CUMIPMT(G69/12,E69*12,F69,R69,R69+11,0))) -> 63238.5 | U69: 0.02 | V69: =T_Prestamos[[#This Row],[% apertura]]*T_Prestamos[[#This Row],[Importe]] -> 10998 | X69: TYR INVESTMENT PARTNER | Y69: =IF(T_Prestamos[[#This Row],[Situación]]="Activos",IF(T_Prestamos[[#This Row],[Tipo préstamo]]="Francés",DATEDIF(T_Prestamos[[#This Row],[firma préstamo]],DATE(YEAR(TODAY()),1,1),"m"),0),0) -> 0 | Z69: =IF(T_Prestamos[[#This Row],[Situación]]="Activos",IF(T_Prestamos[[#This Row],[Tipo préstamo]]="Americano",T_Prestamos[[#This Row],[Importe]]*T_Prestamos[[#This Row],[% interés ordinario]],-CUMIPMT(T_Prestamos[[#This Row],[% interés ordinario]]/12,T_Prestamos[[#This Row],[Años]]*12,T_Prestamos[[#This Row],[Importe]],T_Prestamos[[#This Row],[Primera cuota año]],T_Prestamos[[#This Row],[Primera cuota año]]+11,0)),0) -> 63238.5 | AA69: =IF(T_Prestamos[[#This Row],[firma préstamo]]>DATE(YEAR(TODAY())-1,MONTH(TODAY()),DAY(TODAY())),T_Prestamos[[#This Row],[Importe]]*T_Prestamos[[#This Row],[% apertura]],0) -> 10998

Sheet Tabla Partícipes
B2: CC CCPP | C2: Nombre CCPP
B3: 2201 | C3: EXPORTEN
B4: 2202 | C4: Jaume Marcos Domenech
B5: 2203 | C5: José Cosculluela
B6: 2204 | C6: 1151 INVERSIONES, SL
B7: 2205 | C7: Xavier Riart
B8: 2206 | C8: PRESTAPRO CAPITAL, SL

Sheet Tabla Participación CCPP
B2: Participación por CCPP
B3: CC Prestataria | C3: Prestatario | D3: Importe préstamo | E3: CC CCPP | F3: CCPP | G3: Importe | H3: Participación | I3: Fecha firma | J3: Situación | K3: % Gestión | L3: Gestión | M3: Intereses | N3: Apertura | O3: Apertura LTM | P3: Garantía
B4: 2042 | C4: =VLOOKUP(T_Participaciones[[#This Row],[CC Prestataria]],T_Prestamos[#Data],2) -> Parla 2 | D4: =SUMIFS(T_Prestamos[Importe],T_Prestamos[Centro coste],T_Participaciones[[#This Row],[CC Prestataria]]) -> 107425 | E4: 2201 | F4: =VLOOKUP(T_Participaciones[[#This Row],[CC CCPP]],T_Participes[#Data],2) -> EXPORTEN | G4: 30000 | H4: =T_Participaciones[[#This Row],[Importe]]/T_Participaciones[[#This Row],[Importe préstamo]] -> 0.2792646 | I4: 45448 | J4: Activa | K4: 0.02 | L4: =T_Participaciones[[#This Row],[% Gestión]]*T_Participaciones[[#This Row],[Importe]] -> 600 | M4: =SUMIFS(T_Prestamos[Int. Anual],T_Prestamos[Centro coste],T_Participaciones[[#This Row],[CC Prestataria]])*T_Participaciones[[#This Row],[Participación]] -> 3285 | N4: 0 | O4: =IF(T_Participaciones[[#This Row],[Fecha firma]]>DATE(YEAR(TODAY())-1,MONTH(TODAY()),DAY(TODAY())),T_Participaciones[[#This Row],[Importe]]*T_Participaciones[[#This Row],[Apertura]],0) -> 0 | P4: =VLOOKUP(T_Participaciones[[#This Row],[CC Prestataria]],T_Prestamos[],'Tabla Préstamos'!$I$2,FALSE)*T_Participaciones[[#This Row],[Participación]]*IF(T_Participaciones[[#This Row],[Situación]]="Cancelada",0,1) -> 66145.357
B5: 2047 | C5: =VLOOKUP(T_Participaciones[[#This Row],[CC Prestataria]],T_Prestamos[#Data],2) -> Jerez | D5: =SUMIFS(T_Prestamos[Importe],T_Prestamos[Centro coste],T_Participaciones[[#This Row],[CC Prestataria]]) -> 124595 | E5: 2201 | F5: =VLOOKUP(T_Participaciones[[#This Row],[CC CCPP]],T_Participes[#Data],2) -> EXPORTEN | G5: 35000 | H5: =T_Participaciones[[#This Row],[Importe]]/T_Participaciones[[#This Row],[Importe préstamo]] -> 0.28091015 | I5: 45448 | J5: Cancelada | K5: 0.02 | L5: =T_Participaciones[[#This Row],[% Gestión]]*T_Participaciones[[#This Row],[Importe]] -> 700 | M5: =SUMIFS(T_Prestamos[Int. Anual],T_Prestamos[Centro coste],T_Participaciones[[#This Row],[CC Prestataria]])*T_Participaciones[[#This Row],[Participación]] -> 0 | N5: 0 | O5: =IF(T_Participaciones[[#This Row],[Fecha firma]]>DATE(YEAR(TODAY())-1,MONTH(TODAY()),DAY(TODAY())),T_Participaciones[[#This Row],[Importe]]*T_Participaciones[[#This Row],[Apertura]],0) -> 0 | P5: =VLOOKUP(T_Participaciones[[#This Row],[CC Prestataria]],T_Prestamos[],'Tabla Préstamos'!$I$2,FALSE)*T_Participaciones[[#This Row],[Participación]]*IF(T_Participaciones[[#This Row],[Situación]]="Cancelada",0,1) -> 0
B6: 2053 | C6: =VLOOKUP(T_Participaciones[[#This Row],[CC Prestataria]],T_Prestamos[#Data],2) -> Oropesa | D6: =SUMIFS(T_Prestamos[Importe],T_Prestamos[Centro coste],T_Participaciones[[#This Row],[CC Prestataria]]) -> 59745 | E6: 2201 | F6: =VLOOKUP(T_Participaciones[[#This Row],[CC CCPP]],T_Participes[#Data],2) -> EXPORTEN | G6: 30000 | H6: =T_Participaciones[[#This Row],[Importe]]/T_Participaciones[[#This Row],[Importe préstamo]] -> 0.50213407 | I6: 45448 | J6: Cancelada | K6: 0.02 | L6: =T_Participaciones[[#This Row],[% Gestión]]*T_Participaciones[[#This Row],[Importe]] -> 600 | M6: =SUMIFS(T_Prestamos[Int. Anual],T_Prestamos[Centro coste],T_Participaciones[[#This Row],[CC Prestataria]])*T_Participaciones[[#This Row],[Participación]] -> 0 | N6: 0 | O6: =IF(T_Participaciones[[#This Row],[Fecha firma]]>DATE(YEAR(TODAY())-1,MONTH(TODAY()),DAY(TODAY())),T_Participaciones[[#This Row],[Importe]]*T_Participaciones[[#This Row],[Apertura]],0) -> 0 | P6: =VLOOKUP(T_Participaciones[[#This Row],[CC Prestataria]],T_Prestamos[],'Tabla Préstamos'!$I$2,FALSE)*T_Participaciones[[#This Row],[Participación]]*IF(T_Participaciones[[#This Row],[Situación]]="Cancelada",0,1) -> 0
B7: 2054 | C7: =VLOOKUP(T_Participaciones[[#This Row],[CC Prestataria]],T_Prestamos[#Data],2) -> Sierra Madrid | D7: =SUMIFS(T_Prestamos[Importe],T_Prestamos[Centro coste],T_Participaciones[[#This Row],[CC Prestataria]]) -> 118495 | E7: 2201 | F7: =VLOOKUP(T_Participaciones[[#This Row],[CC CCPP]],T_Participes[#Data],2) -> EXPORTEN | G7: 35000 | H7: =T_Participaciones[[#This Row],[Importe]]/T_Participaciones[[#This Row],[Importe préstamo]] -> 0.29537111 | I7: 45448 | J7: Cancelada | K7: 0.02 | L7: =T_Participaciones[[#This Row],[% Gestión]]*T_Participaciones[[#This Row],[Importe]] -> 700 | M7: =SUMIFS(T_Prestamos[Int. Anual],T_Prestamos[Centro coste],T_Participaciones[[#This Row],[CC Prestataria]])*T_Participaciones[[#This Row],[Participación]] -> 0 | N7: 0 | O7: =IF(T_Participaciones[[#This Row],[Fecha firma]]>DATE(YEAR(TODAY())-1,MONTH(TODAY()),DAY(TODAY())),T_Participaciones[[#This Row],[Importe]]*T_Participaciones[[#This Row],[Apertura]],0) -> 0 | P7: =VLOOKUP(T_Participaciones[[#This Row],[CC Prestataria]],T_Prestamos[],'Tabla Préstamos'!$I$2,FALSE)*T_Participaciones[[#This Row],[Participación]]*IF(T_Participaciones[[#This Row],[Situación]]="Cancelada",0,1) -> 0
B8: 2056 | C8: =VLOOKUP(T_Participaciones[[#This Row],[CC Prestataria]],T_Prestamos[#Data],2) -> Parla 3 | D8: =SUMIFS(T_Prestamos[Importe],T_Prestamos[Centro coste],T_Participaciones[[#This Row],[CC Prestataria]]) -> 160000 | E8: 2201 | F8: =VLOOKUP(T_Participaciones[[#This Row],[CC CCPP]],T_Participes[#Data],2) -> EXPORTEN | G8: 30000 | H8: =T_Participaciones[[#This Row],[Importe]]/T_Participaciones[[#This Row],[Importe préstamo]] -> 0.1875 | I8: 45470 | J8: Activa | K8: 0.02 | L8: =T_Participaciones[[#This Row],[% Gestión]]*T_Participaciones[[#This Row],[Importe]] -> 600 | M8: =SUMIFS(T_Prestamos[Int. Anual],T_Prestamos[Centro coste],T_Participaciones[[#This Row],[CC Prestataria]])*T_Participaciones[[#This Row],[Participación]] -> 3450 | N8: 0 | O8: =IF(T_Participaciones[[#This Row],[Fecha firma]]>DATE(YEAR(TODAY())-1,MONTH(TODAY()),DAY(TODAY())),T_Participaciones[[#This Row],[Importe]]*T_Participaciones[[#This Row],[Apertura]],0) -> 0 | P8: =VLOOKUP(T_Participaciones[[#This Row],[CC Prestataria]],T_Prestamos[],'Tabla Préstamos'!$I$2,FALSE)*T_Participaciones[[#This Row],[Participación]]*IF(T_Participaciones[[#This Row],[Situación]]="Cancelada",0,1) -> 75119.812
B9: 2057 | C9: =VLOOKUP(T_Participaciones[[#This Row],[CC Prestataria]],T_Prestamos[#Data],2) -> Blanes | D9: =SUMIFS(T_Prestamos[Importe],T_Prestamos[Centro coste],T_Participaciones[[#This Row],[CC Prestataria]]) -> 114020 | E9: 2201 | F9: =VLOOKUP(T_Participaciones[[#This Row],[CC CCPP]],T_Participes[#Data],2) -> EXPORTEN | G9: 55000 | H9: =T_Participaciones[[#This Row],[Importe]]/T_Participaciones[[#This Row],[Importe préstamo]] -> 0.48237151 | I9: 45561 | J9: Activa | K9: 0.02 | L9: =T_Participaciones[[#This Row],[% Gestión]]*T_Participaciones[[#This Row],[Importe]] -> 1100 | M9: =SUMIFS(T_Prestamos[Int. Anual],T_Prestamos[Centro coste],T_Participaciones[[#This Row],[CC Prestataria]])*T_Participaciones[[#This Row],[Participación]] -> 6022.5 | N9: 0 | O9: =IF(T_Participaciones[[#This Row],[Fecha firma]]>DATE(YEAR(TODAY())-1,MONTH(TODAY()),DAY(TODAY())),T_Participaciones[[#This Row],[Importe]]*T_Participaciones[[#This Row],[Apertura]],0) -> 0 | P9: =VLOOKUP(T_Participaciones[[#This Row],[CC Prestataria]],T_Prestamos[],'Tabla Préstamos'!$I$2,FALSE)*T_Participaciones[[#This Row],[Participación]]*IF(T_Participaciones[[#This Row],[Situación]]="Cancelada",0,1) -> 158182.64
B10: 2057 | C10: =VLOOKUP(T_Participaciones[[#This Row],[CC Prestataria]],T_Prestamos[#Data],2) -> Blanes | D10: =SUMIFS(T_Prestamos[Importe],T_Prestamos[Centro coste],T_Participaciones[[#This Row],[CC Prestataria]]) -> 114020 | E10: 2202 | F10: =VLOOKUP(T_Participaciones[[#This Row],[CC CCPP]],T_Participes[#Data],2) -> Jaume Marcos Domenech | G10: 12500 | H10: =T_Participaciones[[#This Row],[Importe]]/T_Participaciones[[#This Row],[Importe préstamo]] -> 0.10962989 | I10: 45593 | J10: Activa | K10: 0.02 | L10: =T_Participaciones[[#This Row],[% Gestión]]*T_Participaciones[[#This Row],[Importe]] -> 250 | M10: =SUMIFS(T_Prestamos[Int. Anual],T_Prestamos[Centro coste],T_Participaciones[[#This Row],[CC Prestataria]])*T_Participaciones[[#This Row],[Participación]] -> 1368.75 | N10: 0 | O10: =IF(T_Participaciones[[#This Row],[Fecha firma]]>DATE(YEAR(TODAY())-1,MONTH(TODAY()),DAY(TODAY())),T_Participaciones[[#This Row],[Importe]]*T_Participaciones[[#This Row],[Apertura]],0) -> 0 | P10: =VLOOKUP(T_Participaciones[[#This Row],[CC Prestataria]],T_Prestamos[],'Tabla Préstamos'!$I$2,FALSE)*T_Participaciones[[#This Row],[Participación]]*IF(T_Participaciones[[#This Row],[Situación]]="Cancelada",0,1) -> 35950.601
B11: 2047 | C11: =VLOOKUP(T_Participaciones[[#This Row],[CC Prestataria]],T_Prestamos[#Data],2) -> Jerez | D11: =SUMIFS(T_Prestamos[Importe],T_Prestamos[Centro coste],T_Participaciones[[#This Row],[CC Prestataria]]) -> 124595 | E11: 2202 | F11: =VLOOKUP(T_Participaciones[[#This Row],[CC CCPP]],T_Participes[#Data],2) -> Jaume Marcos Domenech | G11: 12500 | H11: =T_Participaciones[[#This Row],[Importe]]/T_Participaciones[[#This Row],[Importe préstamo]] -> 0.10032505 | I11: 45587 | J11: Cancelada | K11: 0.02 | L11: =T_Participaciones[[#This Row],[% Gestión]]*T_Participaciones[[#This Row],[Importe]] -> 250 | M11: =SUMIFS(T_Prestamos[Int. Anual],T_Prestamos[Centro coste],T_Participaciones[[#This Row],[CC Prestataria]])*T_Participaciones[[#This Row],[Participación]] -> 0 | N11: 0 | O11: =IF(T_Participaciones[[#This Row],[Fecha firma]]>DATE(YEAR(TODAY())-1,MONTH(TODAY()),DAY(TODAY())),T_Participaciones[[#This Row],[Importe]]*T_Participaciones[[#This Row],[Apertura]],0) -> 0 | P11: =VLOOKUP(T_Participaciones[[#This Row],[CC Prestataria]],T_Prestamos[],'Tabla Préstamos'!$I$2,FALSE)*T_Participaciones[[#This Row],[Participación]]*IF(T_Participaciones[[#This Row],[Situación]]="Cancelada",0,1) -> 0
B12: 2053 | C12: =VLOOKUP(T_Participaciones[[#This Row],[CC Prestataria]],T_Prestamos[#Data],2) -> Oropesa | D12: =SUMIFS(T_Prestamos[Importe],T_Prestamos[Centro coste],T_Participaciones[[#This Row],[CC Prestataria]]) -> 59745 | E12: 2202 | F12: =VLOOKUP(T_Participaciones[[#This Row],[CC CCPP]],T_Participes[#Data],2) -> Jaume Marcos Domenech | G12: 12500 | H12: =T_Participaciones[[#This Row],[Importe]]/T_Participaciones[[#This Row],[Importe préstamo]] -> 0.20922253 | I12: 45587 | J12: Cancelada | K12: 0.02 | L12: =T_Participaciones[[#This Row],[% Gestión]]*T_Participaciones[[#This Row],[Importe]] -> 250 | M12: =SUMIFS(T_Prestamos[Int. Anual],T_Prestamos[Centro coste],T_Participaciones[[#This Row],[CC Prestataria]])*T_Participaciones[[#This Row],[Participación]] -> 0 | N12: 0 | O12: =IF(T_Participaciones[[#This Row],[Fecha firma]]>DATE(YEAR(TODAY())-1,MONTH(TODAY()),DAY(TODAY())),T_Participaciones[[#This Row],[Importe]]*T_Participaciones[[#This Row],[Apertura]],0) -> 0 | P12: =VLOOKUP(T_Participaciones[[#This Row],[CC Prestataria]],T_Prestamos[],'Tabla Préstamos'!$I$2,FALSE)*T_Participaciones[[#This Row],[Participación]]*IF(T_Participaciones[[#This Row],[Situación]]="Cancelada",0,1) -> 0
B13: 2056 | C13: =VLOOKUP(T_Participaciones[[#This Row],[CC Prestataria]],T_Prestamos[#Data],2) -> Parla 3 | D13: =SUMIFS(T_Prestamos[Importe],T_Prestamos[Centro coste],T_Participaciones[[#This Row],[CC Prestataria]]) -> 160000 | E13: 2202 | F13: =VLOOKUP(T_Participaciones[[#This Row],[CC CCPP]],T_Participes[#Data],2) -> Jaume Marcos Domenech | G13: 12500 | H13: =T_Participaciones[[#This Row],[Importe]]/T_Participaciones[[#This Row],[Importe préstamo]] -> 0.078125 | I13: 45587 | J13: Activa | K13: 0.02 | L13: =T_Participaciones[[#This Row],[% Gestión]]*T_Participaciones[[#This Row],[Importe]] -> 250 | M13: =SUMIFS(T_Prestamos[Int. Anual],T_Prestamos[Centro coste],T_Participaciones[[#This Row],[CC Prestataria]])*T_Participaciones[[#This Row],[Participación]] -> 1437.5 | N13: 0 | O13: =IF(T_Participaciones[[#This Row],[Fecha firma]]>DATE(YEAR(TODAY())-1,MONTH(TODAY()),DAY(TODAY())),T_Participaciones[[#This Row],[Importe]]*T_Participaciones[[#This Row],[Apertura]],0) -> 0 | P13: =VLOOKUP(T_Participaciones[[#This Row],[CC Prestataria]],T_Prestamos[],'Tabla Préstamos'!$I$2,FALSE)*T_Participaciones[[#This Row],[Participación]]*IF(T_Participaciones[[#This Row],[Situación]]="Cancelada",0,1) -> 31299.922
B14: 2060 | C14: =VLOOKUP(T_Participaciones[[#This Row],[CC Prestataria]],T_Prestamos[#Data],2) -> Málaga 1 | D14: =SUMIFS(T_Prestamos[Importe],T_Prestamos[Centro coste],T_Participaciones[[#This Row],[CC Prestataria]]) -> 71940 | E14: 2202 | F14: =VLOOKUP(T_Participaciones[[#This Row],[CC CCPP]],T_Participes[#Data],2) -> Jaume Marcos Domenech | G14: 12500 | H14: =T_Participaciones[[#This Row],[Importe]]/T_Participaciones[[#This Row],[Importe préstamo]] -> 0.17375591 | I14: 45742 | J14: Activa | K14: 0.02 | L14: =T_Participaciones[[#This Row],[% Gestión]]*T_Participaciones[[#This Row],[Importe]] -> 250 | M14: =SUMIFS(T_Prestamos[Int. Anual],T_Prestamos[Centro coste],T_Participaciones[[#This Row],[CC Prestataria]])*T_Participaciones[[#This Row],[Participación]] -> 1368.75 | N14: 0 | O14: =IF(T_Participaciones[[#This Row],[Fecha firma]]>DATE(YEAR(TODAY())-1,MONTH(TODAY()),DAY(TODAY())),T_Participaciones[[#This Row],[Importe]]*T_Participaciones[[#This Row],[Apertura]],0) -> 0 | P14: =VLOOKUP(T_Participaciones[[#This Row],[CC Prestataria]],T_Prestamos[],'Tabla Préstamos'!$I$2,FALSE)*T_Participaciones[[#This Row],[Participación]]*IF(T_Participaciones[[#This Row],[Situación]]="Cancelada",0,1) -> 51845.635
B15: 2061 | C15: =VLOOKUP(T_Participaciones[[#This Row],[CC Prestataria]],T_Prestamos[#Data],2) -> Carabanchel | D15: =SUMIFS(T_Prestamos[Importe],T_Prestamos[Centro coste],T_Participaciones[[#This Row],[CC Prestataria]]) -> 143990 | E15: 2202 | F15: =VLOOKUP(T_Participaciones[[#This Row],[CC CCPP]],T_Participes[#Data],2) -> Jaume Marcos Domenech | G15: 12500 | H15: =T_Participaciones[[#This Row],[Importe]]/T_Participaciones[[#This Row],[Importe préstamo]] -> 0.086811584 | I15: 45742 | J15: Activa | K15: 0.02 | L15: =T_Participaciones[[#This Row],[% Gestión]]*T_Participaciones[[#This Row],[Importe]] -> 250 | M15: =SUMIFS(T_Prestamos[Int. Anual],T_Prestamos[Centro coste],T_Participaciones[[#This Row],[CC Prestataria]])*T_Participaciones[[#This Row],[Participación]] -> 1368.75 | N15: 0 | O15: =IF(T_Participaciones[[#This Row],[Fecha firma]]>DATE(YEAR(TODAY())-1,MONTH(TODAY()),DAY(TODAY())),T_Participaciones[[#This Row],[Importe]]*T_Participaciones[[#This Row],[Apertura]],0) -> 0 | P15: =VLOOKUP(T_Participaciones[[#This Row],[CC Prestataria]],T_Prestamos[],'Tabla Préstamos'!$I$2,FALSE)*T_Participaciones[[#This Row],[Participación]]*IF(T_Participaciones[[#This Row],[Situación]]="Cancelada",0,1) -> 29125.286
... B28: 2065 | C28: =VLOOKUP(T_Participaciones[[#This Row],[CC Prestataria]],T_Prestamos[#Data],2) -> Málaga 3 | D28: =SUMIFS(T_Prestamos[Importe],T_Prestamos[Centro coste],T_Participaciones[[#This Row],[CC Prestataria]]) -> 139760 | E28: 2204 | F28: =VLOOKUP(T_Participaciones[[#This Row],[CC CCPP]],T_Participes[#Data],2) -> 1151 INVERSIONES, SL | G28: 40000 | H28: =T_Participaciones[[#This Row],[Importe]]/T_Participaciones[[#This Row],[Importe préstamo]] -> 0.28620492 | I28: 45961 | J28: Activa | K28: 0.02 | L28: =T_Participaciones[[#This Row],[% Gestión]]*T_Participaciones[[#This Row],[Importe]] -> 800 | M28: =SUMIFS(T_Prestamos[Int. Anual],T_Prestamos[Centro coste],T_Participaciones[[#This Row],[CC Prestataria]])*T_Participaciones[[#This Row],[Participación]] -> 4600 | N28: 0 | O28: =IF(T_Participaciones[[#This Row],[Fecha firma]]>DATE(YEAR(TODAY())-1,MONTH(TODAY()),DAY(TODAY())),T_Participaciones[[#This Row],[Importe]]*T_Participaciones[[#This Row],[Apertura]],0) -> 0 | P28: =VLOOKUP(T_Participaciones[[#This Row],[CC Prestataria]],T_Prestamos[],'Tabla Préstamos'!$I$2,FALSE)*T_Participaciones[[#This Row],[Participación]]*IF(T_Participaciones[[#This Row],[Situación]]="Cancelada",0,1) -> 100390.96
B29: 2062 | C29: =VLOOKUP(T_Participaciones[[#This Row],[CC Prestataria]],T_Prestamos[#Data],2) -> Málaga 2 | D29: =SUMIFS(T_Prestamos[Importe],T_Prestamos[Centro coste],T_Participaciones[[#This Row],[CC Prestataria]]) -> 398880 | E29: 2205 | F29: =VLOOKUP(T_Participaciones[[#This Row],[CC CCPP]],T_Participes[#Data],2) -> Xavier Riart | G29: 30000 | H29: =T_Participaciones[[#This Row],[Importe]]/T_Participaciones[[#This Row],[Importe préstamo]] -> 0.07521059 | I29: 45971 | J29: Activa | K29: 0.02 | L29: =T_Participaciones[[#This Row],[% Gestión]]*T_Participaciones[[#This Row],[Importe]] -> 600 | M29: =SUMIFS(T_Prestamos[Int. Anual],T_Prestamos[Centro coste],T_Participaciones[[#This Row],[CC Prestataria]])*T_Participaciones[[#This Row],[Participación]] -> 3285 | N29: 0 | O29: =IF(T_Participaciones[[#This Row],[Fecha firma]]>DATE(YEAR(TODAY())-1,MONTH(TODAY()),DAY(TODAY())),T_Participaciones[[#This Row],[Importe]]*T_Participaciones[[#This Row],[Apertura]],0) -> 0 | P29: =VLOOKUP(T_Participaciones[[#This Row],[CC Prestataria]],T_Prestamos[],'Tabla Préstamos'!$I$2,FALSE)*T_Participaciones[[#This Row],[Participación]]*IF(T_Participaciones[[#This Row],[Situación]]="Cancelada",0,1) -> 90453.144 | W29: =450000-65000+30000 -> 415000
B30: 2063 | C30: =VLOOKUP(T_Participaciones[[#This Row],[CC Prestataria]],T_Prestamos[#Data],2) -> Mallorca | D30: =SUMIFS(T_Prestamos[Importe],T_Prestamos[Centro coste],T_Participaciones[[#This Row],[CC Prestataria]]) -> 167150 | E30: 2205 | F30: =VLOOKUP(T_Participaciones[[#This Row],[CC CCPP]],T_Participes[#Data],2) -> Xavier Riart | G30: 25000 | H30: =T_Participaciones[[#This Row],[Importe]]/T_Participaciones[[#This Row],[Importe préstamo]] -> 0.14956626 | I30: 45971 | J30: Activa | K30: 0.02 | L30: =T_Participaciones[[#This Row],[% Gestión]]*T_Participaciones[[#This Row],[Importe]] -> 500 | M30: =SUMIFS(T_Prestamos[Int. Anual],T_Prestamos[Centro coste],T_Participaciones[[#This Row],[CC Prestataria]])*T_Participaciones[[#This Row],[Participación]] -> 2875 | N30: 0 | O30: =IF(T_Participaciones[[#This Row],[Fecha firma]]>DATE(YEAR(TODAY())-1,MONTH(TODAY()),DAY(TODAY())),T_Participaciones[[#This Row],[Importe]]*T_Participaciones[[#This Row],[Apertura]],0) -> 0 | P30: =VLOOKUP(T_Participaciones[[#This Row],[CC Prestataria]],T_Prestamos[],'Tabla Préstamos'!$I$2,FALSE)*T_Participaciones[[#This Row],[Participación]]*IF(T_Participaciones[[#This Row],[Situación]]="Cancelada",0,1) -> 315103.95
B31: 2061 | C31: =VLOOKUP(T_Participaciones[[#This Row],[CC Prestataria]],T_Prestamos[#Data],2) -> Carabanchel | D31: =SUMIFS(T_Prestamos[Importe],T_Prestamos[Centro coste],T_Participaciones[[#This Row],[CC Prestataria]]) -> 143990 | E31: 2205 | F31: =VLOOKUP(T_Participaciones[[#This Row],[CC CCPP]],T_Participes[#Data],2) -> Xavier Riart | G31: 15000 | H31: =T_Participaciones[[#This Row],[Importe]]/T_Participaciones[[#This Row],[Importe préstamo]] -> 0.1041739 | I31: 45971 | J31: Activa | K31: 0.02 | L31: =T_Participaciones[[#This Row],[% Gestión]]*T_Participaciones[[#This Row],[Importe]] -> 300 | M31: =SUMIFS(T_Prestamos[Int. Anual],T_Prestamos[Centro coste],T_Participaciones[[#This Row],[CC Prestataria]])*T_Participaciones[[#This Row],[Participación]] -> 1642.5 | N31: 0 | O31: =IF(T_Participaciones[[#This Row],[Fecha firma]]>DATE(YEAR(TODAY())-1,MONTH(TODAY()),DAY(TODAY())),T_Participaciones[[#This Row],[Importe]]*T_Participaciones[[#This Row],[Apertura]],0) -> 0 | P31: =VLOOKUP(T_Participaciones[[#This Row],[CC Prestataria]],T_Prestamos[],'Tabla Préstamos'!$I$2,FALSE)*T_Participaciones[[#This Row],[Participación]]*IF(T_Participaciones[[#This Row],[Situación]]="Cancelada",0,1) -> 34950.344
B32: 2066 | C32: =VLOOKUP(T_Participaciones[[#This Row],[CC Prestataria]],T_Prestamos[#Data],2) -> Almería | D32: =SUMIFS(T_Prestamos[Importe],T_Prestamos[Centro coste],T_Participaciones[[#This Row],[CC Prestataria]]) -> 176950 | E32: 2201 | F32: =VLOOKUP(T_Participaciones[[#This Row],[CC CCPP]],T_Participes[#Data],2) -> EXPORTEN | G32: 130000 | H32: =T_Participaciones[[#This Row],[Importe]]/T_Participaciones[[#This Row],[Importe préstamo]] -> 0.73467081 | I32: 46001 | J32: Activa | K32: 0.02 | L32: =T_Participaciones[[#This Row],[% Gestión]]*T_Participaciones[[#This Row],[Importe]] -> 2600 | M32: =SUMIFS(T_Prestamos[Int. Anual],T_Prestamos[Centro coste],T_Participaciones[[#This Row],[CC Prestataria]])*T_Participaciones[[#This Row],[Participación]] -> 14300 | N32: 0 | O32: =IF(T_Participaciones[[#This Row],[Fecha firma]]>DATE(YEAR(TODAY())-1,MONTH(TODAY()),DAY(TODAY())),T_Participaciones[[#This Row],[Importe]]*T_Participaciones[[#This Row],[Apertura]],0) -> 0 | P32: =VLOOKUP(T_Participaciones[[#This Row],[CC Prestataria]],T_Prestamos[],'Tabla Préstamos'!$I$2,FALSE)*T_Participaciones[[#This Row],[Participación]]*IF(T_Participaciones[[#This Row],[Situación]]="Cancelada",0,1) -> 364191.75
B33: 2066 | C33: =VLOOKUP(T_Participaciones[[#This Row],[CC Prestataria]],T_Prestamos[#Data],2) -> Almería | D33: =SUMIFS(T_Prestamos[Importe],T_Prestamos[Centro coste],T_Participaciones[[#This Row],[CC Prestataria]]) -> 176950 | E33: 2205 | F33: =VLOOKUP(T_Participaciones[[#This Row],[CC CCPP]],T_Participes[#Data],2) -> Xavier Riart | G33: 30000 | H33: =T_Participaciones[[#This Row],[Importe]]/T_Participaciones[[#This Row],[Importe préstamo]] -> 0.16953942 | I33: 46001 | J33: Activa | K33: 0.02 | L33: =T_Participaciones[[#This Row],[% Gestión]]*T_Participaciones[[#This Row],[Importe]] -> 600 | M33: =SUMIFS(T_Prestamos[Int. Anual],T_Prestamos[Centro coste],T_Participaciones[[#This Row],[CC Prestataria]])*T_Participaciones[[#This Row],[Participación]] -> 3300 | N33: 0 | O33: =IF(T_Participaciones[[#This Row],[Fecha firma]]>DATE(YEAR(TODAY())-1,MONTH(TODAY()),DAY(TODAY())),T_Participaciones[[#This Row],[Importe]]*T_Participaciones[[#This Row],[Apertura]],0) -> 0 | P33: =VLOOKUP(T_Participaciones[[#This Row],[CC Prestataria]],T_Prestamos[],'Tabla Préstamos'!$I$2,FALSE)*T_Participaciones[[#This Row],[Participación]]*IF(T_Participaciones[[#This Row],[Situación]]="Cancelada",0,1) -> 84044.25
B34: 2067 | C34: =VLOOKUP(T_Participaciones[[#This Row],[CC Prestataria]],T_Prestamos[#Data],2) -> Casares | D34: =SUMIFS(T_Prestamos[Importe],T_Prestamos[Centro coste],T_Participaciones[[#This Row],[CC Prestataria]]) -> 549900 | E34: 2201 | F34: =VLOOKUP(T_Participaciones[[#This Row],[CC CCPP]],T_Participes[#Data],2) -> EXPORTEN | G34: 250000 | H34: =T_Participaciones[[#This Row],[Importe]]/T_Participaciones[[#This Row],[Importe préstamo]] -> 0.45462811 | I34: 46009 | J34: Activa | K34: 0.02 | L34: =T_Participaciones[[#This Row],[% Gestión]]*T_Participaciones[[#This Row],[Importe]] -> 5000 | M34: =SUMIFS(T_Prestamos[Int. Anual],T_Prestamos[Centro coste],T_Participaciones[[#This Row],[CC Prestataria]])*T_Participaciones[[#This Row],[Participación]] -> 28750 | N34: 0 | O34: =IF(T_Participaciones[[#This Row],[Fecha firma]]>DATE(YEAR(TODAY())-1,MONTH(TODAY()),DAY(TODAY())),T_Participaciones[[#This Row],[Importe]]*T_Participaciones[[#This Row],[Apertura]],0) -> 0 | P34: =VLOOKUP(T_Participaciones[[#This Row],[CC Prestataria]],T_Prestamos[],'Tabla Préstamos'!$I$2,FALSE)*T_Participaciones[[#This Row],[Participación]]*IF(T_Participaciones[[#This Row],[Situación]]="Cancelada",0,1) -> 1129283.4
B35: 2067 | C35: =VLOOKUP(T_Participaciones[[#This Row],[CC Prestataria]],T_Prestamos[#Data],2) -> Casares | D35: =SUMIFS(T_Prestamos[Importe],T_Prestamos[Centro coste],T_Participaciones[[#This Row],[CC Prestataria]]) -> 549900 | E35: 2206 | F35: =VLOOKUP(T_Participaciones[[#This Row],[CC CCPP]],T_Participes[#Data],2) -> PRESTAPRO CAPITAL, SL | G35: 50000 | H35: =T_Participaciones[[#This Row],[Importe]]/T_Participaciones[[#This Row],[Importe préstamo]] -> 0.090925623 | I35: 46009 | J35: Activa | K35: 0 | L35: =T_Participaciones[[#This Row],[% Gestión]]*T_Participaciones[[#This Row],[Importe]] -> 0 | M35: =SUMIFS(T_Prestamos[Int. Anual],T_Prestamos[Centro coste],T_Participaciones[[#This Row],[CC Prestataria]])*T_Participaciones[[#This Row],[Participación]] -> 5750 | N35: 0.02 | O35: =IF(T_Participaciones[[#This Row],[Fecha firma]]>DATE(YEAR(TODAY())-1,MONTH(TODAY()),DAY(TODAY())),T_Participaciones[[#This Row],[Importe]]*T_Participaciones[[#This Row],[Apertura]],0) -> 1000 | P35: =VLOOKUP(T_Participaciones[[#This Row],[CC Prestataria]],T_Prestamos[],'Tabla Préstamos'!$I$2,FALSE)*T_Participaciones[[#This Row],[Participación]]*IF(T_Participaciones[[#This Row],[Situación]]="Cancelada",0,1) -> 225856.68
B37: Esta tabla se usa en la confección de presupuestos
B38: Importante que se refleje la realidad en cuanto a los préstamos activos, las fechas de caducidad
B39: Sólo se importarán los centros con número
G41: =G32+G34+#REF! -> #REF!
